{"lastUpdated": "2025-05-26T00:58:44Z", "data": [
  {
    "name": "Kraum, Ludevic's Opus / Tymna the Weaver",
    "conversionRate": 0.37823275862068967,
    "metaShare": 0.04782765551718807
  },
  {
    "name": "Kinnan, Bonder Prodigy",
    "conversionRate": 0.24583333333333332,
    "metaShare": 0.03710766376333557
  },
  {
    "name": "Thrasios, Triton Hero / Tymna the Weaver",
    "conversionRate": 0.2995658465991317,
    "metaShare": 0.03561304952842344
  },
  {
    "name": "Rograkh, Son of Rohgahh / Thrasios, Triton Hero",
    "conversionRate": 0.31648936170212766,
    "metaShare": 0.01937844663196413
  },
  {
    "name": "Sisay, Weatherlight Captain",
    "conversionRate": 0.3394495412844037,
    "metaShare": 0.01685306395918157
  },
  {
    "name": "Magda, Brazen Outlaw",
    "conversionRate": 0.25165562913907286,
    "metaShare": 0.01556460341184353
  },
  {
    "name": "Rograkh, Son of Rohgahh / Silas Renn, Seeker Adept",
    "conversionRate": 0.3377049180327869,
    "metaShare": 0.015719218677524096
  },
  {
    "name": "Hashaton, Scarab's Fist",
    "conversionRate": 0.2015810276679842,
    "metaShare": 0.01303922073906097
  },
  {
    "name": "Glarb, Calamity's Augur",
    "conversionRate": 0.2301255230125523,
    "metaShare": 0.012317682832551666
  },
  {
    "name": "Tivit, Seller of Secrets",
    "conversionRate": 0.2683982683982684,
    "metaShare": 0.011905375457403495
  },
  {
    "name": "Yuriko, the Tiger's Shadow",
    "conversionRate": 0.19158878504672897,
    "metaShare": 0.011029222285213627
  },
  {
    "name": "Malcolm, Keen-Eyed Navigator / Vial Smasher the Fierce",
    "conversionRate": 0.24848484848484848,
    "metaShare": 0.008503839612431067
  },
  {
    "name": "Derevi, Empyrial Tactician",
    "conversionRate": 0.33783783783783783,
    "metaShare": 0.0076276864402412
  },
  {
    "name": "Najeela, the Blade-Blossom",
    "conversionRate": 0.22058823529411764,
    "metaShare": 0.007009225377518941
  },
  {
    "name": "Ob Nixilis, Captive Kingpin",
    "conversionRate": 0.21804511278195488,
    "metaShare": 0.006854610111838376
  },
  {
    "name": "Etali, Primal Conqueror // Etali, Primal Sickness",
    "conversionRate": 0.2903225806451613,
    "metaShare": 0.006390764314796681
  },
  {
    "name": "Marneus Calgar",
    "conversionRate": 0.3178294573643411,
    "metaShare": 0.006648456424264289
  },
  {
    "name": "Kenrith, the Returned King",
    "conversionRate": 0.29457364341085274,
    "metaShare": 0.006648456424264289
  },
  {
    "name": "Stella Lee, Wild Card",
    "conversionRate": 0.21311475409836064,
    "metaShare": 0.006287687471009638
  },
  {
    "name": "Tayam, Luminous Enigma",
    "conversionRate": 0.2627118644067797,
    "metaShare": 0.006081533783435551
  },
  {
    "name": "Atraxa, Grand Unifier",
    "conversionRate": 0.2627118644067797,
    "metaShare": 0.006081533783435551
  },
  {
    "name": "Dihada, Binder of Wills",
    "conversionRate": 0.2159090909090909,
    "metaShare": 0.0045353811266299025
  },
  {
    "name": "Tevesh Szat, Doom of Fools / Thrasios, Triton Hero",
    "conversionRate": 0.3409090909090909,
    "metaShare": 0.0045353811266299025
  },
  {
    "name": "Lumra, Bellow of the Woods",
    "conversionRate": 0.2808988764044944,
    "metaShare": 0.004586919548523424
  },
  {
    "name": "Urza, Lord High Artificer",
    "conversionRate": 0.1038961038961039,
    "metaShare": 0.003968458485801165
  },
  {
    "name": "Malcolm, Keen-Eyed Navigator / Tymna the Weaver",
    "conversionRate": 0.2375,
    "metaShare": 0.00412307375148173
  },
  {
    "name": "Krark, the Thumbless / Sakashima of a Thousand Faces",
    "conversionRate": 0.2235294117647059,
    "metaShare": 0.004380765860949338
  },
  {
    "name": "Inalla, Archmage Ritualist",
    "conversionRate": 0.325,
    "metaShare": 0.00412307375148173
  },
  {
    "name": "K'rrik, Son of Yawgmoth",
    "conversionRate": 0.1625,
    "metaShare": 0.00412307375148173
  },
  {
    "name": "Thrasios, Triton Hero / Yoshimaru, Ever Faithful",
    "conversionRate": 0.35714285714285715,
    "metaShare": 0.004329227439055816
  },
  {
    "name": "Rocco, Cabaretti Caterer",
    "conversionRate": 0.35135135135135137,
    "metaShare": 0.0038138432201206
  },
  {
    "name": "Talion, the Kindly Lord",
    "conversionRate": 0.22535211267605634,
    "metaShare": 0.003659227954440035
  },
  {
    "name": "Heliod, the Radiant Dawn // Heliod, the Warped Eclipse",
    "conversionRate": 0.3783783783783784,
    "metaShare": 0.0038138432201206
  },
  {
    "name": "Ral, Monsoon Mage // Ral, Leyline Prodigy",
    "conversionRate": 0.4782608695652174,
    "metaShare": 0.003556151110652992
  },
  {
    "name": "Loot, the Pathfinder",
    "conversionRate": 0.2,
    "metaShare": 0.003349997423078905
  },
  {
    "name": "Flubs, the Fool",
    "conversionRate": 0.22388059701492538,
    "metaShare": 0.0034530742668659486
  },
  {
    "name": "Kediss, Emberclaw Familiar / Malcolm, Keen-Eyed Navigator",
    "conversionRate": 0.1746031746031746,
    "metaShare": 0.0032469205792918622
  },
  {
    "name": "Winota, Joiner of Forces",
    "conversionRate": 0.19672131147540983,
    "metaShare": 0.003143843735504819
  },
  {
    "name": "The Gitrog Monster",
    "conversionRate": 0.2545454545454545,
    "metaShare": 0.002834613204143689
  },
  {
    "name": "The Master of Keys",
    "conversionRate": 0.19230769230769232,
    "metaShare": 0.0026799979384631244
  },
  {
    "name": "Ellivere of the Wild Court",
    "conversionRate": 0.23076923076923078,
    "metaShare": 0.0026799979384631244
  },
  {
    "name": "Shorikai, Genesis Engine",
    "conversionRate": 0.16666666666666666,
    "metaShare": 0.0024738442508890376
  },
  {
    "name": "Rakdos, the Muscle",
    "conversionRate": 0.2653061224489796,
    "metaShare": 0.0025253826727825593
  },
  {
    "name": "Elsha of the Infinite",
    "conversionRate": 0.24,
    "metaShare": 0.002576921094676081
  },
  {
    "name": "Zur the Enchanter",
    "conversionRate": 0.13725490196078433,
    "metaShare": 0.0026284595165696027
  },
  {
    "name": "Krark, the Thumbless / Silas Renn, Seeker Adept",
    "conversionRate": 0.35294117647058826,
    "metaShare": 0.0026284595165696027
  },
  {
    "name": "Krark, the Thumbless / Tymna the Weaver",
    "conversionRate": 0.30612244897959184,
    "metaShare": 0.0025253826727825593
  },
  {
    "name": "Dargo, the Shipwrecker / Tymna the Weaver",
    "conversionRate": 0.3877551020408163,
    "metaShare": 0.0025253826727825593
  },
  {
    "name": "Plagon, Lord of the Beach",
    "conversionRate": 0.17777777777777778,
    "metaShare": 0.002319228985208473
  },
  {
    "name": "Tameshi, Reality Architect",
    "conversionRate": 0.22727272727272727,
    "metaShare": 0.0022676905633149513
  },
  {
    "name": "Zirda, the Dawnwaker",
    "conversionRate": 0.3953488372093023,
    "metaShare": 0.0022161521414214296
  },
  {
    "name": "Thrasios, Triton Hero / Vial Smasher the Fierce",
    "conversionRate": 0.06521739130434782,
    "metaShare": 0.0023707674071019947
  },
  {
    "name": "Rowan, Scion of War",
    "conversionRate": 0.20512820512820512,
    "metaShare": 0.002009998453847343
  },
  {
    "name": "Animar, Soul of Elements",
    "conversionRate": 0.2564102564102564,
    "metaShare": 0.002009998453847343
  },
  {
    "name": "Tana, the Bloodsower / Tymna the Weaver",
    "conversionRate": 0.39473684210526316,
    "metaShare": 0.0019584600319538215
  },
  {
    "name": "Esika, God of the Tree // The Prismatic Bridge",
    "conversionRate": 0.35135135135135137,
    "metaShare": 0.0019069216100603
  },
  {
    "name": "Francisco, Fowl Marauder / Thrasios, Triton Hero",
    "conversionRate": 0.32432432432432434,
    "metaShare": 0.0019069216100603
  },
  {
    "name": "Yawgmoth, Thran Physician",
    "conversionRate": 0.25,
    "metaShare": 0.0012369221254445188
  },
  {
    "name": "Pantlaza, Sun-Favored",
    "conversionRate": 0.125,
    "metaShare": 0.0016492295005926918
  },
  {
    "name": "Niv-Mizzet, Parun",
    "conversionRate": 0.15625,
    "metaShare": 0.0016492295005926918
  },
  {
    "name": "Godo, Bandit Warlord",
    "conversionRate": 0.375,
    "metaShare": 0.0016492295005926918
  },
  {
    "name": "Chatterfang, Squirrel General",
    "conversionRate": 0.3448275862068966,
    "metaShare": 0.001494614234912127
  },
  {
    "name": "Korvold, Fae-Cursed King",
    "conversionRate": 0.21428571428571427,
    "metaShare": 0.0014430758130186054
  },
  {
    "name": "Krark, the Thumbless / Thrasios, Triton Hero",
    "conversionRate": 0.36666666666666664,
    "metaShare": 0.0015461526568056486
  },
  {
    "name": "Raffine, Scheming Seer",
    "conversionRate": 0.43333333333333335,
    "metaShare": 0.0015461526568056486
  },
  {
    "name": "Bjorna, Nightfall Alchemist / Wernog, Rider's Chaplain",
    "conversionRate": 0.2857142857142857,
    "metaShare": 0.0014430758130186054
  },
  {
    "name": "Arcum Dagsson",
    "conversionRate": 0.3103448275862069,
    "metaShare": 0.001494614234912127
  },
  {
    "name": "Narset, Enlightened Master",
    "conversionRate": 0.28,
    "metaShare": 0.0012884605473380405
  },
  {
    "name": "Kodama of the East Tree / Tymna the Weaver",
    "conversionRate": 0.5,
    "metaShare": 0.0013399989692315622
  },
  {
    "name": "Tasigur, the Golden Fang",
    "conversionRate": 0.25,
    "metaShare": 0.0012369221254445188
  },
  {
    "name": "Ms. Bumbleflower",
    "conversionRate": 0.08695652173913043,
    "metaShare": 0.0011853837035509973
  },
  {
    "name": "Malcolm, Keen-Eyed Navigator / Tana, the Bloodsower",
    "conversionRate": 0.36363636363636365,
    "metaShare": 0.0011338452816574756
  },
  {
    "name": "Helga, Skittish Seer",
    "conversionRate": 0.3888888888888889,
    "metaShare": 0.0009276915940833892
  },
  {
    "name": "Tiamat",
    "conversionRate": 0.2222222222222222,
    "metaShare": 0.0009276915940833892
  },
  {
    "name": "Sythis, Harvest's Hand",
    "conversionRate": 0.4090909090909091,
    "metaShare": 0.0011338452816574756
  },
  {
    "name": "Emry, Lurker of the Loch",
    "conversionRate": 0.30434782608695654,
    "metaShare": 0.0011853837035509973
  },
  {
    "name": "The Wise Mothman",
    "conversionRate": 0,
    "metaShare": 0.0010307684378704325
  },
  {
    "name": "Narset, Enlightened Exile",
    "conversionRate": 0.21739130434782608,
    "metaShare": 0.0011853837035509973
  },
  {
    "name": "Zhulodok, Void Gorger",
    "conversionRate": 0.0625,
    "metaShare": 0.0008246147502963459
  },
  {
    "name": "Selvala, Heart of the Wilds",
    "conversionRate": 0.13636363636363635,
    "metaShare": 0.0011338452816574756
  },
  {
    "name": "",
    "conversionRate": 0.17647058823529413,
    "metaShare": 0.0008761531721898676
  },
  {
    "name": "Breya, Etherium Shaper",
    "conversionRate": 0.19047619047619047,
    "metaShare": 0.001082306859763954
  },
  {
    "name": "Thalia and The Gitrog Monster",
    "conversionRate": 0.2,
    "metaShare": 0.0010307684378704325
  },
  {
    "name": "Minsc, Beloved Ranger",
    "conversionRate": 0.36363636363636365,
    "metaShare": 0.0011338452816574756
  },
  {
    "name": "Haldan, Avid Arcanist / Pako, Arcane Retriever",
    "conversionRate": 0.10526315789473684,
    "metaShare": 0.0009792300159769108
  },
  {
    "name": "Jeska, Thrice Reborn / Tymna the Weaver",
    "conversionRate": 0.2,
    "metaShare": 0.0010307684378704325
  },
  {
    "name": "Scion of the Ur-Dragon",
    "conversionRate": 0.2,
    "metaShare": 0.0010307684378704325
  },
  {
    "name": "Felothar the Steadfast",
    "conversionRate": 0.05263157894736842,
    "metaShare": 0.0009792300159769108
  },
  {
    "name": "Valgavoth, Harrower of Souls",
    "conversionRate": 0,
    "metaShare": 0.0008246147502963459
  },
  {
    "name": "Erinis, Gloom Stalker / Street Urchin",
    "conversionRate": 0.4,
    "metaShare": 0.0007730763284028243
  },
  {
    "name": "Ishai, Ojutai Dragonspeaker / Jeska, Thrice Reborn",
    "conversionRate": 0.25,
    "metaShare": 0.0010307684378704325
  },
  {
    "name": "Kaalia of the Vast",
    "conversionRate": 0.21052631578947367,
    "metaShare": 0.0009792300159769108
  },
  {
    "name": "Cazur, Ruthless Stalker / Ukkima, Stalking Shadow",
    "conversionRate": 0.15,
    "metaShare": 0.0010307684378704325
  },
  {
    "name": "Krenko, Mob Boss",
    "conversionRate": 0.058823529411764705,
    "metaShare": 0.0008761531721898676
  },
  {
    "name": "Slicer, Hired Muscle // Slicer, High-Speed Antagonist",
    "conversionRate": 0.26666666666666666,
    "metaShare": 0.0007730763284028243
  },
  {
    "name": "Rograkh, Son of Rohgahh / Tymna the Weaver",
    "conversionRate": 0.16666666666666666,
    "metaShare": 0.0009276915940833892
  },
  {
    "name": "Temmet, Naktamun's Will",
    "conversionRate": 0,
    "metaShare": 0.0008246147502963459
  },
  {
    "name": "Chulane, Teller of Tales",
    "conversionRate": 0.2,
    "metaShare": 0.0007730763284028243
  },
  {
    "name": "Deadpool, Trading Card",
    "conversionRate": 0.25,
    "metaShare": 0.0008246147502963459
  },
  {
    "name": "Eshki, Temur's Roar",
    "conversionRate": 0,
    "metaShare": 0.0008246147502963459
  },
  {
    "name": "Jhoira, Weatherlight Captain",
    "conversionRate": 0.17647058823529413,
    "metaShare": 0.0008761531721898676
  },
  {
    "name": "Niv-Mizzet, Visionary",
    "conversionRate": 0.07142857142857142,
    "metaShare": 0.0007215379065093027
  },
  {
    "name": "Zurgo Stormrender",
    "conversionRate": 0,
    "metaShare": 0.0005669226408287378
  },
  {
    "name": "Yidris, Maelstrom Wielder",
    "conversionRate": 0.3076923076923077,
    "metaShare": 0.0006699994846157811
  },
  {
    "name": "Marwyn, the Nurturer",
    "conversionRate": 0.3,
    "metaShare": 0.0005153842189352162
  },
  {
    "name": "Jhoira, Ageless Innovator",
    "conversionRate": 0.38461538461538464,
    "metaShare": 0.0006699994846157811
  },
  {
    "name": "Rograkh, Son of Rohgahh / Tevesh Szat, Doom of Fools",
    "conversionRate": 0.13333333333333333,
    "metaShare": 0.0007730763284028243
  },
  {
    "name": "Jetmir, Nexus of Revels",
    "conversionRate": 0.21428571428571427,
    "metaShare": 0.0007215379065093027
  },
  {
    "name": "Tatyova, Benthic Druid",
    "conversionRate": 0.46153846153846156,
    "metaShare": 0.0006699994846157811
  },
  {
    "name": "Satya, Aetherflux Genius",
    "conversionRate": 0,
    "metaShare": 0.0006699994846157811
  },
  {
    "name": "Orvar, the All-Form",
    "conversionRate": 0,
    "metaShare": 0.0006699994846157811
  },
  {
    "name": "Hakbal of the Surging Soul",
    "conversionRate": 0,
    "metaShare": 0.0007215379065093027
  },
  {
    "name": "Omnath, Locus of Creation",
    "conversionRate": 0.15384615384615385,
    "metaShare": 0.0006699994846157811
  },
  {
    "name": "Xyris, the Writhing Storm",
    "conversionRate": 0.1,
    "metaShare": 0.0005153842189352162
  },
  {
    "name": "Bruse Tarl, Boorish Herder / Thrasios, Triton Hero",
    "conversionRate": 0.15384615384615385,
    "metaShare": 0.0006699994846157811
  },
  {
    "name": "Morska, Undersea Sleuth",
    "conversionRate": 0,
    "metaShare": 0.0007215379065093027
  },
  {
    "name": "Storm, Force of Nature",
    "conversionRate": 0.15384615384615385,
    "metaShare": 0.0006699994846157811
  },
  {
    "name": "Gyruda, Doom of Depths",
    "conversionRate": 0.35714285714285715,
    "metaShare": 0.0007215379065093027
  },
  {
    "name": "Evelyn, the Covetous",
    "conversionRate": 0.09090909090909091,
    "metaShare": 0.0005669226408287378
  },
  {
    "name": "Kess, Dissident Mage",
    "conversionRate": 0.38461538461538464,
    "metaShare": 0.0006699994846157811
  },
  {
    "name": "Aragorn, the Uniter",
    "conversionRate": 0,
    "metaShare": 0.0006184610627222594
  },
  {
    "name": "Bladewing the Risen",
    "conversionRate": 0.25,
    "metaShare": 0.0006184610627222594
  },
  {
    "name": "Sefris of the Hidden Ways",
    "conversionRate": 0.2,
    "metaShare": 0.0005153842189352162
  },
  {
    "name": "Ezio Auditore da Firenze",
    "conversionRate": 0,
    "metaShare": 0.0004638457970416946
  },
  {
    "name": "Edgar Markov",
    "conversionRate": 0,
    "metaShare": 0.0005153842189352162
  },
  {
    "name": "Akiri, Line-Slinger / Thrasios, Triton Hero",
    "conversionRate": 0.08333333333333333,
    "metaShare": 0.0006184610627222594
  },
  {
    "name": "Ratadrabik of Urborg",
    "conversionRate": 0.4,
    "metaShare": 0.0005153842189352162
  },
  {
    "name": "Dina, Soul Steeper",
    "conversionRate": 0.5833333333333334,
    "metaShare": 0.0006184610627222594
  },
  {
    "name": "Halana, Kessig Ranger / Tymna the Weaver",
    "conversionRate": 0.45454545454545453,
    "metaShare": 0.0005669226408287378
  },
  {
    "name": "Winter, Cynical Opportunist",
    "conversionRate": 0,
    "metaShare": 0.0006184610627222594
  },
  {
    "name": "The Ur-Dragon",
    "conversionRate": 0.08333333333333333,
    "metaShare": 0.0006184610627222594
  },
  {
    "name": "Shalai and Hallar",
    "conversionRate": 0.2222222222222222,
    "metaShare": 0.0004638457970416946
  },
  {
    "name": "Ashling, Flame Dancer",
    "conversionRate": 0.18181818181818182,
    "metaShare": 0.0005669226408287378
  },
  {
    "name": "Redshift, Rocketeer Chief",
    "conversionRate": 0.2727272727272727,
    "metaShare": 0.0005669226408287378
  },
  {
    "name": "Codie, Vociferous Codex",
    "conversionRate": 0.2222222222222222,
    "metaShare": 0.0004638457970416946
  },
  {
    "name": "Shiko and Narset, Unified",
    "conversionRate": 0,
    "metaShare": 0.0005669226408287378
  },
  {
    "name": "Éowyn, Shieldmaiden",
    "conversionRate": 0,
    "metaShare": 0.0005669226408287378
  },
  {
    "name": "Jacob Hauken, Inspector // Hauken's Insight",
    "conversionRate": 0.2,
    "metaShare": 0.0005153842189352162
  },
  {
    "name": "Raggadragga, Goreguts Boss",
    "conversionRate": 0.2857142857142857,
    "metaShare": 0.00036076895325465135
  },
  {
    "name": "Selvala, Explorer Returned",
    "conversionRate": 0.6,
    "metaShare": 0.0002576921094676081
  },
  {
    "name": "The First Sliver",
    "conversionRate": 0.125,
    "metaShare": 0.00041230737514817294
  },
  {
    "name": "Sauron, the Dark Lord",
    "conversionRate": 0.3,
    "metaShare": 0.0005153842189352162
  },
  {
    "name": "Minsc & Boo, Timeless Heroes",
    "conversionRate": 0.16666666666666666,
    "metaShare": 0.0003092305313611297
  },
  {
    "name": "Veyran, Voice of Duality",
    "conversionRate": 0,
    "metaShare": 0.00036076895325465135
  },
  {
    "name": "Francisco, Fowl Marauder / Malcolm, Keen-Eyed Navigator",
    "conversionRate": 0.75,
    "metaShare": 0.00041230737514817294
  },
  {
    "name": "Anje Falkenrath",
    "conversionRate": 0.1111111111111111,
    "metaShare": 0.0004638457970416946
  },
  {
    "name": "Marchesa, Dealer of Death",
    "conversionRate": 0,
    "metaShare": 0.0005153842189352162
  },
  {
    "name": "Gev, Scaled Scorch",
    "conversionRate": 0.2,
    "metaShare": 0.0005153842189352162
  },
  {
    "name": "Saheeli, Radiant Creator",
    "conversionRate": 0,
    "metaShare": 0.0005153842189352162
  },
  {
    "name": "Zimone, Paradox Sculptor",
    "conversionRate": 0,
    "metaShare": 0.0005153842189352162
  },
  {
    "name": "Frodo, Adventurous Hobbit / Sam, Loyal Attendant",
    "conversionRate": 0.2222222222222222,
    "metaShare": 0.0004638457970416946
  },
  {
    "name": "Oswald Fiddlebender",
    "conversionRate": 0.4,
    "metaShare": 0.0005153842189352162
  },
  {
    "name": "Azami, Lady of Scrolls",
    "conversionRate": 0.1111111111111111,
    "metaShare": 0.0004638457970416946
  },
  {
    "name": "Yusri, Fortune's Flame",
    "conversionRate": 0.25,
    "metaShare": 0.00041230737514817294
  },
  {
    "name": "Nekusar, the Mindrazer",
    "conversionRate": 0,
    "metaShare": 0.0005153842189352162
  },
  {
    "name": "Ghyrson Starn, Kelermorph",
    "conversionRate": 0.25,
    "metaShare": 0.00041230737514817294
  },
  {
    "name": "Kodama of the East Tree / Thrasios, Triton Hero",
    "conversionRate": 0.3333333333333333,
    "metaShare": 0.0003092305313611297
  },
  {
    "name": "Rona, Herald of Invasion // Rona, Tolarian Obliterator",
    "conversionRate": 0.2222222222222222,
    "metaShare": 0.0004638457970416946
  },
  {
    "name": "Narset, Jeskai Waymaster",
    "conversionRate": 0.1,
    "metaShare": 0.0005153842189352162
  },
  {
    "name": "Teval, the Balanced Scale",
    "conversionRate": 0,
    "metaShare": 0.0003092305313611297
  },
  {
    "name": "Zimone, Mystery Unraveler",
    "conversionRate": 0.2222222222222222,
    "metaShare": 0.0004638457970416946
  },
  {
    "name": "Maelstrom Wanderer",
    "conversionRate": 0,
    "metaShare": 0.0002576921094676081
  },
  {
    "name": "Captain America, First Avenger",
    "conversionRate": 0.25,
    "metaShare": 0.00041230737514817294
  },
  {
    "name": "Liberator, Urza's Battlethopter",
    "conversionRate": 0.1111111111111111,
    "metaShare": 0.0004638457970416946
  },
  {
    "name": "Lonis, Cryptozoologist",
    "conversionRate": 0.2222222222222222,
    "metaShare": 0.0004638457970416946
  },
  {
    "name": "Tamiyo, Inquisitive Student // Tamiyo, Seasoned Scholar",
    "conversionRate": 0.4444444444444444,
    "metaShare": 0.0004638457970416946
  },
  {
    "name": "Aesi, Tyrant of Gyre Strait",
    "conversionRate": 0,
    "metaShare": 0.0004638457970416946
  },
  {
    "name": "Francisco, Fowl Marauder / Ishai, Ojutai Dragonspeaker",
    "conversionRate": 0.2222222222222222,
    "metaShare": 0.0004638457970416946
  },
  {
    "name": "Tergrid, God of Fright // Tergrid's Lantern",
    "conversionRate": 0.125,
    "metaShare": 0.00041230737514817294
  },
  {
    "name": "Iron Man, Titan of Innovation",
    "conversionRate": 0.3333333333333333,
    "metaShare": 0.0003092305313611297
  },
  {
    "name": "Ketramose, the New Dawn",
    "conversionRate": 0.3333333333333333,
    "metaShare": 0.0003092305313611297
  },
  {
    "name": "Teshar, Ancestor's Apostle",
    "conversionRate": 0,
    "metaShare": 0.0002576921094676081
  },
  {
    "name": "Kona, Rescue Beastie",
    "conversionRate": 0.125,
    "metaShare": 0.00041230737514817294
  },
  {
    "name": "Baylen, the Haymaker",
    "conversionRate": 0.5714285714285714,
    "metaShare": 0.00036076895325465135
  },
  {
    "name": "Vohar, Vodalian Desecrator",
    "conversionRate": 0.14285714285714285,
    "metaShare": 0.00036076895325465135
  },
  {
    "name": "K-9, Mark I / The Fourteenth Doctor",
    "conversionRate": 0,
    "metaShare": 0.0003092305313611297
  },
  {
    "name": "Kodama of the East Tree / Sakashima of a Thousand Faces",
    "conversionRate": 0.25,
    "metaShare": 0.00041230737514817294
  },
  {
    "name": "Omnath, Locus of All",
    "conversionRate": 0.25,
    "metaShare": 0.00041230737514817294
  },
  {
    "name": "Queza, Augur of Agonies",
    "conversionRate": 0.14285714285714285,
    "metaShare": 0.00036076895325465135
  },
  {
    "name": "Kotis, Sibsig Champion",
    "conversionRate": 0,
    "metaShare": 0.0003092305313611297
  },
  {
    "name": "Bruvac the Grandiloquent",
    "conversionRate": 0,
    "metaShare": 0.0002576921094676081
  },
  {
    "name": "Captain Howler, Sea Scourge",
    "conversionRate": 0,
    "metaShare": 0.00041230737514817294
  },
  {
    "name": "Ulalek, Fused Atrocity",
    "conversionRate": 0,
    "metaShare": 0.0002576921094676081
  },
  {
    "name": "Jodah, the Unifier",
    "conversionRate": 0.16666666666666666,
    "metaShare": 0.0003092305313611297
  },
  {
    "name": "Braids, Arisen Nightmare",
    "conversionRate": 0.16666666666666666,
    "metaShare": 0.0003092305313611297
  },
  {
    "name": "Ojer Axonil, Deepest Might // Temple of Power",
    "conversionRate": 0.14285714285714285,
    "metaShare": 0.00036076895325465135
  },
  {
    "name": "Captain Sisay",
    "conversionRate": 0.375,
    "metaShare": 0.00041230737514817294
  },
  {
    "name": "Old Stickfingers",
    "conversionRate": 0.25,
    "metaShare": 0.00041230737514817294
  },
  {
    "name": "Yisan, the Wanderer Bard",
    "conversionRate": 0.42857142857142855,
    "metaShare": 0.00036076895325465135
  },
  {
    "name": "Oskar, Rubbish Reclaimer",
    "conversionRate": 0.2857142857142857,
    "metaShare": 0.00036076895325465135
  },
  {
    "name": "Reyhan, Last of the Abzan / Rograkh, Son of Rohgahh",
    "conversionRate": 0.375,
    "metaShare": 0.00041230737514817294
  },
  {
    "name": "Cecily, Haunted Mage / Sophina, Spearsage Deserter",
    "conversionRate": 0.25,
    "metaShare": 0.00041230737514817294
  },
  {
    "name": "The Fourteenth Doctor / Vislor Turlough",
    "conversionRate": 0.8571428571428571,
    "metaShare": 0.00036076895325465135
  },
  {
    "name": "Kroxa, Titan of Death's Hunger",
    "conversionRate": 0.14285714285714285,
    "metaShare": 0.00036076895325465135
  },
  {
    "name": "Prosper, Tome-Bound",
    "conversionRate": 0,
    "metaShare": 0.00036076895325465135
  },
  {
    "name": "Teferi, Temporal Archmage",
    "conversionRate": 0.25,
    "metaShare": 0.00020615368757408647
  },
  {
    "name": "Elmar, Ulvenwald Informant / Wernog, Rider's Chaplain",
    "conversionRate": 0,
    "metaShare": 0.00036076895325465135
  },
  {
    "name": "Bruse Tarl, Boorish Herder / Malcolm, Keen-Eyed Navigator",
    "conversionRate": 0,
    "metaShare": 0.0002576921094676081
  },
  {
    "name": "Armix, Filigree Thrasher / Thrasios, Triton Hero",
    "conversionRate": 0.2,
    "metaShare": 0.0002576921094676081
  },
  {
    "name": "Clavileño, First of the Blessed",
    "conversionRate": 0,
    "metaShare": 0.0002576921094676081
  },
  {
    "name": "Admiral Brass, Unsinkable",
    "conversionRate": 0,
    "metaShare": 0.00036076895325465135
  },
  {
    "name": "Grist, the Hunger Tide",
    "conversionRate": 0.2857142857142857,
    "metaShare": 0.00036076895325465135
  },
  {
    "name": "Lathril, Blade of the Elves",
    "conversionRate": 0,
    "metaShare": 0.0002576921094676081
  },
  {
    "name": "Edward Kenway",
    "conversionRate": 0,
    "metaShare": 0.0003092305313611297
  },
  {
    "name": "The Beamtown Bullies",
    "conversionRate": 0,
    "metaShare": 0.00010307684378704323
  },
  {
    "name": "The Necrobloom",
    "conversionRate": 0,
    "metaShare": 0.0002576921094676081
  },
  {
    "name": "The Master, Transcendent",
    "conversionRate": 0.14285714285714285,
    "metaShare": 0.00036076895325465135
  },
  {
    "name": "Urabrask // The Great Work",
    "conversionRate": 0.14285714285714285,
    "metaShare": 0.00036076895325465135
  },
  {
    "name": "Mirko, Obsessive Theorist",
    "conversionRate": 0,
    "metaShare": 0.0003092305313611297
  },
  {
    "name": "Brago, King Eternal",
    "conversionRate": 0.2,
    "metaShare": 0.0002576921094676081
  },
  {
    "name": "Lord Windgrace",
    "conversionRate": 0.42857142857142855,
    "metaShare": 0.00036076895325465135
  },
  {
    "name": "Go-Shintai of Life's Origin",
    "conversionRate": 0.2,
    "metaShare": 0.0002576921094676081
  },
  {
    "name": "Meria, Scholar of Antiquity",
    "conversionRate": 0.2857142857142857,
    "metaShare": 0.00036076895325465135
  },
  {
    "name": "Hapatra, Vizier of Poisons",
    "conversionRate": 0,
    "metaShare": 0.00036076895325465135
  },
  {
    "name": "Dogmeat, Ever Loyal",
    "conversionRate": 0,
    "metaShare": 0.0003092305313611297
  },
  {
    "name": "Kykar, Wind's Fury",
    "conversionRate": 0,
    "metaShare": 0.00020615368757408647
  },
  {
    "name": "Borborygmos and Fblthp",
    "conversionRate": 0.2,
    "metaShare": 0.0002576921094676081
  },
  {
    "name": "Vren, the Relentless",
    "conversionRate": 0.3333333333333333,
    "metaShare": 0.0003092305313611297
  },
  {
    "name": "Breeches, Brazen Plunderer / Malcolm, Keen-Eyed Navigator",
    "conversionRate": 0.4,
    "metaShare": 0.0002576921094676081
  },
  {
    "name": "Kamahl, Heart of Krosa / Tymna the Weaver",
    "conversionRate": 0.2,
    "metaShare": 0.0002576921094676081
  },
  {
    "name": "Meren of Clan Nel Toth",
    "conversionRate": 0,
    "metaShare": 0.00020615368757408647
  },
  {
    "name": "Nalia de'Arnise",
    "conversionRate": 0,
    "metaShare": 0.0003092305313611297
  },
  {
    "name": "Cormela, Glamour Thief",
    "conversionRate": 0,
    "metaShare": 0.00020615368757408647
  },
  {
    "name": "Varina, Lich Queen",
    "conversionRate": 0.25,
    "metaShare": 0.00020615368757408647
  },
  {
    "name": "Cecily, Haunted Mage / Othelm, Sigardian Outcast",
    "conversionRate": 0.5,
    "metaShare": 0.0003092305313611297
  },
  {
    "name": "Thada Adel, Acquisitor",
    "conversionRate": 0.3333333333333333,
    "metaShare": 0.00015461526568056485
  },
  {
    "name": "Wilhelt, the Rotcleaver",
    "conversionRate": 0,
    "metaShare": 0.0003092305313611297
  },
  {
    "name": "Arabella, Abandoned Doll",
    "conversionRate": 0,
    "metaShare": 0.0003092305313611297
  },
  {
    "name": "Bruse Tarl, Boorish Herder / Kamahl, Heart of Krosa",
    "conversionRate": 0.3333333333333333,
    "metaShare": 0.0003092305313611297
  },
  {
    "name": "Don Andres, the Renegade",
    "conversionRate": 0,
    "metaShare": 0.0003092305313611297
  },
  {
    "name": "Heliod, Sun-Crowned",
    "conversionRate": 0.2,
    "metaShare": 0.0002576921094676081
  },
  {
    "name": "Osgir, the Reconstructor",
    "conversionRate": 0,
    "metaShare": 0.0002576921094676081
  },
  {
    "name": "Rose Tyler / The Tenth Doctor",
    "conversionRate": 0,
    "metaShare": 0.0003092305313611297
  },
  {
    "name": "Dargo, the Shipwrecker / Silas Renn, Seeker Adept",
    "conversionRate": 0.4,
    "metaShare": 0.0002576921094676081
  },
  {
    "name": "Tatsunari, Toad Rider",
    "conversionRate": 0,
    "metaShare": 0.0003092305313611297
  },
  {
    "name": "Prossh, Skyraider of Kher",
    "conversionRate": 0,
    "metaShare": 0.00020615368757408647
  },
  {
    "name": "Ardenn, Intrepid Archaeologist / Rograkh, Son of Rohgahh",
    "conversionRate": 0.2,
    "metaShare": 0.0002576921094676081
  },
  {
    "name": "Teysa Karlov",
    "conversionRate": 0.4,
    "metaShare": 0.0002576921094676081
  },
  {
    "name": "Edric, Spymaster of Trest",
    "conversionRate": 0.5,
    "metaShare": 0.0003092305313611297
  },
  {
    "name": "Disa the Restless",
    "conversionRate": 0,
    "metaShare": 0.00015461526568056485
  },
  {
    "name": "Voja, Jaws of the Conclave",
    "conversionRate": 0,
    "metaShare": 0.0002576921094676081
  },
  {
    "name": "Anikthea, Hand of Erebos",
    "conversionRate": 0,
    "metaShare": 0.0002576921094676081
  },
  {
    "name": "Oloro, Ageless Ascetic",
    "conversionRate": 0,
    "metaShare": 0.0003092305313611297
  },
  {
    "name": "Zedruu the Greathearted",
    "conversionRate": 0,
    "metaShare": 0.00010307684378704323
  },
  {
    "name": "Lonis, Genetics Expert",
    "conversionRate": 0.2,
    "metaShare": 0.0002576921094676081
  },
  {
    "name": "Brallin, Skyshark Rider / Shabraz, the Skyshark",
    "conversionRate": 0.3333333333333333,
    "metaShare": 0.00015461526568056485
  },
  {
    "name": "Ruric Thar, the Unbowed",
    "conversionRate": 0,
    "metaShare": 0.0002576921094676081
  },
  {
    "name": "Henzie \"Toolbox\" Torre",
    "conversionRate": 0.4,
    "metaShare": 0.0002576921094676081
  },
  {
    "name": "Bello, Bard of the Brambles",
    "conversionRate": 0,
    "metaShare": 0.0002576921094676081
  },
  {
    "name": "Zimone and Dina",
    "conversionRate": 0.6,
    "metaShare": 0.0002576921094676081
  },
  {
    "name": "Tazri, Beacon of Unity",
    "conversionRate": 0.4,
    "metaShare": 0.0002576921094676081
  },
  {
    "name": "Lavinia, Azorius Renegade",
    "conversionRate": 0,
    "metaShare": 0.0002576921094676081
  },
  {
    "name": "Eladamri, Korvecdal",
    "conversionRate": 0,
    "metaShare": 0.00020615368757408647
  },
  {
    "name": "Krark, the Thumbless / Reyhan, Last of the Abzan",
    "conversionRate": 0.2,
    "metaShare": 0.0002576921094676081
  },
  {
    "name": "Pir, Imaginative Rascal / Toothy, Imaginary Friend",
    "conversionRate": 0.25,
    "metaShare": 0.00020615368757408647
  },
  {
    "name": "Alela, Cunning Conqueror",
    "conversionRate": 0,
    "metaShare": 0.0002576921094676081
  },
  {
    "name": "Feather, the Redeemed",
    "conversionRate": 0,
    "metaShare": 0.00015461526568056485
  },
  {
    "name": "Ishai, Ojutai Dragonspeaker / Kodama of the East Tree",
    "conversionRate": 0.2,
    "metaShare": 0.0002576921094676081
  },
  {
    "name": "Sauron, Lord of the Rings",
    "conversionRate": 0,
    "metaShare": 0.0002576921094676081
  },
  {
    "name": "Six",
    "conversionRate": 0,
    "metaShare": 0.0002576921094676081
  },
  {
    "name": "The Howling Abomination",
    "conversionRate": 0,
    "metaShare": 0.00015461526568056485
  },
  {
    "name": "Yarok, the Desecrated",
    "conversionRate": 0,
    "metaShare": 0.00010307684378704323
  },
  {
    "name": "Yeva, Nature's Herald",
    "conversionRate": 0.4,
    "metaShare": 0.0002576921094676081
  },
  {
    "name": "Kotori, Pilot Prodigy",
    "conversionRate": 0,
    "metaShare": 0.0002576921094676081
  },
  {
    "name": "Grenzo, Dungeon Warden",
    "conversionRate": 0,
    "metaShare": 0.00010307684378704323
  },
  {
    "name": "Zurgo and Ojutai",
    "conversionRate": 0,
    "metaShare": 0.00020615368757408647
  },
  {
    "name": "Daretti, Scrap Savant",
    "conversionRate": 0,
    "metaShare": 0.0002576921094676081
  },
  {
    "name": "Padeem, Consul of Innovation",
    "conversionRate": 0,
    "metaShare": 0.00020615368757408647
  },
  {
    "name": "Unesh, Criosphinx Sovereign",
    "conversionRate": 0,
    "metaShare": 0.00020615368757408647
  },
  {
    "name": "Commodore Guff",
    "conversionRate": 0,
    "metaShare": 0.00020615368757408647
  },
  {
    "name": "Eriette of the Charmed Apple",
    "conversionRate": 0,
    "metaShare": 0.0002576921094676081
  },
  {
    "name": "Hazel of the Rootbloom",
    "conversionRate": 0,
    "metaShare": 0.00020615368757408647
  },
  {
    "name": "Ureni of the Unwritten",
    "conversionRate": 0,
    "metaShare": 0.00015461526568056485
  },
  {
    "name": "Hidetsugu and Kairi",
    "conversionRate": 0.4,
    "metaShare": 0.0002576921094676081
  },
  {
    "name": "Vadrik, Astral Archmage",
    "conversionRate": 0.25,
    "metaShare": 0.00020615368757408647
  },
  {
    "name": "Dargo, the Shipwrecker / Malcolm, Keen-Eyed Navigator",
    "conversionRate": 0,
    "metaShare": 0.00020615368757408647
  },
  {
    "name": "Elsha, Threefold Master",
    "conversionRate": 0.25,
    "metaShare": 0.00020615368757408647
  },
  {
    "name": "Dr. Madison Li",
    "conversionRate": 0,
    "metaShare": 0.0002576921094676081
  },
  {
    "name": "Kotis, the Fangkeeper",
    "conversionRate": 0,
    "metaShare": 0.0002576921094676081
  },
  {
    "name": "Sorin of House Markov // Sorin, Ravenous Neonate",
    "conversionRate": 0,
    "metaShare": 0.00020615368757408647
  },
  {
    "name": "Alexios, Deimos of Kosmos",
    "conversionRate": 0,
    "metaShare": 0.0002576921094676081
  },
  {
    "name": "Light-Paws, Emperor's Voice",
    "conversionRate": 0,
    "metaShare": 0.00020615368757408647
  },
  {
    "name": "Gut, True Soul Zealot / Inspiring Leader",
    "conversionRate": 0,
    "metaShare": 0.00020615368757408647
  },
  {
    "name": "Ardenn, Intrepid Archaeologist / Tana, the Bloodsower",
    "conversionRate": 0.3333333333333333,
    "metaShare": 0.00015461526568056485
  },
  {
    "name": "Fynn, the Fangbearer",
    "conversionRate": 0,
    "metaShare": 0.00010307684378704323
  },
  {
    "name": "Gonti, Night Minister",
    "conversionRate": 0,
    "metaShare": 0.00020615368757408647
  },
  {
    "name": "Roxanne, Starfall Savant",
    "conversionRate": 0.25,
    "metaShare": 0.00020615368757408647
  },
  {
    "name": "Gretchen Titchwillow",
    "conversionRate": 0.25,
    "metaShare": 0.00020615368757408647
  },
  {
    "name": "Mogis, God of Slaughter",
    "conversionRate": 0,
    "metaShare": 0.00020615368757408647
  },
  {
    "name": "Zinnia, Valley's Voice",
    "conversionRate": 0,
    "metaShare": 0.00015461526568056485
  },
  {
    "name": "Satoru, the Infiltrator",
    "conversionRate": 0.5,
    "metaShare": 0.00010307684378704323
  },
  {
    "name": "Sidar Jabari of Zhalfir",
    "conversionRate": 0,
    "metaShare": 0.00015461526568056485
  },
  {
    "name": "The Mimeoplasm",
    "conversionRate": 0.25,
    "metaShare": 0.00020615368757408647
  },
  {
    "name": "Marath, Will of the Wild",
    "conversionRate": 0,
    "metaShare": 0.00015461526568056485
  },
  {
    "name": "Isshin, Two Heavens as One",
    "conversionRate": 0,
    "metaShare": 0.00020615368757408647
  },
  {
    "name": "Purphoros, God of the Forge",
    "conversionRate": 0,
    "metaShare": 0.00020615368757408647
  },
  {
    "name": "Ishai, Ojutai Dragonspeaker / Krark, the Thumbless",
    "conversionRate": 0.25,
    "metaShare": 0.00020615368757408647
  },
  {
    "name": "Acererak the Archlich",
    "conversionRate": 0,
    "metaShare": 0.00020615368757408647
  },
  {
    "name": "Sakashima of a Thousand Faces / Tymna the Weaver",
    "conversionRate": 0,
    "metaShare": 0.00020615368757408647
  },
  {
    "name": "Galadriel, Light of Valinor",
    "conversionRate": 0.3333333333333333,
    "metaShare": 0.00015461526568056485
  },
  {
    "name": "Giada, Font of Hope",
    "conversionRate": 0,
    "metaShare": 0.00010307684378704323
  },
  {
    "name": "Katilda, Dawnhart Prime",
    "conversionRate": 0.5,
    "metaShare": 0.00020615368757408647
  },
  {
    "name": "Francisco, Fowl Marauder / Rograkh, Son of Rohgahh",
    "conversionRate": 0.25,
    "metaShare": 0.00020615368757408647
  },
  {
    "name": "Gonti, Canny Acquisitor",
    "conversionRate": 0,
    "metaShare": 0.00020615368757408647
  },
  {
    "name": "Kozilek, the Great Distortion",
    "conversionRate": 0,
    "metaShare": 0.00015461526568056485
  },
  {
    "name": "Medomai the Ageless",
    "conversionRate": 0,
    "metaShare": 0
  },
  {
    "name": "Captain N'ghathrod",
    "conversionRate": 0,
    "metaShare": 0.00020615368757408647
  },
  {
    "name": "Omo, Queen of Vesuva",
    "conversionRate": 0,
    "metaShare": 0.00020615368757408647
  },
  {
    "name": "The Thirteenth Doctor / Yasmin Khan",
    "conversionRate": 0,
    "metaShare": 0.00020615368757408647
  },
  {
    "name": "Tegwyll, Duke of Splendor",
    "conversionRate": 0,
    "metaShare": 0.00020615368757408647
  },
  {
    "name": "Ygra, Eater of All",
    "conversionRate": 0,
    "metaShare": 0.00005153842189352162
  },
  {
    "name": "Lotho, Corrupt Shirriff",
    "conversionRate": 0.75,
    "metaShare": 0.00020615368757408647
  },
  {
    "name": "Grolnok, the Omnivore",
    "conversionRate": 0.25,
    "metaShare": 0.00020615368757408647
  },
  {
    "name": "Rhys the Redeemed",
    "conversionRate": 0,
    "metaShare": 0.00015461526568056485
  },
  {
    "name": "Hansk, Slayer Zealot",
    "conversionRate": 0,
    "metaShare": 0.00015461526568056485
  },
  {
    "name": "Octavia, Living Thesis",
    "conversionRate": 0,
    "metaShare": 0.00020615368757408647
  },
  {
    "name": "Birgi, God of Storytelling // Harnfel, Horn of Bounty",
    "conversionRate": 0,
    "metaShare": 0.00015461526568056485
  },
  {
    "name": "Be'lakor, the Dark Master",
    "conversionRate": 0,
    "metaShare": 0.00015461526568056485
  },
  {
    "name": "Ixhel, Scion of Atraxa",
    "conversionRate": 0,
    "metaShare": 0.00020615368757408647
  },
  {
    "name": "Toxrill, the Corrosive",
    "conversionRate": 0,
    "metaShare": 0.00015461526568056485
  },
  {
    "name": "Ghave, Guru of Spores",
    "conversionRate": 0,
    "metaShare": 0.00015461526568056485
  },
  {
    "name": "Rionya, Fire Dancer",
    "conversionRate": 0,
    "metaShare": 0.00015461526568056485
  },
  {
    "name": "Dargo, the Shipwrecker / Thrasios, Triton Hero",
    "conversionRate": 0,
    "metaShare": 0.00020615368757408647
  },
  {
    "name": "Ezuri, Renegade Leader",
    "conversionRate": 0,
    "metaShare": 0.00015461526568056485
  },
  {
    "name": "Akiri, Line-Slinger / Malcolm, Keen-Eyed Navigator",
    "conversionRate": 0.25,
    "metaShare": 0.00020615368757408647
  },
  {
    "name": "Zada, Hedron Grinder",
    "conversionRate": 0.5,
    "metaShare": 0.00020615368757408647
  },
  {
    "name": "Yuma, Proud Protector",
    "conversionRate": 0,
    "metaShare": 0.00020615368757408647
  },
  {
    "name": "Miirym, Sentinel Wyrm",
    "conversionRate": 0,
    "metaShare": 0.00010307684378704323
  },
  {
    "name": "Edgar, Charmed Groom // Edgar Markov's Coffin",
    "conversionRate": 0,
    "metaShare": 0.00020615368757408647
  },
  {
    "name": "Satoru Umezawa",
    "conversionRate": 0,
    "metaShare": 0
  },
  {
    "name": "Shiko, Paragon of the Way",
    "conversionRate": 0,
    "metaShare": 0.00005153842189352162
  },
  {
    "name": "Nymris, Oona's Trickster",
    "conversionRate": 0,
    "metaShare": 0.00020615368757408647
  },
  {
    "name": "Danny Pink",
    "conversionRate": 0,
    "metaShare": 0.00020615368757408647
  },
  {
    "name": "Davros, Dalek Creator",
    "conversionRate": 0.3333333333333333,
    "metaShare": 0.00015461526568056485
  },
  {
    "name": "Faldorn, Dread Wolf Herald",
    "conversionRate": 0,
    "metaShare": 0.00020615368757408647
  },
  {
    "name": "Inquisitor Greyfax",
    "conversionRate": 0,
    "metaShare": 0.00020615368757408647
  },
  {
    "name": "Mizzix of the Izmagnus",
    "conversionRate": 0,
    "metaShare": 0.00010307684378704323
  },
  {
    "name": "Grand Arbiter Augustin IV",
    "conversionRate": 0.25,
    "metaShare": 0.00020615368757408647
  },
  {
    "name": "Niv-Mizzet Reborn",
    "conversionRate": 0,
    "metaShare": 0.00010307684378704323
  },
  {
    "name": "Leonardo da Vinci",
    "conversionRate": 0,
    "metaShare": 0.00015461526568056485
  },
  {
    "name": "Kumena, Tyrant of Orazca",
    "conversionRate": 0,
    "metaShare": 0.00015461526568056485
  },
  {
    "name": "Rakdos, Lord of Riots",
    "conversionRate": 0,
    "metaShare": 0.00015461526568056485
  },
  {
    "name": "Alaundo the Seer",
    "conversionRate": 0.3333333333333333,
    "metaShare": 0.00015461526568056485
  },
  {
    "name": "Koll, the Forgemaster",
    "conversionRate": 0,
    "metaShare": 0.00015461526568056485
  },
  {
    "name": "Chishiro, the Shattered Blade",
    "conversionRate": 0,
    "metaShare": 0.00015461526568056485
  },
  {
    "name": "Kodama of the East Tree / Silas Renn, Seeker Adept",
    "conversionRate": 0,
    "metaShare": 0.00015461526568056485
  },
  {
    "name": "Gishath, Sun's Avatar",
    "conversionRate": 0,
    "metaShare": 0.00010307684378704323
  },
  {
    "name": "Garth One-Eye",
    "conversionRate": 0,
    "metaShare": 0.00015461526568056485
  },
  {
    "name": "Kambal, Profiteering Mayor",
    "conversionRate": 0.3333333333333333,
    "metaShare": 0.00015461526568056485
  },
  {
    "name": "General Ferrous Rokiric",
    "conversionRate": 0,
    "metaShare": 0.00015461526568056485
  },
  {
    "name": "Livio, Oathsworn Sentinel / Thrasios, Triton Hero",
    "conversionRate": 0.3333333333333333,
    "metaShare": 0.00015461526568056485
  },
  {
    "name": "Slimefoot and Squee",
    "conversionRate": 0,
    "metaShare": 0.00005153842189352162
  },
  {
    "name": "Winter, Misanthropic Guide",
    "conversionRate": 0,
    "metaShare": 0.00015461526568056485
  },
  {
    "name": "Willowdusk, Essence Seer",
    "conversionRate": 0,
    "metaShare": 0.00005153842189352162
  },
  {
    "name": "Kamiz, Obscura Oculus",
    "conversionRate": 0,
    "metaShare": 0.00015461526568056485
  },
  {
    "name": "The Reality Chip",
    "conversionRate": 0.3333333333333333,
    "metaShare": 0.00015461526568056485
  },
  {
    "name": "Burakos, Party Leader / Candlekeep Sage",
    "conversionRate": 0.3333333333333333,
    "metaShare": 0.00015461526568056485
  },
  {
    "name": "Loyal Subordinate",
    "conversionRate": 0.5,
    "metaShare": 0.00010307684378704323
  },
  {
    "name": "Kibo, Uktabi Prince",
    "conversionRate": 0,
    "metaShare": 0.00015461526568056485
  },
  {
    "name": "Jeska, Thrice Reborn / Thrasios, Triton Hero",
    "conversionRate": 0,
    "metaShare": 0.00010307684378704323
  },
  {
    "name": "Coram, the Undertaker",
    "conversionRate": 0,
    "metaShare": 0.00015461526568056485
  },
  {
    "name": "Prime Speaker Vannifar",
    "conversionRate": 0.5,
    "metaShare": 0.00010307684378704323
  },
  {
    "name": "The Jolly Balloon Man",
    "conversionRate": 0,
    "metaShare": 0.00015461526568056485
  },
  {
    "name": "Malcolm, Keen-Eyed Navigator / Rograkh, Son of Rohgahh",
    "conversionRate": 0,
    "metaShare": 0.00005153842189352162
  },
  {
    "name": "Esior, Wardwing Familiar / Tymna the Weaver",
    "conversionRate": 0,
    "metaShare": 0.00015461526568056485
  },
  {
    "name": "Dionus, Elvish Archdruid",
    "conversionRate": 0.5,
    "metaShare": 0.00010307684378704323
  },
  {
    "name": "Yasharn, Implacable Earth",
    "conversionRate": 0,
    "metaShare": 0.00015461526568056485
  },
  {
    "name": "Azusa, Lost but Seeking",
    "conversionRate": 0,
    "metaShare": 0.00010307684378704323
  },
  {
    "name": "Jolene, the Plunder Queen",
    "conversionRate": 0.5,
    "metaShare": 0.00010307684378704323
  },
  {
    "name": "Muxus, Goblin Grandee",
    "conversionRate": 0.6666666666666666,
    "metaShare": 0.00015461526568056485
  },
  {
    "name": "Nelly Borca, Impulsive Accuser",
    "conversionRate": 0,
    "metaShare": 0.00015461526568056485
  },
  {
    "name": "Emiel the Blessed",
    "conversionRate": 0,
    "metaShare": 0.00015461526568056485
  },
  {
    "name": "Dargo, the Shipwrecker / Reyhan, Last of the Abzan",
    "conversionRate": 0,
    "metaShare": 0.00015461526568056485
  },
  {
    "name": "Ragavan, Nimble Pilferer",
    "conversionRate": 0,
    "metaShare": 0.00010307684378704323
  },
  {
    "name": "Francisco, Fowl Marauder / Kraum, Ludevic's Opus",
    "conversionRate": 0,
    "metaShare": 0.00015461526568056485
  },
  {
    "name": "Mendicant Core, Guidelight",
    "conversionRate": 0,
    "metaShare": 0.00015461526568056485
  },
  {
    "name": "Kraum, Ludevic's Opus / Tevesh Szat, Doom of Fools",
    "conversionRate": 0,
    "metaShare": 0.00010307684378704323
  },
  {
    "name": "Nardole, Resourceful Cyborg / The Fourteenth Doctor",
    "conversionRate": 0,
    "metaShare": 0.00015461526568056485
  },
  {
    "name": "Narci, Fable Singer",
    "conversionRate": 0,
    "metaShare": 0.00015461526568056485
  },
  {
    "name": "Thrasios, Triton Hero / Tormod, the Desecrator",
    "conversionRate": 0,
    "metaShare": 0.00015461526568056485
  },
  {
    "name": "Abdel Adrian, Gorion's Ward / Candlekeep Sage",
    "conversionRate": 0.5,
    "metaShare": 0.00010307684378704323
  },
  {
    "name": "Ob Nixilis of the Black Oath",
    "conversionRate": 0,
    "metaShare": 0.00015461526568056485
  },
  {
    "name": "Liesa, Shroud of Dusk",
    "conversionRate": 0,
    "metaShare": 0.00010307684378704323
  },
  {
    "name": "Sarah Jane Smith / The Sixth Doctor",
    "conversionRate": 0,
    "metaShare": 0.00015461526568056485
  },
  {
    "name": "Fblthp, the Lost",
    "conversionRate": 0,
    "metaShare": 0.00010307684378704323
  },
  {
    "name": "Sliver Gravemother",
    "conversionRate": 0,
    "metaShare": 0.00015461526568056485
  },
  {
    "name": "Neyali, Suns' Vanguard",
    "conversionRate": 0,
    "metaShare": 0.00015461526568056485
  },
  {
    "name": "Anim Pakal, Thousandth Moon",
    "conversionRate": 0,
    "metaShare": 0.00015461526568056485
  },
  {
    "name": "Aminatou, Veil Piercer",
    "conversionRate": 0,
    "metaShare": 0.00015461526568056485
  },
  {
    "name": "Loot, the Key to Everything",
    "conversionRate": 0,
    "metaShare": 0.00015461526568056485
  },
  {
    "name": "Balthor the Defiled",
    "conversionRate": 0.5,
    "metaShare": 0.00010307684378704323
  },
  {
    "name": "Nicol Bolas, the Ravager // Nicol Bolas, the Arisen",
    "conversionRate": 1,
    "metaShare": 0.00010307684378704323
  },
  {
    "name": "Talrand, Sky Summoner",
    "conversionRate": 0,
    "metaShare": 0.00015461526568056485
  },
  {
    "name": "Vnwxt, Verbose Host",
    "conversionRate": 0,
    "metaShare": 0.00005153842189352162
  },
  {
    "name": "Kasla, the Broken Halo",
    "conversionRate": 0,
    "metaShare": 0.00015461526568056485
  },
  {
    "name": "Bria, Riptide Rogue",
    "conversionRate": 0,
    "metaShare": 0.00015461526568056485
  },
  {
    "name": "Magus Lucea Kane",
    "conversionRate": 0,
    "metaShare": 0.00015461526568056485
  },
  {
    "name": "Olivia, Opulent Outlaw",
    "conversionRate": 0,
    "metaShare": 0.00015461526568056485
  },
  {
    "name": "Oviya, Automech Artisan",
    "conversionRate": 0,
    "metaShare": 0.00015461526568056485
  },
  {
    "name": "Marvin, Murderous Mimic",
    "conversionRate": 0.5,
    "metaShare": 0.00010307684378704323
  },
  {
    "name": "Muldrotha, the Gravetide",
    "conversionRate": 1,
    "metaShare": 0.00005153842189352162
  },
  {
    "name": "Nezahal, Primal Tide",
    "conversionRate": 0.3333333333333333,
    "metaShare": 0.00015461526568056485
  },
  {
    "name": "Omnath, Locus of Mana",
    "conversionRate": 0,
    "metaShare": 0.00005153842189352162
  },
  {
    "name": "Far Traveler / Wilson, Refined Grizzly",
    "conversionRate": 0.5,
    "metaShare": 0.00010307684378704323
  },
  {
    "name": "Queen Marchesa",
    "conversionRate": 0,
    "metaShare": 0.00010307684378704323
  },
  {
    "name": "Ikra Shidiqi, the Usurper / Kraum, Ludevic's Opus",
    "conversionRate": 0,
    "metaShare": 0.00010307684378704323
  },
  {
    "name": "Black Panther, Wakandan King",
    "conversionRate": 0,
    "metaShare": 0.00010307684378704323
  },
  {
    "name": "Tinybones, Trinket Thief",
    "conversionRate": 0,
    "metaShare": 0.00010307684378704323
  },
  {
    "name": "Rielle, the Everwise",
    "conversionRate": 0,
    "metaShare": 0.00010307684378704323
  },
  {
    "name": "Red Death, Shipwrecker",
    "conversionRate": 0,
    "metaShare": 0.00010307684378704323
  },
  {
    "name": "Nikara, Lair Scavenger / Yannik, Scavenging Sentinel",
    "conversionRate": 0.5,
    "metaShare": 0.00010307684378704323
  },
  {
    "name": "Daretti, Rocketeer Engineer",
    "conversionRate": 0,
    "metaShare": 0.00010307684378704323
  },
  {
    "name": "Karazikar, the Eye Tyrant",
    "conversionRate": 0,
    "metaShare": 0.00010307684378704323
  },
  {
    "name": "Elas il-Kor, Sadistic Pilgrim",
    "conversionRate": 0,
    "metaShare": 0.00010307684378704323
  },
  {
    "name": "Mabel, Heir to Cragflame",
    "conversionRate": 0,
    "metaShare": 0.00010307684378704323
  },
  {
    "name": "Evie Frye / Jacob Frye",
    "conversionRate": 0,
    "metaShare": 0.00010307684378704323
  },
  {
    "name": "Vannifar, Evolved Enigma",
    "conversionRate": 0,
    "metaShare": 0.00010307684378704323
  },
  {
    "name": "Kiki-Jiki, Mirror Breaker",
    "conversionRate": 0,
    "metaShare": 0.00010307684378704323
  },
  {
    "name": "Aminatou, the Fateshifter",
    "conversionRate": 0,
    "metaShare": 0.00010307684378704323
  },
  {
    "name": "Anowon, the Ruin Thief",
    "conversionRate": 0,
    "metaShare": 0.00010307684378704323
  },
  {
    "name": "Delina, Wild Mage",
    "conversionRate": 0.5,
    "metaShare": 0.00010307684378704323
  },
  {
    "name": "Raphael, Fiendish Savior",
    "conversionRate": 0,
    "metaShare": 0.00010307684378704323
  },
  {
    "name": "Atarka, World Render",
    "conversionRate": 0,
    "metaShare": 0.00010307684378704323
  },
  {
    "name": "Kydele, Chosen of Kruphix / Tymna the Weaver",
    "conversionRate": 0,
    "metaShare": 0.00010307684378704323
  },
  {
    "name": "Tuvasa the Sunlit",
    "conversionRate": 0,
    "metaShare": 0.00010307684378704323
  },
  {
    "name": "Ishai, Ojutai Dragonspeaker / Rograkh, Son of Rohgahh",
    "conversionRate": 1,
    "metaShare": 0.00005153842189352162
  },
  {
    "name": "Imoti, Celebrant of Bounty",
    "conversionRate": 0,
    "metaShare": 0.00005153842189352162
  },
  {
    "name": "Sliver Overlord",
    "conversionRate": 0.5,
    "metaShare": 0.00010307684378704323
  },
  {
    "name": "Othelm, Sigardian Outcast / Wernog, Rider's Chaplain",
    "conversionRate": 0.5,
    "metaShare": 0.00010307684378704323
  },
  {
    "name": "Atraxa, Praetors' Voice",
    "conversionRate": 0,
    "metaShare": 0.00005153842189352162
  },
  {
    "name": "Gaddock Teeg",
    "conversionRate": 0,
    "metaShare": 0.00010307684378704323
  },
  {
    "name": "Francisco, Fowl Marauder / Tymna the Weaver",
    "conversionRate": 0.5,
    "metaShare": 0.00010307684378704323
  },
  {
    "name": "Rodolf Duskbringer",
    "conversionRate": 0,
    "metaShare": 0.00010307684378704323
  },
  {
    "name": "Saruman, the White Hand",
    "conversionRate": 0,
    "metaShare": 0.00010307684378704323
  },
  {
    "name": "Umbris, Fear Manifest",
    "conversionRate": 0,
    "metaShare": 0.00010307684378704323
  },
  {
    "name": "Child of Alara",
    "conversionRate": 0,
    "metaShare": 0.00010307684378704323
  },
  {
    "name": "Loot, Exuberant Explorer",
    "conversionRate": 0.5,
    "metaShare": 0.00010307684378704323
  },
  {
    "name": "Ojer Kaslem, Deepest Growth // Temple of Cultivation",
    "conversionRate": 1,
    "metaShare": 0.00010307684378704323
  },
  {
    "name": "Ian Malcolm, Chaotician",
    "conversionRate": 0,
    "metaShare": 0.00010307684378704323
  },
  {
    "name": "Toshiro Umezawa",
    "conversionRate": 0,
    "metaShare": 0.00010307684378704323
  },
  {
    "name": "Hylda of the Icy Crown",
    "conversionRate": 0,
    "metaShare": 0.00010307684378704323
  },
  {
    "name": "Ardenn, Intrepid Archaeologist / Vial Smasher the Fierce",
    "conversionRate": 0,
    "metaShare": 0.00010307684378704323
  },
  {
    "name": "Archelos, Lagoon Mystic",
    "conversionRate": 0,
    "metaShare": 0.00010307684378704323
  },
  {
    "name": "Tovolar, Dire Overlord // Tovolar, the Midnight Scourge",
    "conversionRate": 0,
    "metaShare": 0.00005153842189352162
  },
  {
    "name": "The Pride of Hull Clade",
    "conversionRate": 0,
    "metaShare": 0.00005153842189352162
  },
  {
    "name": "Ashaya, Soul of the Wild",
    "conversionRate": 0,
    "metaShare": 0.00010307684378704323
  },
  {
    "name": "Slimefoot, the Stowaway",
    "conversionRate": 0,
    "metaShare": 0.00010307684378704323
  },
  {
    "name": "Teysa, Orzhov Scion",
    "conversionRate": 0,
    "metaShare": 0.00010307684378704323
  },
  {
    "name": "Mazzy, Truesword Paladin",
    "conversionRate": 0,
    "metaShare": 0.00010307684378704323
  },
  {
    "name": "Mimeoplasm, Revered One",
    "conversionRate": 0,
    "metaShare": 0.00005153842189352162
  },
  {
    "name": "General Tazri",
    "conversionRate": 0,
    "metaShare": 0.00005153842189352162
  },
  {
    "name": "Sidisi, Brood Tyrant",
    "conversionRate": 0,
    "metaShare": 0.00005153842189352162
  },
  {
    "name": "Eluge, the Shoreless Sea",
    "conversionRate": 0,
    "metaShare": 0.00010307684378704323
  },
  {
    "name": "Marina Vendrell",
    "conversionRate": 0,
    "metaShare": 0.00005153842189352162
  },
  {
    "name": "Trazyn the Infinite",
    "conversionRate": 0.5,
    "metaShare": 0.00010307684378704323
  },
  {
    "name": "The Ancient One",
    "conversionRate": 0,
    "metaShare": 0.00005153842189352162
  },
  {
    "name": "Wolverine, Best There Is",
    "conversionRate": 0,
    "metaShare": 0.00005153842189352162
  },
  {
    "name": "Haunted One / Zellix, Sanity Flayer",
    "conversionRate": 0,
    "metaShare": 0.00005153842189352162
  },
  {
    "name": "Jin-Gitaxias, Progress Tyrant",
    "conversionRate": 0,
    "metaShare": 0.00005153842189352162
  },
  {
    "name": "Tasha, the Witch Queen",
    "conversionRate": 0,
    "metaShare": 0.00005153842189352162
  },
  {
    "name": "Wyleth, Soul of Steel",
    "conversionRate": 0,
    "metaShare": 0.00010307684378704323
  },
  {
    "name": "Bright-Palm, Soul Awakener",
    "conversionRate": 0,
    "metaShare": 0.00010307684378704323
  },
  {
    "name": "Nissa, Resurgent Animist",
    "conversionRate": 0,
    "metaShare": 0.00010307684378704323
  },
  {
    "name": "Queen Kayla bin-Kroog",
    "conversionRate": 0,
    "metaShare": 0.00010307684378704323
  },
  {
    "name": "Solphim, Mayhem Dominus",
    "conversionRate": 0,
    "metaShare": 0.00010307684378704323
  },
  {
    "name": "Indoraptor, the Perfect Hybrid",
    "conversionRate": 0.5,
    "metaShare": 0.00010307684378704323
  },
  {
    "name": "Jorn, God of Winter // Kaldring, the Rimestaff",
    "conversionRate": 0,
    "metaShare": 0.00010307684378704323
  },
  {
    "name": "Shroofus Sproutsire",
    "conversionRate": 0,
    "metaShare": 0.00010307684378704323
  },
  {
    "name": "Eruth, Tormented Prophet",
    "conversionRate": 0,
    "metaShare": 0.00010307684378704323
  },
  {
    "name": "Demonlord Belzenlok",
    "conversionRate": 0,
    "metaShare": 0.00010307684378704323
  },
  {
    "name": "Omnath, Locus of the Roil",
    "conversionRate": 0,
    "metaShare": 0.00010307684378704323
  },
  {
    "name": "Kiora, Sovereign of the Deep",
    "conversionRate": 0,
    "metaShare": 0.00010307684378704323
  },
  {
    "name": "Goro-Goro and Satoru",
    "conversionRate": 0,
    "metaShare": 0.00010307684378704323
  },
  {
    "name": "Caesar, Legion's Emperor",
    "conversionRate": 0,
    "metaShare": 0.00010307684378704323
  },
  {
    "name": "Rukarumel, Biologist",
    "conversionRate": 0,
    "metaShare": 0
  },
  {
    "name": "The Locust God",
    "conversionRate": 0,
    "metaShare": 0
  },
  {
    "name": "Kydele, Chosen of Kruphix / Rograkh, Son of Rohgahh",
    "conversionRate": 0.5,
    "metaShare": 0.00010307684378704323
  },
  {
    "name": "Vihaan, Goldwaker",
    "conversionRate": 0.5,
    "metaShare": 0.00010307684378704323
  },
  {
    "name": "Stenn, Paranoid Partisan",
    "conversionRate": 0,
    "metaShare": 0.00010307684378704323
  },
  {
    "name": "Teval, Arbiter of Virtue",
    "conversionRate": 0.5,
    "metaShare": 0.00010307684378704323
  },
  {
    "name": "K-9, Mark I / The War Doctor",
    "conversionRate": 0.5,
    "metaShare": 0.00010307684378704323
  },
  {
    "name": "Basim Ibn Ishaq",
    "conversionRate": 0,
    "metaShare": 0.00010307684378704323
  },
  {
    "name": "Belbe, Corrupted Observer",
    "conversionRate": 0,
    "metaShare": 0.00010307684378704323
  },
  {
    "name": "Kraum, Ludevic's Opus / Reyhan, Last of the Abzan",
    "conversionRate": 0,
    "metaShare": 0.00010307684378704323
  },
  {
    "name": "Alela, Artful Provocateur",
    "conversionRate": 0,
    "metaShare": 0.00010307684378704323
  },
  {
    "name": "Abdel Adrian, Gorion's Ward / Agent of the Iron Throne",
    "conversionRate": 0,
    "metaShare": 0.00010307684378704323
  },
  {
    "name": "Urza, Chief Artificer",
    "conversionRate": 0,
    "metaShare": 0.00010307684378704323
  },
  {
    "name": "Varragoth, Bloodsky Sire",
    "conversionRate": 0,
    "metaShare": 0.00005153842189352162
  },
  {
    "name": "Jhoira of the Ghitu",
    "conversionRate": 0,
    "metaShare": 0.00010307684378704323
  },
  {
    "name": "Gale, Waterdeep Prodigy / Scion of Halaster",
    "conversionRate": 0.5,
    "metaShare": 0.00010307684378704323
  },
  {
    "name": "Omnath, Locus of Rage",
    "conversionRate": 0,
    "metaShare": 0.00005153842189352162
  },
  {
    "name": "Feywild Visitor / Karlach, Fury of Avernus",
    "conversionRate": 0.5,
    "metaShare": 0.00010307684378704323
  },
  {
    "name": "Zacama, Primal Calamity",
    "conversionRate": 1,
    "metaShare": 0.00010307684378704323
  },
  {
    "name": "Muerra, Trash Tactician",
    "conversionRate": 0,
    "metaShare": 0.00010307684378704323
  },
  {
    "name": "Indominus Rex, Alpha",
    "conversionRate": 0,
    "metaShare": 0.00010307684378704323
  },
  {
    "name": "Kediss, Emberclaw Familiar / Tymna the Weaver",
    "conversionRate": 0.5,
    "metaShare": 0.00010307684378704323
  },
  {
    "name": "Lazav, the Multifarious",
    "conversionRate": 0,
    "metaShare": 0.00010307684378704323
  },
  {
    "name": "Tinybones, Bauble Burglar",
    "conversionRate": 0,
    "metaShare": 0.00005153842189352162
  },
  {
    "name": "Okaun, Eye of Chaos / Zndrsplt, Eye of Wisdom",
    "conversionRate": 0,
    "metaShare": 0.00010307684378704323
  },
  {
    "name": "Massacre Girl",
    "conversionRate": 0,
    "metaShare": 0.00005153842189352162
  },
  {
    "name": "Wayta, Trainer Prodigy",
    "conversionRate": 0,
    "metaShare": 0.00010307684378704323
  },
  {
    "name": "Saffi Eriksdotter",
    "conversionRate": 0.5,
    "metaShare": 0.00010307684378704323
  },
  {
    "name": "Karn, Legacy Reforged",
    "conversionRate": 0,
    "metaShare": 0.00005153842189352162
  },
  {
    "name": "Raff, Weatherlight Stalwart",
    "conversionRate": 0,
    "metaShare": 0.00005153842189352162
  },
  {
    "name": "Huatli, Poet of Unity // Roar of the Fifth People",
    "conversionRate": 0,
    "metaShare": 0.00010307684378704323
  },
  {
    "name": "The Cyber-Controller",
    "conversionRate": 0,
    "metaShare": 0.00010307684378704323
  },
  {
    "name": "Vadrok, Apex of Thunder",
    "conversionRate": 0,
    "metaShare": 0.00010307684378704323
  },
  {
    "name": "Strefan, Maurer Progenitor",
    "conversionRate": 0,
    "metaShare": 0.00010307684378704323
  },
  {
    "name": "Atogatog",
    "conversionRate": 0,
    "metaShare": 0.00010307684378704323
  },
  {
    "name": "Jace, Vryn's Prodigy // Jace, Telepath Unbound",
    "conversionRate": 0,
    "metaShare": 0.00010307684378704323
  },
  {
    "name": "Araumi of the Dead Tide",
    "conversionRate": 0,
    "metaShare": 0.00005153842189352162
  },
  {
    "name": "Felothar, Dawn of the Abzan",
    "conversionRate": 1,
    "metaShare": 0.00005153842189352162
  },
  {
    "name": "Taigam, Master Opportunist",
    "conversionRate": 0,
    "metaShare": 0.00005153842189352162
  },
  {
    "name": "Ghired, Mirror of the Wilds",
    "conversionRate": 0,
    "metaShare": 0.00010307684378704323
  },
  {
    "name": "Merieke Ri Berit",
    "conversionRate": 1,
    "metaShare": 0.00005153842189352162
  },
  {
    "name": "Silas Renn, Seeker Adept / Yoshimaru, Ever Faithful",
    "conversionRate": 0,
    "metaShare": 0.00005153842189352162
  },
  {
    "name": "Ao, the Dawn Sky",
    "conversionRate": 0.5,
    "metaShare": 0.00010307684378704323
  },
  {
    "name": "Otrimi, the Ever-Playful",
    "conversionRate": 0,
    "metaShare": 0.00010307684378704323
  },
  {
    "name": "Jodah, Archmage Eternal",
    "conversionRate": 0,
    "metaShare": 0.00010307684378704323
  },
  {
    "name": "Casal, Lurkwood Pathfinder // Casal, Pathbreaker Owlbear",
    "conversionRate": 0,
    "metaShare": 0.00010307684378704323
  },
  {
    "name": "Otharri, Suns' Glory",
    "conversionRate": 0,
    "metaShare": 0.00010307684378704323
  },
  {
    "name": "Jarad, Golgari Lich Lord",
    "conversionRate": 0,
    "metaShare": 0.00005153842189352162
  },
  {
    "name": "Vorinclex // The Grand Evolution",
    "conversionRate": 1,
    "metaShare": 0.00010307684378704323
  },
  {
    "name": "Szarekh, the Silent King",
    "conversionRate": 0.5,
    "metaShare": 0.00010307684378704323
  },
  {
    "name": "The Lord of Pain",
    "conversionRate": 0,
    "metaShare": 0.00005153842189352162
  },
  {
    "name": "Miara, Thorn of the Glade / Numa, Joraga Chieftain",
    "conversionRate": 0,
    "metaShare": 0.00005153842189352162
  },
  {
    "name": "Esior, Wardwing Familiar / Keleth, Sunmane Familiar",
    "conversionRate": 0,
    "metaShare": 0.00005153842189352162
  },
  {
    "name": "Agent of the Shadow Thieves / Rasaad yn Bashir",
    "conversionRate": 0,
    "metaShare": 0.00005153842189352162
  },
  {
    "name": "Lilysplash Mentor",
    "conversionRate": 0,
    "metaShare": 0.00005153842189352162
  },
  {
    "name": "Chandra's Spitfire",
    "conversionRate": 0,
    "metaShare": 0.00005153842189352162
  },
  {
    "name": "Feywild Visitor / Gut, True Soul Zealot",
    "conversionRate": 0,
    "metaShare": 0.00005153842189352162
  },
  {
    "name": "Juri, Master of the Revue",
    "conversionRate": 0,
    "metaShare": 0.00005153842189352162
  },
  {
    "name": "Scholar of the Ages",
    "conversionRate": 1,
    "metaShare": 0.00005153842189352162
  },
  {
    "name": "Floodgate",
    "conversionRate": 1,
    "metaShare": 0.00005153842189352162
  },
  {
    "name": "Abdel Adrian, Gorion's Ward / Street Urchin",
    "conversionRate": 1,
    "metaShare": 0.00005153842189352162
  },
  {
    "name": "Knotvine Mystic",
    "conversionRate": 1,
    "metaShare": 0.00005153842189352162
  },
  {
    "name": "Disciple of Deceit",
    "conversionRate": 1,
    "metaShare": 0.00005153842189352162
  },
  {
    "name": "Sprite Dragon",
    "conversionRate": 0,
    "metaShare": 0
  },
  {
    "name": "King of the Pride",
    "conversionRate": 0,
    "metaShare": 0
  },
  {
    "name": "Abdel Adrian, Gorion's Ward / Sword Coast Sailor",
    "conversionRate": 0,
    "metaShare": 0
  },
  {
    "name": "Kheru Goldkeeper",
    "conversionRate": 0,
    "metaShare": 0
  },
  {
    "name": "Mystic Enforcer",
    "conversionRate": 0,
    "metaShare": 0
  },
  {
    "name": "Stormclaw Rager",
    "conversionRate": 0,
    "metaShare": 0
  },
  {
    "name": "Vhal, Candlekeep Researcher",
    "conversionRate": 0,
    "metaShare": 0.00005153842189352162
  },
  {
    "name": "Ad Nauseam",
    "conversionRate": 1,
    "metaShare": 0.00005153842189352162
  },
  {
    "name": "Young Pyromancer",
    "conversionRate": 0,
    "metaShare": 0
  },
  {
    "name": "Ley Weaver / Lore Weaver",
    "conversionRate": 0,
    "metaShare": 0
  },
  {
    "name": "Winding Constrictor",
    "conversionRate": 0,
    "metaShare": 0.00005153842189352162
  },
  {
    "name": "Third Path Iconoclast",
    "conversionRate": 1,
    "metaShare": 0.00005153842189352162
  },
  {
    "name": "Oji, the Exquisite Blade",
    "conversionRate": 1,
    "metaShare": 0.00005153842189352162
  },
  {
    "name": "Bruna, Light of Alabaster",
    "conversionRate": 0,
    "metaShare": 0.00005153842189352162
  },
  {
    "name": "Loyal Apprentice",
    "conversionRate": 0,
    "metaShare": 0.00005153842189352162
  },
  {
    "name": "Empyrean Eagle",
    "conversionRate": 0,
    "metaShare": 0.00005153842189352162
  },
  {
    "name": "Hollow Marauder",
    "conversionRate": 0,
    "metaShare": 0
  },
  {
    "name": "Rilsa Rael, Kingpin",
    "conversionRate": 0,
    "metaShare": 0.00005153842189352162
  },
  {
    "name": "Unctus, Grand Metatect",
    "conversionRate": 0,
    "metaShare": 0.00005153842189352162
  },
  {
    "name": "Kutzil, Malamet Exemplar",
    "conversionRate": 0,
    "metaShare": 0.00005153842189352162
  },
  {
    "name": "Shao Jun",
    "conversionRate": 0,
    "metaShare": 0.00005153842189352162
  },
  {
    "name": "Lazav, Familiar Stranger",
    "conversionRate": 0,
    "metaShare": 0
  },
  {
    "name": "Lagomos, Hand of Hatred",
    "conversionRate": 0,
    "metaShare": 0.00005153842189352162
  },
  {
    "name": "Venser, Corpse Puppet",
    "conversionRate": 0,
    "metaShare": 0.00005153842189352162
  },
  {
    "name": "Shanid, Sleepers' Scourge",
    "conversionRate": 0,
    "metaShare": 0.00005153842189352162
  },
  {
    "name": "Daxos of Meletis",
    "conversionRate": 0,
    "metaShare": 0
  },
  {
    "name": "Grothama, All-Devouring",
    "conversionRate": 0,
    "metaShare": 0.00005153842189352162
  },
  {
    "name": "Grenzo, Havoc Raiser",
    "conversionRate": 0,
    "metaShare": 0.00005153842189352162
  },
  {
    "name": "Mishra, Artificer Prodigy",
    "conversionRate": 0,
    "metaShare": 0.00005153842189352162
  },
  {
    "name": "Treebeard, Gracious Host",
    "conversionRate": 0,
    "metaShare": 0.00005153842189352162
  },
  {
    "name": "Nadier, Agent of the Duskenel / Thrasios, Triton Hero",
    "conversionRate": 0,
    "metaShare": 0.00005153842189352162
  },
  {
    "name": "Anhelo, the Painter",
    "conversionRate": 0,
    "metaShare": 0.00005153842189352162
  },
  {
    "name": "Sarah Jane Smith / The Fourth Doctor",
    "conversionRate": 0,
    "metaShare": 0.00005153842189352162
  },
  {
    "name": "Cecily, Haunted Mage",
    "conversionRate": 0,
    "metaShare": 0.00005153842189352162
  },
  {
    "name": "Armix, Filigree Thrasher / Tymna the Weaver",
    "conversionRate": 0,
    "metaShare": 0.00005153842189352162
  },
  {
    "name": "The Mycotyrant",
    "conversionRate": 0,
    "metaShare": 0.00005153842189352162
  },
  {
    "name": "Kianne, Dean of Substance // Imbraham, Dean of Theory",
    "conversionRate": 0,
    "metaShare": 0.00005153842189352162
  },
  {
    "name": "Hanna, Ship's Navigator",
    "conversionRate": 0,
    "metaShare": 0
  },
  {
    "name": "Malcolm, Keen-Eyed Navigator / Thrasios, Triton Hero",
    "conversionRate": 0,
    "metaShare": 0
  },
  {
    "name": "Myra the Magnificent",
    "conversionRate": 0,
    "metaShare": 0.00005153842189352162
  },
  {
    "name": "Agent of the Iron Throne / Jaheira, Friend of the Forest",
    "conversionRate": 0,
    "metaShare": 0.00005153842189352162
  },
  {
    "name": "Gwendlyn Di Corci",
    "conversionRate": 0,
    "metaShare": 0.00005153842189352162
  },
  {
    "name": "Livaan, Cultist of Tiamat / Sword Coast Sailor",
    "conversionRate": 0,
    "metaShare": 0.00005153842189352162
  },
  {
    "name": "The Speed Demon",
    "conversionRate": 0,
    "metaShare": 0.00005153842189352162
  },
  {
    "name": "Mortarion, Daemon Primarch",
    "conversionRate": 0,
    "metaShare": 0.00005153842189352162
  },
  {
    "name": "Estrid, the Masked",
    "conversionRate": 0,
    "metaShare": 0.00005153842189352162
  },
  {
    "name": "Jan Jansen, Chaos Crafter",
    "conversionRate": 0,
    "metaShare": 0.00005153842189352162
  },
  {
    "name": "Erinis, Gloom Stalker / Guild Artisan",
    "conversionRate": 0,
    "metaShare": 0
  },
  {
    "name": "Rose, Cutthroat Raider",
    "conversionRate": 0,
    "metaShare": 0.00005153842189352162
  },
  {
    "name": "Agent of the Iron Throne / Volo, Itinerant Scholar",
    "conversionRate": 1,
    "metaShare": 0.00005153842189352162
  },
  {
    "name": "Seton, Krosan Protector",
    "conversionRate": 0,
    "metaShare": 0.00005153842189352162
  },
  {
    "name": "Plargg, Dean of Chaos // Augusta, Dean of Order",
    "conversionRate": 0,
    "metaShare": 0.00005153842189352162
  },
  {
    "name": "Sheoldred, the Apocalypse",
    "conversionRate": 0,
    "metaShare": 0.00005153842189352162
  },
  {
    "name": "Kellan, Daring Traveler // Journey On",
    "conversionRate": 0,
    "metaShare": 0.00005153842189352162
  },
  {
    "name": "Tetzin, Gnome Champion // The Golden-Gear Colossus",
    "conversionRate": 0,
    "metaShare": 0.00005153842189352162
  },
  {
    "name": "Ghost of Ramirez DePietro / Tymna the Weaver",
    "conversionRate": 0,
    "metaShare": 0.00005153842189352162
  },
  {
    "name": "Karn, Silver Golem",
    "conversionRate": 1,
    "metaShare": 0.00005153842189352162
  },
  {
    "name": "Arahbo, the First Fang",
    "conversionRate": 1,
    "metaShare": 0.00005153842189352162
  },
  {
    "name": "Zaxara, the Exemplary",
    "conversionRate": 0,
    "metaShare": 0.00005153842189352162
  },
  {
    "name": "Tymna the Weaver / Yoshimaru, Ever Faithful",
    "conversionRate": 0,
    "metaShare": 0.00005153842189352162
  },
  {
    "name": "Karador, Ghost Chieftain",
    "conversionRate": 1,
    "metaShare": 0.00005153842189352162
  },
  {
    "name": "Gale, Waterdeep Prodigy / Street Urchin",
    "conversionRate": 0,
    "metaShare": 0.00005153842189352162
  },
  {
    "name": "Toralf, God of Fury // Toralf's Hammer",
    "conversionRate": 0,
    "metaShare": 0.00005153842189352162
  },
  {
    "name": "Kykar, Zephyr Awakener",
    "conversionRate": 0,
    "metaShare": 0.00005153842189352162
  },
  {
    "name": "Ryan Sinclair / The War Doctor",
    "conversionRate": 0,
    "metaShare": 0.00005153842189352162
  },
  {
    "name": "Flamewar, Brash Veteran // Flamewar, Streetwise Operative",
    "conversionRate": 0,
    "metaShare": 0.00005153842189352162
  },
  {
    "name": "Aisha of Sparks and Smoke",
    "conversionRate": 0,
    "metaShare": 0.00005153842189352162
  },
  {
    "name": "Francisco, Fowl Marauder / Reyhan, Last of the Abzan",
    "conversionRate": 0,
    "metaShare": 0.00005153842189352162
  },
  {
    "name": "Taigam, Ojutai Master",
    "conversionRate": 0,
    "metaShare": 0.00005153842189352162
  },
  {
    "name": "Nin, the Pain Artist",
    "conversionRate": 0,
    "metaShare": 0.00005153842189352162
  },
  {
    "name": "Taii Wakeen, Perfect Shot",
    "conversionRate": 0,
    "metaShare": 0.00005153842189352162
  },
  {
    "name": "Arahbo, Roar of the World",
    "conversionRate": 0,
    "metaShare": 0.00005153842189352162
  },
  {
    "name": "Dargo, the Shipwrecker / Tevesh Szat, Doom of Fools",
    "conversionRate": 1,
    "metaShare": 0.00005153842189352162
  },
  {
    "name": "Gisa and Geralf",
    "conversionRate": 0,
    "metaShare": 0.00005153842189352162
  },
  {
    "name": "Kitt Kanto, Mayhem Diva",
    "conversionRate": 0,
    "metaShare": 0.00005153842189352162
  },
  {
    "name": "Commissar Severina Raine",
    "conversionRate": 0,
    "metaShare": 0.00005153842189352162
  },
  {
    "name": "Arna Kennerüd, Skycaptain",
    "conversionRate": 0,
    "metaShare": 0.00005153842189352162
  },
  {
    "name": "Clement, the Worrywort",
    "conversionRate": 0,
    "metaShare": 0.00005153842189352162
  },
  {
    "name": "Sidar Kondo of Jamuraa / Tymna the Weaver",
    "conversionRate": 0,
    "metaShare": 0.00005153842189352162
  },
  {
    "name": "Kambal, Consul of Allocation",
    "conversionRate": 0,
    "metaShare": 0.00005153842189352162
  },
  {
    "name": "Abaddon the Despoiler",
    "conversionRate": 0,
    "metaShare": 0.00005153842189352162
  },
  {
    "name": "Firkraag, Cunning Instigator",
    "conversionRate": 0,
    "metaShare": 0.00005153842189352162
  },
  {
    "name": "Malcolm, Keen-Eyed Navigator / Tevesh Szat, Doom of Fools",
    "conversionRate": 0,
    "metaShare": 0
  },
  {
    "name": "The Swarmlord",
    "conversionRate": 0,
    "metaShare": 0.00005153842189352162
  },
  {
    "name": "Freyalise, Llanowar's Fury",
    "conversionRate": 0,
    "metaShare": 0.00005153842189352162
  },
  {
    "name": "Malik, Grim Manipulator",
    "conversionRate": 0,
    "metaShare": 0.00005153842189352162
  },
  {
    "name": "Melira, Sylvok Outcast",
    "conversionRate": 0,
    "metaShare": 0.00005153842189352162
  },
  {
    "name": "The Gitrog, Ravenous Ride",
    "conversionRate": 0,
    "metaShare": 0.00005153842189352162
  },
  {
    "name": "Miara, Thorn of the Glade / Thrasios, Triton Hero",
    "conversionRate": 0,
    "metaShare": 0.00005153842189352162
  },
  {
    "name": "Sen Triplets",
    "conversionRate": 1,
    "metaShare": 0.00005153842189352162
  },
  {
    "name": "Ardenn, Intrepid Archaeologist / Thrasios, Triton Hero",
    "conversionRate": 1,
    "metaShare": 0.00005153842189352162
  },
  {
    "name": "Johann, Apprentice Sorcerer",
    "conversionRate": 0,
    "metaShare": 0.00005153842189352162
  },
  {
    "name": "Bristly Bill, Spine Sower",
    "conversionRate": 0,
    "metaShare": 0.00005153842189352162
  },
  {
    "name": "Reyhan, Last of the Abzan / Tymna the Weaver",
    "conversionRate": 1,
    "metaShare": 0.00005153842189352162
  },
  {
    "name": "Bruse Tarl, Boorish Herder / Kodama of the East Tree",
    "conversionRate": 0,
    "metaShare": 0.00005153842189352162
  },
  {
    "name": "Rosheen Meanderer",
    "conversionRate": 0,
    "metaShare": 0
  },
  {
    "name": "Atla Palani, Nest Tender",
    "conversionRate": 0,
    "metaShare": 0
  },
  {
    "name": "Krark, the Thumbless / Sidar Kondo of Jamuraa",
    "conversionRate": 0,
    "metaShare": 0.00005153842189352162
  },
  {
    "name": "Phenax, God of Deception",
    "conversionRate": 1,
    "metaShare": 0.00005153842189352162
  },
  {
    "name": "Sidar Kondo of Jamuraa / Tevesh Szat, Doom of Fools",
    "conversionRate": 1,
    "metaShare": 0.00005153842189352162
  },
  {
    "name": "Volo, Guide to Monsters",
    "conversionRate": 0,
    "metaShare": 0.00005153842189352162
  },
  {
    "name": "Aragorn, King of Gondor",
    "conversionRate": 0,
    "metaShare": 0.00005153842189352162
  },
  {
    "name": "Selenia, Dark Angel",
    "conversionRate": 0,
    "metaShare": 0.00005153842189352162
  },
  {
    "name": "Grumgully, the Generous",
    "conversionRate": 0,
    "metaShare": 0
  },
  {
    "name": "Galea, Kindler of Hope",
    "conversionRate": 0,
    "metaShare": 0.00005153842189352162
  },
  {
    "name": "Livio, Oathsworn Sentinel / Tana, the Bloodsower",
    "conversionRate": 0,
    "metaShare": 0.00005153842189352162
  },
  {
    "name": "Ghired, Conclave Exile",
    "conversionRate": 0,
    "metaShare": 0.00005153842189352162
  },
  {
    "name": "Zeriam, Golden Wind",
    "conversionRate": 0,
    "metaShare": 0.00005153842189352162
  },
  {
    "name": "Greensleeves, Maro-Sorcerer",
    "conversionRate": 0,
    "metaShare": 0.00005153842189352162
  },
  {
    "name": "Ishai, Ojutai Dragonspeaker / Tana, the Bloodsower",
    "conversionRate": 0,
    "metaShare": 0.00005153842189352162
  },
  {
    "name": "Neera, Wild Mage",
    "conversionRate": 0,
    "metaShare": 0.00005153842189352162
  },
  {
    "name": "Kaervek, the Punisher",
    "conversionRate": 0,
    "metaShare": 0.00005153842189352162
  },
  {
    "name": "Sarulf, Realm Eater",
    "conversionRate": 0,
    "metaShare": 0.00005153842189352162
  },
  {
    "name": "Nylea, Keen-Eyed",
    "conversionRate": 1,
    "metaShare": 0.00005153842189352162
  },
  {
    "name": "Folk Hero / Volo, Itinerant Scholar",
    "conversionRate": 1,
    "metaShare": 0.00005153842189352162
  },
  {
    "name": "Mishra, Claimed by Gix",
    "conversionRate": 1,
    "metaShare": 0.00005153842189352162
  },
  {
    "name": "Nashi, Searcher in the Dark",
    "conversionRate": 1,
    "metaShare": 0.00005153842189352162
  },
  {
    "name": "Tor Wauki the Younger",
    "conversionRate": 0,
    "metaShare": 0.00005153842189352162
  },
  {
    "name": "Camellia, the Seedmiser",
    "conversionRate": 0,
    "metaShare": 0.00005153842189352162
  },
  {
    "name": "Grist, Voracious Larva // Grist, the Plague Swarm",
    "conversionRate": 0,
    "metaShare": 0.00005153842189352162
  },
  {
    "name": "Hardy Outlander / Karlach, Fury of Avernus",
    "conversionRate": 0,
    "metaShare": 0.00005153842189352162
  },
  {
    "name": "Damia, Sage of Stone",
    "conversionRate": 0,
    "metaShare": 0.00005153842189352162
  },
  {
    "name": "Greven, Predator Captain",
    "conversionRate": 0,
    "metaShare": 0.00005153842189352162
  },
  {
    "name": "Dargo, the Shipwrecker / Jeska, Thrice Reborn",
    "conversionRate": 0,
    "metaShare": 0.00005153842189352162
  },
  {
    "name": "Urza, Lord Protector",
    "conversionRate": 0,
    "metaShare": 0.00005153842189352162
  },
  {
    "name": "Cloakwood Hermit / Sivriss, Nightmare Speaker",
    "conversionRate": 0,
    "metaShare": 0.00005153842189352162
  },
  {
    "name": "Herigast, Erupting Nullkite",
    "conversionRate": 0,
    "metaShare": 0.00005153842189352162
  },
  {
    "name": "Hinata, Dawn-Crowned",
    "conversionRate": 0,
    "metaShare": 0.00005153842189352162
  },
  {
    "name": "Reyhan, Last of the Abzan / Vial Smasher the Fierce",
    "conversionRate": 0,
    "metaShare": 0.00005153842189352162
  },
  {
    "name": "Flaming Fist / Wilson, Refined Grizzly",
    "conversionRate": 0,
    "metaShare": 0.00005153842189352162
  },
  {
    "name": "Mr. House, President and CEO",
    "conversionRate": 0,
    "metaShare": 0
  },
  {
    "name": "Ojer Pakpatiq, Deepest Epoch // Temple of Cyclical Time",
    "conversionRate": 0,
    "metaShare": 0
  },
  {
    "name": "Alania, Divergent Storm",
    "conversionRate": 0,
    "metaShare": 0.00005153842189352162
  },
  {
    "name": "Shilgengar, Sire of Famine",
    "conversionRate": 0,
    "metaShare": 0.00005153842189352162
  },
  {
    "name": "Armix, Filigree Thrasher / Tevesh Szat, Doom of Fools",
    "conversionRate": 0,
    "metaShare": 0.00005153842189352162
  },
  {
    "name": "Kwain, Itinerant Meddler",
    "conversionRate": 0,
    "metaShare": 0.00005153842189352162
  },
  {
    "name": "Maha, Its Feathers Night",
    "conversionRate": 0,
    "metaShare": 0
  },
  {
    "name": "Millicent, Restless Revenant",
    "conversionRate": 0,
    "metaShare": 0
  },
  {
    "name": "Kamahl, Heart of Krosa / Kodama of the East Tree",
    "conversionRate": 1,
    "metaShare": 0.00005153842189352162
  },
  {
    "name": "Archangel Avacyn // Avacyn, the Purifier",
    "conversionRate": 0,
    "metaShare": 0
  },
  {
    "name": "Ratonhnhaké꞉ton",
    "conversionRate": 1,
    "metaShare": 0.00005153842189352162
  },
  {
    "name": "Hama Pashar, Ruin Seeker",
    "conversionRate": 0,
    "metaShare": 0.00005153842189352162
  },
  {
    "name": "Marchesa, the Black Rose",
    "conversionRate": 0,
    "metaShare": 0.00005153842189352162
  },
  {
    "name": "Desmond Miles",
    "conversionRate": 0,
    "metaShare": 0
  },
  {
    "name": "Leinore, Autumn Sovereign",
    "conversionRate": 0,
    "metaShare": 0.00005153842189352162
  },
  {
    "name": "Marvo, Deep Operative",
    "conversionRate": 0,
    "metaShare": 0
  },
  {
    "name": "Tazri, Beacon of Unity / Trazyn the Infinite",
    "conversionRate": 0,
    "metaShare": 0.00005153842189352162
  },
  {
    "name": "Extus, Oriq Overlord // Awaken the Blood Avatar",
    "conversionRate": 0,
    "metaShare": 0.00005153842189352162
  },
  {
    "name": "Kydele, Chosen of Kruphix / Vial Smasher the Fierce",
    "conversionRate": 1,
    "metaShare": 0.00005153842189352162
  },
  {
    "name": "Trelasarra, Moon Dancer",
    "conversionRate": 0,
    "metaShare": 0
  },
  {
    "name": "Ghalta, Primal Hunger",
    "conversionRate": 0,
    "metaShare": 0.00005153842189352162
  },
  {
    "name": "Lynde, Cheerful Tormentor",
    "conversionRate": 0,
    "metaShare": 0
  },
  {
    "name": "Saheeli, the Sun's Brilliance",
    "conversionRate": 1,
    "metaShare": 0.00005153842189352162
  },
  {
    "name": "Francisco, Fowl Marauder / Kodama of the East Tree",
    "conversionRate": 0,
    "metaShare": 0.00005153842189352162
  },
  {
    "name": "Feywild Visitor / Ganax, Astral Hunter",
    "conversionRate": 0,
    "metaShare": 0.00005153842189352162
  },
  {
    "name": "Urtet, Remnant of Memnarch",
    "conversionRate": 0,
    "metaShare": 0.00005153842189352162
  },
  {
    "name": "Éowyn, Lady of Rohan",
    "conversionRate": 0,
    "metaShare": 0
  },
  {
    "name": "Rashmi and Ragavan",
    "conversionRate": 0,
    "metaShare": 0
  },
  {
    "name": "Jared Carthalion",
    "conversionRate": 0,
    "metaShare": 0
  },
  {
    "name": "Zevlor, Elturel Exile",
    "conversionRate": 0,
    "metaShare": 0
  },
  {
    "name": "Zurgo, Thunder's Decree",
    "conversionRate": 0,
    "metaShare": 0
  },
  {
    "name": "Norin the Wary",
    "conversionRate": 0,
    "metaShare": 0.00005153842189352162
  },
  {
    "name": "Malcolm, Alluring Scoundrel",
    "conversionRate": 1,
    "metaShare": 0.00005153842189352162
  },
  {
    "name": "Peri Brown / The Sixth Doctor",
    "conversionRate": 0,
    "metaShare": 0.00005153842189352162
  },
  {
    "name": "Neriv, Heart of the Storm",
    "conversionRate": 0,
    "metaShare": 0.00005153842189352162
  },
  {
    "name": "Rendmaw, Creaking Nest",
    "conversionRate": 0,
    "metaShare": 0.00005153842189352162
  },
  {
    "name": "Master Chef / Vhal, Candlekeep Researcher",
    "conversionRate": 0,
    "metaShare": 0.00005153842189352162
  },
  {
    "name": "Rashmi, Eternities Crafter",
    "conversionRate": 1,
    "metaShare": 0.00005153842189352162
  },
  {
    "name": "Imskir Iron-Eater / Tetzin, Gnome Champion // The Golden-Gear Colossus",
    "conversionRate": 0,
    "metaShare": 0.00005153842189352162
  },
  {
    "name": "Urabrask, Heretic Praetor",
    "conversionRate": 0,
    "metaShare": 0.00005153842189352162
  },
  {
    "name": "Alesha, Who Smiles at Death",
    "conversionRate": 0,
    "metaShare": 0
  },
  {
    "name": "Cecily, Haunted Mage / Wernog, Rider's Chaplain",
    "conversionRate": 1,
    "metaShare": 0.00005153842189352162
  },
  {
    "name": "Ruby, Daring Tracker",
    "conversionRate": 1,
    "metaShare": 0.00005153842189352162
  },
  {
    "name": "Evereth, Viceroy of Plunder",
    "conversionRate": 0,
    "metaShare": 0.00005153842189352162
  },
  {
    "name": "Circu, Dimir Lobotomist",
    "conversionRate": 0,
    "metaShare": 0.00005153842189352162
  },
  {
    "name": "Jeska, Thrice Reborn / Yoshimaru, Ever Faithful",
    "conversionRate": 0,
    "metaShare": 0.00005153842189352162
  },
  {
    "name": "Djeru and Hazoret",
    "conversionRate": 1,
    "metaShare": 0.00005153842189352162
  },
  {
    "name": "Finneas, Ace Archer",
    "conversionRate": 0,
    "metaShare": 0.00005153842189352162
  },
  {
    "name": "Elminster",
    "conversionRate": 0,
    "metaShare": 0.00005153842189352162
  },
  {
    "name": "Mayael the Anima",
    "conversionRate": 0,
    "metaShare": 0.00005153842189352162
  },
  {
    "name": "The Scarab God",
    "conversionRate": 0,
    "metaShare": 0.00005153842189352162
  },
  {
    "name": "Havi, the All-Father",
    "conversionRate": 0,
    "metaShare": 0
  },
  {
    "name": "Galadriel, Elven-Queen",
    "conversionRate": 0,
    "metaShare": 0.00005153842189352162
  },
  {
    "name": "Noble Heritage / Wilson, Refined Grizzly",
    "conversionRate": 0,
    "metaShare": 0.00005153842189352162
  },
  {
    "name": "Samut, Voice of Dissent",
    "conversionRate": 0,
    "metaShare": 0.00005153842189352162
  },
  {
    "name": "Shu Yun, the Silent Tempest",
    "conversionRate": 0,
    "metaShare": 0.00005153842189352162
  },
  {
    "name": "Imskir Iron-Eater",
    "conversionRate": 0,
    "metaShare": 0.00005153842189352162
  },
  {
    "name": "Arcades, the Strategist",
    "conversionRate": 0,
    "metaShare": 0.00005153842189352162
  },
  {
    "name": "Tana, the Bloodsower / Tevesh Szat, Doom of Fools",
    "conversionRate": 0,
    "metaShare": 0
  },
  {
    "name": "Pia Nalaar, Consul of Revival",
    "conversionRate": 0,
    "metaShare": 0
  },
  {
    "name": "Bartolomé del Presidio",
    "conversionRate": 0,
    "metaShare": 0.00005153842189352162
  },
  {
    "name": "Gandalf the White",
    "conversionRate": 0,
    "metaShare": 0.00005153842189352162
  },
  {
    "name": "Zimone, All-Questioning",
    "conversionRate": 0,
    "metaShare": 0.00005153842189352162
  },
  {
    "name": "Quintorius, Field Historian",
    "conversionRate": 0,
    "metaShare": 0.00005153842189352162
  },
  {
    "name": "Terrian, World Tyrant",
    "conversionRate": 0,
    "metaShare": 0.00005153842189352162
  },
  {
    "name": "Judith, the Scourge Diva",
    "conversionRate": 0,
    "metaShare": 0.00005153842189352162
  },
  {
    "name": "Jin-Gitaxias // The Great Synthesis",
    "conversionRate": 0,
    "metaShare": 0.00005153842189352162
  },
  {
    "name": "Kellan, the Fae-Blooded // Birthright Boon",
    "conversionRate": 0,
    "metaShare": 0.00005153842189352162
  },
  {
    "name": "Ephara, God of the Polis",
    "conversionRate": 0,
    "metaShare": 0.00005153842189352162
  },
  {
    "name": "Brenard, Ginger Sculptor",
    "conversionRate": 0,
    "metaShare": 0.00005153842189352162
  },
  {
    "name": "Koma, World-Eater",
    "conversionRate": 0,
    "metaShare": 0.00005153842189352162
  },
  {
    "name": "Tomik, Wielder of Law",
    "conversionRate": 0,
    "metaShare": 0.00005153842189352162
  },
  {
    "name": "Eligeth, Crossroads Augur / Thrasios, Triton Hero",
    "conversionRate": 0,
    "metaShare": 0.00005153842189352162
  },
  {
    "name": "Ryan Sinclair / The Thirteenth Doctor",
    "conversionRate": 0,
    "metaShare": 0.00005153842189352162
  },
  {
    "name": "Chromium, the Mutable",
    "conversionRate": 0,
    "metaShare": 0.00005153842189352162
  },
  {
    "name": "Feldon of the Third Path",
    "conversionRate": 0,
    "metaShare": 0.00005153842189352162
  },
  {
    "name": "Amareth, the Lustrous",
    "conversionRate": 0,
    "metaShare": 0.00005153842189352162
  },
  {
    "name": "Kathril, Aspect Warper",
    "conversionRate": 0,
    "metaShare": 0.00005153842189352162
  },
  {
    "name": "Alesha, Who Laughs at Fate",
    "conversionRate": 0,
    "metaShare": 0.00005153842189352162
  },
  {
    "name": "Adeliz, the Cinder Wind",
    "conversionRate": 0,
    "metaShare": 0.00005153842189352162
  },
  {
    "name": "Sophia, Dogged Detective",
    "conversionRate": 0,
    "metaShare": 0.00005153842189352162
  },
  {
    "name": "Glissa Sunslayer",
    "conversionRate": 0,
    "metaShare": 0.00005153842189352162
  },
  {
    "name": "Charix, the Raging Isle",
    "conversionRate": 1,
    "metaShare": 0.00005153842189352162
  },
  {
    "name": "Kalamax, the Stormsire",
    "conversionRate": 0,
    "metaShare": 0.00005153842189352162
  },
  {
    "name": "Vishgraz, the Doomhive",
    "conversionRate": 0,
    "metaShare": 0.00005153842189352162
  },
  {
    "name": "Ashad, the Lone Cyberman",
    "conversionRate": 0,
    "metaShare": 0
  },
  {
    "name": "Shanna, Purifying Blade",
    "conversionRate": 0,
    "metaShare": 0.00005153842189352162
  },
  {
    "name": "Chainer, Dementia Master",
    "conversionRate": 0,
    "metaShare": 0.00005153842189352162
  },
  {
    "name": "Gonti, Lord of Luxury",
    "conversionRate": 0,
    "metaShare": 0
  },
  {
    "name": "Keleth, Sunmane Familiar / Yoshimaru, Ever Faithful",
    "conversionRate": 0,
    "metaShare": 0.00005153842189352162
  },
  {
    "name": "Tom Bombadil",
    "conversionRate": 0,
    "metaShare": 0.00005153842189352162
  },
  {
    "name": "Sword Coast Sailor / Wyll, Blade of Frontiers",
    "conversionRate": 0,
    "metaShare": 0.00005153842189352162
  },
  {
    "name": "Eshki Dragonclaw",
    "conversionRate": 0,
    "metaShare": 0.00005153842189352162
  },
  {
    "name": "Ureni, the Song Unending",
    "conversionRate": 0,
    "metaShare": 0
  },
  {
    "name": "Betor, Ancestor's Voice",
    "conversionRate": 1,
    "metaShare": 0.00005153842189352162
  },
  {
    "name": "River Song",
    "conversionRate": 0,
    "metaShare": 0
  },
  {
    "name": "Karametra, God of Harvests",
    "conversionRate": 0,
    "metaShare": 0.00005153842189352162
  },
  {
    "name": "Samut, the Driving Force",
    "conversionRate": 0,
    "metaShare": 0.00005153842189352162
  },
  {
    "name": "Kastral, the Windcrested",
    "conversionRate": 0,
    "metaShare": 0.00005153842189352162
  },
  {
    "name": "Nethroi, Apex of Death",
    "conversionRate": 0,
    "metaShare": 0.00005153842189352162
  },
  {
    "name": "Jenson Carthalion, Druid Exile",
    "conversionRate": 0,
    "metaShare": 0.00005153842189352162
  },
  {
    "name": "Yargle and Multani",
    "conversionRate": 0,
    "metaShare": 0.00005153842189352162
  },
  {
    "name": "Sram, Senior Edificer",
    "conversionRate": 0,
    "metaShare": 0.00005153842189352162
  },
  {
    "name": "The Infamous Cruelclaw",
    "conversionRate": 0,
    "metaShare": 0.00005153842189352162
  },
  {
    "name": "Magar of the Magic Strings",
    "conversionRate": 0,
    "metaShare": 0.00005153842189352162
  },
  {
    "name": "Torbran, Thane of Red Fell",
    "conversionRate": 0,
    "metaShare": 0
  },
  {
    "name": "Ghen, Arcanum Weaver",
    "conversionRate": 0,
    "metaShare": 0
  },
  {
    "name": "Ludevic, Necro-Alchemist / Tymna the Weaver",
    "conversionRate": 0,
    "metaShare": 0.00005153842189352162
  },
  {
    "name": "Krark, the Thumbless / Rograkh, Son of Rohgahh",
    "conversionRate": 0,
    "metaShare": 0.00005153842189352162
  },
  {
    "name": "Krark, the Thumbless / Kydele, Chosen of Kruphix",
    "conversionRate": 0,
    "metaShare": 0.00005153842189352162
  },
  {
    "name": "Arixmethes, Slumbering Isle",
    "conversionRate": 0,
    "metaShare": 0.00005153842189352162
  },
  {
    "name": "Bill the Pony",
    "conversionRate": 0,
    "metaShare": 0.00005153842189352162
  },
  {
    "name": "Sharuum the Hegemon",
    "conversionRate": 0,
    "metaShare": 0.00005153842189352162
  },
  {
    "name": "Phelia, Exuberant Shepherd",
    "conversionRate": 0,
    "metaShare": 0.00005153842189352162
  },
  {
    "name": "Ikra Shidiqi, the Usurper / Rograkh, Son of Rohgahh",
    "conversionRate": 0,
    "metaShare": 0.00005153842189352162
  },
  {
    "name": "Slurrk, All-Ingesting / Yoshimaru, Ever Faithful",
    "conversionRate": 0,
    "metaShare": 0.00005153842189352162
  },
  {
    "name": "Torsten, Founder of Benalia",
    "conversionRate": 0,
    "metaShare": 0.00005153842189352162
  },
  {
    "name": "Kyodai, Soul of Kamigawa",
    "conversionRate": 0,
    "metaShare": 0.00005153842189352162
  },
  {
    "name": "Brimaz, Blight of Oreskos",
    "conversionRate": 0,
    "metaShare": 0.00005153842189352162
  },
  {
    "name": "Kefnet the Mindful",
    "conversionRate": 0,
    "metaShare": 0.00005153842189352162
  },
  {
    "name": "Silas Renn, Seeker Adept / Vial Smasher the Fierce",
    "conversionRate": 0,
    "metaShare": 0.00005153842189352162
  },
  {
    "name": "Karlach, Fury of Avernus / Sword Coast Sailor",
    "conversionRate": 0,
    "metaShare": 0.00005153842189352162
  },
  {
    "name": "Themberchaud",
    "conversionRate": 0,
    "metaShare": 0.00005153842189352162
  },
  {
    "name": "The Master, Multiplied",
    "conversionRate": 0,
    "metaShare": 0.00005153842189352162
  },
  {
    "name": "Ziatora, the Incinerator",
    "conversionRate": 0,
    "metaShare": 0.00005153842189352162
  },
  {
    "name": "Calamity, Galloping Inferno",
    "conversionRate": 0,
    "metaShare": 0.00005153842189352162
  },
  {
    "name": "Kros, Defense Contractor",
    "conversionRate": 0,
    "metaShare": 0.00005153842189352162
  },
  {
    "name": "Shattergang Brothers",
    "conversionRate": 0,
    "metaShare": 0.00005153842189352162
  },
  {
    "name": "Ruhan of the Fomori",
    "conversionRate": 0,
    "metaShare": 0.00005153842189352162
  },
  {
    "name": "Mavinda, Students' Advocate",
    "conversionRate": 0,
    "metaShare": 0.00005153842189352162
  },
  {
    "name": "Gix, Yawgmoth Praetor",
    "conversionRate": 0,
    "metaShare": 0.00005153842189352162
  },
  {
    "name": "Naru Meha, Master Wizard",
    "conversionRate": 0,
    "metaShare": 0
  },
  {
    "name": "Kami of the Crescent Moon",
    "conversionRate": 0,
    "metaShare": 0
  },
  {
    "name": "Karlov of the Ghost Council",
    "conversionRate": 0,
    "metaShare": 0
  },
  {
    "name": "Y'shtola, Night's Blessed",
    "conversionRate": 0,
    "metaShare": 0
  },
  {
    "name": "Phelddagrif",
    "conversionRate": 0,
    "metaShare": 0.00005153842189352162
  },
  {
    "name": "Kadena, Slinking Sorcerer",
    "conversionRate": 0,
    "metaShare": 0.00005153842189352162
  },
  {
    "name": "Tawnos, Solemn Survivor",
    "conversionRate": 0,
    "metaShare": 0
  },
  {
    "name": "Ramos, Dragon Engine",
    "conversionRate": 0,
    "metaShare": 0
  }
]}
