{"lastUpdated": "2025-02-18T00:48:40Z", "data": [
  {
    "name": "Thrasios, Triton Hero / Tymna the Weaver",
    "conversionRate": 0.27631578947368424,
    "metaShare": 0.05019815059445178
  },
  {
    "name": "Kinnan, Bonder Prodigy",
    "conversionRate": 0.30210325047801145,
    "metaShare": 0.04318031704095112
  },
  {
    "name": "Kraum, Ludevic's Opus / Tymna the Weaver",
    "conversionRate": 0.4163424124513619,
    "metaShare": 0.042437252311756934
  },
  {
    "name": "Sisay, Weatherlight Captain",
    "conversionRate": 0.29411764705882354,
    "metaShare": 0.022457067371202115
  },
  {
    "name": "Rograkh, Son of Rohgahh / Silas Renn, Seeker Adept",
    "conversionRate": 0.2751937984496124,
    "metaShare": 0.02130118890356671
  },
  {
    "name": "Magda, Brazen Outlaw",
    "conversionRate": 0.2619047619047619,
    "metaShare": 0.017338177014531043
  },
  {
    "name": "Tivit, Seller of Secrets",
    "conversionRate": 0.28169014084507044,
    "metaShare": 0.017585865257595774
  },
  {
    "name": "Rograkh, Son of Rohgahh / Thrasios, Triton Hero",
    "conversionRate": 0.29949238578680204,
    "metaShare": 0.016264861294583884
  },
  {
    "name": "Yuriko, the Tiger's Shadow",
    "conversionRate": 0.17058823529411765,
    "metaShare": 0.014035667107001321
  },
  {
    "name": "Najeela, the Blade-Blossom",
    "conversionRate": 0.271523178807947,
    "metaShare": 0.012466974900924703
  },
  {
    "name": "Kenrith, the Returned King",
    "conversionRate": 0.30158730158730157,
    "metaShare": 0.010402906208718626
  },
  {
    "name": "Glarb, Calamity's Augur",
    "conversionRate": 0.2288135593220339,
    "metaShare": 0.009742404227212682
  },
  {
    "name": "Derevi, Empyrial Tactician",
    "conversionRate": 0.2072072072072072,
    "metaShare": 0.00916446499339498
  },
  {
    "name": "Atraxa, Grand Unifier",
    "conversionRate": 0.2909090909090909,
    "metaShare": 0.009081902245706737
  },
  {
    "name": "Malcolm, Keen-Eyed Navigator / Vial Smasher the Fierce",
    "conversionRate": 0.24299065420560748,
    "metaShare": 0.008834214002642008
  },
  {
    "name": "Stella Lee, Wild Card",
    "conversionRate": 0.11224489795918367,
    "metaShare": 0.00809114927344782
  },
  {
    "name": "Talion, the Kindly Lord",
    "conversionRate": 0.21505376344086022,
    "metaShare": 0.007678335535006605
  },
  {
    "name": "Ob Nixilis, Captive Kingpin",
    "conversionRate": 0.27,
    "metaShare": 0.008256274768824307
  },
  {
    "name": "Krark, the Thumbless / Sakashima of a Thousand Faces",
    "conversionRate": 0.25842696629213485,
    "metaShare": 0.007348084544253633
  },
  {
    "name": "Tayam, Luminous Enigma",
    "conversionRate": 0.32098765432098764,
    "metaShare": 0.006687582562747688
  },
  {
    "name": "Malcolm, Keen-Eyed Navigator / Tymna the Weaver",
    "conversionRate": 0.25,
    "metaShare": 0.005614266842800529
  },
  {
    "name": "The Master of Keys",
    "conversionRate": 0.16417910447761194,
    "metaShare": 0.005531704095112285
  },
  {
    "name": "Plagon, Lord of the Beach",
    "conversionRate": 0.1774193548387097,
    "metaShare": 0.00511889035667107
  },
  {
    "name": "Tevesh Szat, Doom of Fools / Thrasios, Triton Hero",
    "conversionRate": 0.265625,
    "metaShare": 0.005284015852047556
  },
  {
    "name": "Rocco, Cabaretti Caterer",
    "conversionRate": 0.2833333333333333,
    "metaShare": 0.004953764861294584
  },
  {
    "name": "Tameshi, Reality Architect",
    "conversionRate": 0.3157894736842105,
    "metaShare": 0.0047060766182298545
  },
  {
    "name": "Inalla, Archmage Ritualist",
    "conversionRate": 0.16363636363636364,
    "metaShare": 0.004540951122853369
  },
  {
    "name": "Winota, Joiner of Forces",
    "conversionRate": 0.19642857142857142,
    "metaShare": 0.004623513870541612
  },
  {
    "name": "Urza, Lord High Artificer",
    "conversionRate": 0.1568627450980392,
    "metaShare": 0.004210700132100396
  },
  {
    "name": "Shorikai, Genesis Engine",
    "conversionRate": 0.24074074074074073,
    "metaShare": 0.004458388375165125
  },
  {
    "name": "Marneus Calgar",
    "conversionRate": 0.2692307692307692,
    "metaShare": 0.0042932628797886395
  },
  {
    "name": "Etali, Primal Conqueror // Etali, Primal Sickness",
    "conversionRate": 0.20408163265306123,
    "metaShare": 0.00404557463672391
  },
  {
    "name": "Rakdos, the Muscle",
    "conversionRate": 0.34,
    "metaShare": 0.004128137384412154
  },
  {
    "name": "Ellivere of the Wild Court",
    "conversionRate": 0.225,
    "metaShare": 0.0033025099075297227
  },
  {
    "name": "Tana, the Bloodsower / Tymna the Weaver",
    "conversionRate": 0.3076923076923077,
    "metaShare": 0.0032199471598414794
  },
  {
    "name": "Dihada, Binder of Wills",
    "conversionRate": 0.3409090909090909,
    "metaShare": 0.003632760898282695
  },
  {
    "name": "The Gitrog Monster",
    "conversionRate": 0.2631578947368421,
    "metaShare": 0.0031373844121532365
  },
  {
    "name": "Krark, the Thumbless / Silas Renn, Seeker Adept",
    "conversionRate": 0.3333333333333333,
    "metaShare": 0.0034676354029062086
  },
  {
    "name": "Kediss, Emberclaw Familiar / Malcolm, Keen-Eyed Navigator",
    "conversionRate": 0.375,
    "metaShare": 0.0033025099075297227
  },
  {
    "name": "Zur the Enchanter",
    "conversionRate": 0.12121212121212122,
    "metaShare": 0.002724570673712021
  },
  {
    "name": "K'rrik, Son of Yawgmoth",
    "conversionRate": 0.3783783783783784,
    "metaShare": 0.0030548216644649935
  },
  {
    "name": "Francisco, Fowl Marauder / Thrasios, Triton Hero",
    "conversionRate": 0.35294117647058826,
    "metaShare": 0.0028071334214002644
  },
  {
    "name": "Elsha of the Infinite",
    "conversionRate": 0.3235294117647059,
    "metaShare": 0.0028071334214002644
  },
  {
    "name": "Esika, God of the Tree // The Prismatic Bridge",
    "conversionRate": 0.3142857142857143,
    "metaShare": 0.0028896961690885073
  },
  {
    "name": "Thrasios, Triton Hero / Vial Smasher the Fierce",
    "conversionRate": 0.14285714285714285,
    "metaShare": 0.0028896961690885073
  },
  {
    "name": "Tasigur, the Golden Fang",
    "conversionRate": 0.2,
    "metaShare": 0.002476882430647292
  },
  {
    "name": "Kodama of the East Tree / Tymna the Weaver",
    "conversionRate": 0.3870967741935484,
    "metaShare": 0.002559445178335535
  },
  {
    "name": "Niv-Mizzet, Parun",
    "conversionRate": 0.23333333333333334,
    "metaShare": 0.002476882430647292
  },
  {
    "name": "Malcolm, Keen-Eyed Navigator / Tana, the Bloodsower",
    "conversionRate": 0.2222222222222222,
    "metaShare": 0.0022291941875825626
  },
  {
    "name": "Korvold, Fae-Cursed King",
    "conversionRate": 0.27586206896551724,
    "metaShare": 0.002394319682959049
  },
  {
    "name": "Hashaton, Scarab's Fist",
    "conversionRate": 0.22727272727272727,
    "metaShare": 0.0018163804491413474
  },
  {
    "name": "Storm, Force of Nature",
    "conversionRate": 0.10714285714285714,
    "metaShare": 0.002311756935270806
  },
  {
    "name": "Krark, the Thumbless / Thrasios, Triton Hero",
    "conversionRate": 0.35714285714285715,
    "metaShare": 0.002311756935270806
  },
  {
    "name": "Niv-Mizzet, Visionary",
    "conversionRate": 0.2222222222222222,
    "metaShare": 0.0022291941875825626
  },
  {
    "name": "Jeska, Thrice Reborn / Tymna the Weaver",
    "conversionRate": 0.4074074074074074,
    "metaShare": 0.0022291941875825626
  },
  {
    "name": "Lumra, Bellow of the Woods",
    "conversionRate": 0.3076923076923077,
    "metaShare": 0.0021466314398943197
  },
  {
    "name": "Heliod, the Radiant Dawn // Heliod, the Warped Eclipse",
    "conversionRate": 0.2962962962962963,
    "metaShare": 0.0022291941875825626
  },
  {
    "name": "Breya, Etherium Shaper",
    "conversionRate": 0.15384615384615385,
    "metaShare": 0.0021466314398943197
  },
  {
    "name": "Godo, Bandit Warlord",
    "conversionRate": 0.47619047619047616,
    "metaShare": 0.0017338177014531043
  },
  {
    "name": "Raffine, Scheming Seer",
    "conversionRate": 0.3181818181818182,
    "metaShare": 0.0018163804491413474
  },
  {
    "name": "Kaalia of the Vast",
    "conversionRate": 0.2857142857142857,
    "metaShare": 0.0017338177014531043
  },
  {
    "name": "Yisan, the Wanderer Bard",
    "conversionRate": 0.21739130434782608,
    "metaShare": 0.0018989431968295905
  },
  {
    "name": "Chatterfang, Squirrel General",
    "conversionRate": 0.55,
    "metaShare": 0.0016512549537648614
  },
  {
    "name": "Animar, Soul of Elements",
    "conversionRate": 0.2631578947368421,
    "metaShare": 0.0015686922060766182
  },
  {
    "name": "Slicer, Hired Muscle // Slicer, High-Speed Antagonist",
    "conversionRate": 0.09523809523809523,
    "metaShare": 0.0017338177014531043
  },
  {
    "name": "Ral, Monsoon Mage // Ral, Leyline Prodigy",
    "conversionRate": 0.3684210526315789,
    "metaShare": 0.0015686922060766182
  },
  {
    "name": "The Wise Mothman",
    "conversionRate": 0.21052631578947367,
    "metaShare": 0.0015686922060766182
  },
  {
    "name": "Narset, Enlightened Exile",
    "conversionRate": 0.3181818181818182,
    "metaShare": 0.0018163804491413474
  },
  {
    "name": "Haldan, Avid Arcanist / Pako, Arcane Retriever",
    "conversionRate": 0.29411764705882354,
    "metaShare": 0.0014035667107001322
  },
  {
    "name": "Zirda, the Dawnwaker",
    "conversionRate": 0.35,
    "metaShare": 0.0016512549537648614
  },
  {
    "name": "Rowan, Scion of War",
    "conversionRate": 0.2222222222222222,
    "metaShare": 0.001486129458388375
  },
  {
    "name": "Marwyn, the Nurturer",
    "conversionRate": 0.17647058823529413,
    "metaShare": 0.0014035667107001322
  },
  {
    "name": "Omnath, Locus of Creation",
    "conversionRate": 0.17647058823529413,
    "metaShare": 0.0014035667107001322
  },
  {
    "name": "Flubs, the Fool",
    "conversionRate": 0.06666666666666667,
    "metaShare": 0.001238441215323646
  },
  {
    "name": "Yawgmoth, Thran Physician",
    "conversionRate": 0.26666666666666666,
    "metaShare": 0.001238441215323646
  },
  {
    "name": "Narset, Enlightened Master",
    "conversionRate": 0.47058823529411764,
    "metaShare": 0.0014035667107001322
  },
  {
    "name": "Baylen, the Haymaker",
    "conversionRate": 0,
    "metaShare": 0.0009081902245706737
  },
  {
    "name": "Krenko, Mob Boss",
    "conversionRate": 0.0625,
    "metaShare": 0.001321003963011889
  },
  {
    "name": "Sythis, Harvest's Hand",
    "conversionRate": 0.25,
    "metaShare": 0.0009907529722589167
  },
  {
    "name": "Rona, Herald of Invasion // Rona, Tolarian Obliterator",
    "conversionRate": 0.125,
    "metaShare": 0.001321003963011889
  },
  {
    "name": "Erinis, Gloom Stalker / Street Urchin",
    "conversionRate": 0.4666666666666667,
    "metaShare": 0.001238441215323646
  },
  {
    "name": "Jhoira, Weatherlight Captain",
    "conversionRate": 0.3333333333333333,
    "metaShare": 0.0009907529722589167
  },
  {
    "name": "Bjorna, Nightfall Alchemist / Wernog, Rider's Chaplain",
    "conversionRate": 0.3125,
    "metaShare": 0.001321003963011889
  },
  {
    "name": "Dargo, the Shipwrecker / Tymna the Weaver",
    "conversionRate": 0.3333333333333333,
    "metaShare": 0.001238441215323646
  },
  {
    "name": "Selvala, Heart of the Wilds",
    "conversionRate": 0.38461538461538464,
    "metaShare": 0.0010733157199471599
  },
  {
    "name": "Bruse Tarl, Boorish Herder / Thrasios, Triton Hero",
    "conversionRate": 0.3076923076923077,
    "metaShare": 0.0010733157199471599
  },
  {
    "name": "Zimone, Mystery Unraveler",
    "conversionRate": 0,
    "metaShare": 0.001155878467635403
  },
  {
    "name": "Jetmir, Nexus of Revels",
    "conversionRate": 0.21428571428571427,
    "metaShare": 0.001155878467635403
  },
  {
    "name": "Armix, Filigree Thrasher / Thrasios, Triton Hero",
    "conversionRate": 0.09090909090909091,
    "metaShare": 0.0009081902245706737
  },
  {
    "name": "Hazel of the Rootbloom",
    "conversionRate": 0,
    "metaShare": 0.0010733157199471599
  },
  {
    "name": "Marchesa, Dealer of Death",
    "conversionRate": 0.07142857142857142,
    "metaShare": 0.001155878467635403
  },
  {
    "name": "Emry, Lurker of the Loch",
    "conversionRate": 0.16666666666666666,
    "metaShare": 0.0009907529722589167
  },
  {
    "name": "Thrasios, Triton Hero / Yoshimaru, Ever Faithful",
    "conversionRate": 0.5384615384615384,
    "metaShare": 0.0010733157199471599
  },
  {
    "name": "Valgavoth, Harrower of Souls",
    "conversionRate": 0.2,
    "metaShare": 0.0008256274768824307
  },
  {
    "name": "Cazur, Ruthless Stalker / Ukkima, Stalking Shadow",
    "conversionRate": 0.07692307692307693,
    "metaShare": 0.0010733157199471599
  },
  {
    "name": "Hidetsugu and Kairi",
    "conversionRate": 0.2727272727272727,
    "metaShare": 0.0009081902245706737
  },
  {
    "name": "Minsc & Boo, Timeless Heroes",
    "conversionRate": 0.07692307692307693,
    "metaShare": 0.0010733157199471599
  },
  {
    "name": "Arcum Dagsson",
    "conversionRate": 0.4166666666666667,
    "metaShare": 0.0009907529722589167
  },
  {
    "name": "Kess, Dissident Mage",
    "conversionRate": 0.3333333333333333,
    "metaShare": 0.0007430647291941875
  },
  {
    "name": "Scion of the Ur-Dragon",
    "conversionRate": 0.08333333333333333,
    "metaShare": 0.0009907529722589167
  },
  {
    "name": "Orvar, the All-Form",
    "conversionRate": 0.09090909090909091,
    "metaShare": 0.0009081902245706737
  },
  {
    "name": "Tatyova, Benthic Druid",
    "conversionRate": 0,
    "metaShare": 0.0009081902245706737
  },
  {
    "name": "Zhulodok, Void Gorger",
    "conversionRate": 0.18181818181818182,
    "metaShare": 0.0009081902245706737
  },
  {
    "name": "Pantlaza, Sun-Favored",
    "conversionRate": 0.08333333333333333,
    "metaShare": 0.0009907529722589167
  },
  {
    "name": "Jhoira, Ageless Innovator",
    "conversionRate": 0.2,
    "metaShare": 0.0008256274768824307
  },
  {
    "name": "Iron Man, Titan of Innovation",
    "conversionRate": 0.09090909090909091,
    "metaShare": 0.0009081902245706737
  },
  {
    "name": "Rograkh, Son of Rohgahh / Tevesh Szat, Doom of Fools",
    "conversionRate": 0.18181818181818182,
    "metaShare": 0.0009081902245706737
  },
  {
    "name": "Helga, Skittish Seer",
    "conversionRate": 0.18181818181818182,
    "metaShare": 0.0009081902245706737
  },
  {
    "name": "Ezio Auditore da Firenze",
    "conversionRate": 0.1,
    "metaShare": 0.0008256274768824307
  },
  {
    "name": "Ishai, Ojutai Dragonspeaker / Jeska, Thrice Reborn",
    "conversionRate": 0.1111111111111111,
    "metaShare": 0.0007430647291941875
  },
  {
    "name": "Sefris of the Hidden Ways",
    "conversionRate": 0.1,
    "metaShare": 0.0008256274768824307
  },
  {
    "name": "Teysa Karlov",
    "conversionRate": 0.125,
    "metaShare": 0.0006605019815059445
  },
  {
    "name": "Galadriel, Light of Valinor",
    "conversionRate": 0.2,
    "metaShare": 0.0008256274768824307
  },
  {
    "name": "Oswald Fiddlebender",
    "conversionRate": 0.4,
    "metaShare": 0.0008256274768824307
  },
  {
    "name": "Zada, Hedron Grinder",
    "conversionRate": 0.3333333333333333,
    "metaShare": 0.0007430647291941875
  },
  {
    "name": "Ms. Bumbleflower",
    "conversionRate": 0.2,
    "metaShare": 0.0008256274768824307
  },
  {
    "name": "Liberator, Urza's Battlethopter",
    "conversionRate": 0.5,
    "metaShare": 0.0008256274768824307
  },
  {
    "name": "Chulane, Teller of Tales",
    "conversionRate": 0.2727272727272727,
    "metaShare": 0.0009081902245706737
  },
  {
    "name": "Dargo, the Shipwrecker / Silas Renn, Seeker Adept",
    "conversionRate": 0,
    "metaShare": 0.0008256274768824307
  },
  {
    "name": "Vohar, Vodalian Desecrator",
    "conversionRate": 0.3333333333333333,
    "metaShare": 0.0007430647291941875
  },
  {
    "name": "Evelyn, the Covetous",
    "conversionRate": 0.3333333333333333,
    "metaShare": 0.0007430647291941875
  },
  {
    "name": "Tamiyo, Inquisitive Student // Tamiyo, Seasoned Scholar",
    "conversionRate": 0.2222222222222222,
    "metaShare": 0.0007430647291941875
  },
  {
    "name": "Ratadrabik of Urborg",
    "conversionRate": 0.375,
    "metaShare": 0.0006605019815059445
  },
  {
    "name": "Xyris, the Writhing Storm",
    "conversionRate": 0,
    "metaShare": 0.0006605019815059445
  },
  {
    "name": "Captain America, First Avenger",
    "conversionRate": 0.125,
    "metaShare": 0.0006605019815059445
  },
  {
    "name": "Yidris, Maelstrom Wielder",
    "conversionRate": 0.4,
    "metaShare": 0.0008256274768824307
  },
  {
    "name": "Oloro, Ageless Ascetic",
    "conversionRate": 0.2222222222222222,
    "metaShare": 0.0007430647291941875
  },
  {
    "name": "The Pride of Hull Clade",
    "conversionRate": 0.25,
    "metaShare": 0.0006605019815059445
  },
  {
    "name": "Ojer Axonil, Deepest Might // Temple of Power",
    "conversionRate": 0.125,
    "metaShare": 0.0006605019815059445
  },
  {
    "name": "Six",
    "conversionRate": 0,
    "metaShare": 0.0007430647291941875
  },
  {
    "name": "Codie, Vociferous Codex",
    "conversionRate": 0.375,
    "metaShare": 0.0006605019815059445
  },
  {
    "name": "Sauron, the Dark Lord",
    "conversionRate": 0.2222222222222222,
    "metaShare": 0.0007430647291941875
  },
  {
    "name": "Kraum, Ludevic's Opus / Reyhan, Last of the Abzan",
    "conversionRate": 0.375,
    "metaShare": 0.0006605019815059445
  },
  {
    "name": "Tazri, Beacon of Unity",
    "conversionRate": 0.2222222222222222,
    "metaShare": 0.0007430647291941875
  },
  {
    "name": "Ashling, Flame Dancer",
    "conversionRate": 0,
    "metaShare": 0.0007430647291941875
  },
  {
    "name": "Captain Sisay",
    "conversionRate": 0.3333333333333333,
    "metaShare": 0.0007430647291941875
  },
  {
    "name": "Rograkh, Son of Rohgahh / Tymna the Weaver",
    "conversionRate": 0.2222222222222222,
    "metaShare": 0.0007430647291941875
  },
  {
    "name": "Disa the Restless",
    "conversionRate": 0.25,
    "metaShare": 0.0006605019815059445
  },
  {
    "name": "Akiri, Line-Slinger / Thrasios, Triton Hero",
    "conversionRate": 0.1111111111111111,
    "metaShare": 0.0007430647291941875
  },
  {
    "name": "Grist, the Hunger Tide",
    "conversionRate": 0.25,
    "metaShare": 0.0006605019815059445
  },
  {
    "name": "Dina, Soul Steeper",
    "conversionRate": 0,
    "metaShare": 0.0005779392338177015
  },
  {
    "name": "Winter, Cynical Opportunist",
    "conversionRate": 0,
    "metaShare": 0.0006605019815059445
  },
  {
    "name": "Yeva, Nature's Herald",
    "conversionRate": 0.2857142857142857,
    "metaShare": 0.0005779392338177015
  },
  {
    "name": "Aminatou, Veil Piercer",
    "conversionRate": 0.16666666666666666,
    "metaShare": 0.0004953764861294584
  },
  {
    "name": "Teshar, Ancestor's Apostle",
    "conversionRate": 0.42857142857142855,
    "metaShare": 0.0005779392338177015
  },
  {
    "name": "Anje Falkenrath",
    "conversionRate": 0.375,
    "metaShare": 0.0006605019815059445
  },
  {
    "name": "Rakdos, Lord of Riots",
    "conversionRate": 0.125,
    "metaShare": 0.0006605019815059445
  },
  {
    "name": "The Jolly Balloon Man",
    "conversionRate": 0,
    "metaShare": 0.0006605019815059445
  },
  {
    "name": "Dionus, Elvish Archdruid",
    "conversionRate": 0,
    "metaShare": 0.0006605019815059445
  },
  {
    "name": "Bladewing the Risen",
    "conversionRate": 0.16666666666666666,
    "metaShare": 0.0004953764861294584
  },
  {
    "name": "Hakbal of the Surging Soul",
    "conversionRate": 0,
    "metaShare": 0.0005779392338177015
  },
  {
    "name": "Morska, Undersea Sleuth",
    "conversionRate": 0,
    "metaShare": 0.0005779392338177015
  },
  {
    "name": "Voja, Jaws of the Conclave",
    "conversionRate": 0.2857142857142857,
    "metaShare": 0.0005779392338177015
  },
  {
    "name": "Lonis, Cryptozoologist",
    "conversionRate": 0,
    "metaShare": 0.0005779392338177015
  },
  {
    "name": "Feywild Visitor / Karlach, Fury of Avernus",
    "conversionRate": 0.16666666666666666,
    "metaShare": 0.0004953764861294584
  },
  {
    "name": "Cormela, Glamour Thief",
    "conversionRate": 0.14285714285714285,
    "metaShare": 0.0005779392338177015
  },
  {
    "name": "Rielle, the Everwise",
    "conversionRate": 0,
    "metaShare": 0.00041281373844121534
  },
  {
    "name": "Shalai and Hallar",
    "conversionRate": 0.14285714285714285,
    "metaShare": 0.0005779392338177015
  },
  {
    "name": "Minsc, Beloved Ranger",
    "conversionRate": 0.2857142857142857,
    "metaShare": 0.0005779392338177015
  },
  {
    "name": "The Master, Transcendent",
    "conversionRate": 0,
    "metaShare": 0.0005779392338177015
  },
  {
    "name": "Heliod, Sun-Crowned",
    "conversionRate": 0.16666666666666666,
    "metaShare": 0.0004953764861294584
  },
  {
    "name": "Nekusar, the Mindrazer",
    "conversionRate": 0.2,
    "metaShare": 0.00041281373844121534
  },
  {
    "name": "Prosper, Tome-Bound",
    "conversionRate": 0,
    "metaShare": 0.0005779392338177015
  },
  {
    "name": "The Infamous Cruelclaw",
    "conversionRate": 0.14285714285714285,
    "metaShare": 0.0005779392338177015
  },
  {
    "name": "Elmar, Ulvenwald Informant / Wernog, Rider's Chaplain",
    "conversionRate": 0.16666666666666666,
    "metaShare": 0.0004953764861294584
  },
  {
    "name": "Edric, Spymaster of Trest",
    "conversionRate": 0.3333333333333333,
    "metaShare": 0.0004953764861294584
  },
  {
    "name": "Lathril, Blade of the Elves",
    "conversionRate": 0,
    "metaShare": 0.00041281373844121534
  },
  {
    "name": "Marath, Will of the Wild",
    "conversionRate": 0,
    "metaShare": 0.00041281373844121534
  },
  {
    "name": "Raggadragga, Goreguts Boss",
    "conversionRate": 0.2,
    "metaShare": 0.00041281373844121534
  },
  {
    "name": "Vren, the Relentless",
    "conversionRate": 0.3333333333333333,
    "metaShare": 0.0004953764861294584
  },
  {
    "name": "Kona, Rescue Beastie",
    "conversionRate": 0.16666666666666666,
    "metaShare": 0.0004953764861294584
  },
  {
    "name": "K-9, Mark I / The Fourteenth Doctor",
    "conversionRate": 0.3333333333333333,
    "metaShare": 0.0004953764861294584
  },
  {
    "name": "Azami, Lady of Scrolls",
    "conversionRate": 0.25,
    "metaShare": 0.00033025099075297226
  },
  {
    "name": "Lotho, Corrupt Shirriff",
    "conversionRate": 0.16666666666666666,
    "metaShare": 0.0004953764861294584
  },
  {
    "name": "Kodama of the East Tree / Sakashima of a Thousand Faces",
    "conversionRate": 0.6,
    "metaShare": 0.00041281373844121534
  },
  {
    "name": "Dargo, the Shipwrecker / Thrasios, Triton Hero",
    "conversionRate": 0.4,
    "metaShare": 0.00041281373844121534
  },
  {
    "name": "Gyruda, Doom of Depths",
    "conversionRate": 0.3333333333333333,
    "metaShare": 0.0004953764861294584
  },
  {
    "name": "Aesi, Tyrant of Gyre Strait",
    "conversionRate": 0,
    "metaShare": 0.0004953764861294584
  },
  {
    "name": "Edward Kenway",
    "conversionRate": 0,
    "metaShare": 0.00041281373844121534
  },
  {
    "name": "Francisco, Fowl Marauder / Malcolm, Keen-Eyed Navigator",
    "conversionRate": 0,
    "metaShare": 0.00033025099075297226
  },
  {
    "name": "Caesar, Legion's Emperor",
    "conversionRate": 0,
    "metaShare": 0.0004953764861294584
  },
  {
    "name": "Roxanne, Starfall Savant",
    "conversionRate": 0.3333333333333333,
    "metaShare": 0.0004953764861294584
  },
  {
    "name": "Gonti, Canny Acquisitor",
    "conversionRate": 0,
    "metaShare": 0.0004953764861294584
  },
  {
    "name": "Brallin, Skyshark Rider / Shabraz, the Skyshark",
    "conversionRate": 0.25,
    "metaShare": 0.00033025099075297226
  },
  {
    "name": "Kambal, Profiteering Mayor",
    "conversionRate": 0,
    "metaShare": 0.00041281373844121534
  },
  {
    "name": "Abdel Adrian, Gorion's Ward / Candlekeep Sage",
    "conversionRate": 0,
    "metaShare": 0.00041281373844121534
  },
  {
    "name": "Aragorn, the Uniter",
    "conversionRate": 0,
    "metaShare": 0.00041281373844121534
  },
  {
    "name": "Breeches, Brazen Plunderer / Malcolm, Keen-Eyed Navigator",
    "conversionRate": 0.2,
    "metaShare": 0.00041281373844121534
  },
  {
    "name": "Thada Adel, Acquisitor",
    "conversionRate": 0.75,
    "metaShare": 0.00033025099075297226
  },
  {
    "name": "Lagrella, the Magpie",
    "conversionRate": 0,
    "metaShare": 0.00041281373844121534
  },
  {
    "name": "Ruric Thar, the Unbowed",
    "conversionRate": 0,
    "metaShare": 0.00033025099075297226
  },
  {
    "name": "Bruse Tarl, Boorish Herder / Malcolm, Keen-Eyed Navigator",
    "conversionRate": 0.2,
    "metaShare": 0.00041281373844121534
  },
  {
    "name": "Prossh, Skyraider of Kher",
    "conversionRate": 0.2,
    "metaShare": 0.00041281373844121534
  },
  {
    "name": "Jodah, the Unifier",
    "conversionRate": 0,
    "metaShare": 0.00041281373844121534
  },
  {
    "name": "Borborygmos and Fblthp",
    "conversionRate": 0.2,
    "metaShare": 0.00041281373844121534
  },
  {
    "name": "Fblthp, the Lost",
    "conversionRate": 0.3333333333333333,
    "metaShare": 0.0002476882430647292
  },
  {
    "name": "Cecily, Haunted Mage / Wernog, Rider's Chaplain",
    "conversionRate": 0.6666666666666666,
    "metaShare": 0.0002476882430647292
  },
  {
    "name": "Ghyrson Starn, Kelermorph",
    "conversionRate": 0.2,
    "metaShare": 0.00041281373844121534
  },
  {
    "name": "Thalia and The Gitrog Monster",
    "conversionRate": 0.2,
    "metaShare": 0.00041281373844121534
  },
  {
    "name": "Francisco, Fowl Marauder / Kraum, Ludevic's Opus",
    "conversionRate": 0.25,
    "metaShare": 0.00033025099075297226
  },
  {
    "name": "Silas Renn, Seeker Adept / Yoshimaru, Ever Faithful",
    "conversionRate": 0,
    "metaShare": 0.0002476882430647292
  },
  {
    "name": "The Ur-Dragon",
    "conversionRate": 0,
    "metaShare": 0.00033025099075297226
  },
  {
    "name": "Satya, Aetherflux Genius",
    "conversionRate": 0,
    "metaShare": 0.00041281373844121534
  },
  {
    "name": "Henzie \"Toolbox\" Torre",
    "conversionRate": 0,
    "metaShare": 0.0002476882430647292
  },
  {
    "name": "Dogmeat, Ever Loyal",
    "conversionRate": 0.2,
    "metaShare": 0.00041281373844121534
  },
  {
    "name": "Yuma, Proud Protector",
    "conversionRate": 0,
    "metaShare": 0.00041281373844121534
  },
  {
    "name": "Teferi, Temporal Archmage",
    "conversionRate": 0.4,
    "metaShare": 0.00041281373844121534
  },
  {
    "name": "Mizzix of the Izmagnus",
    "conversionRate": 0.5,
    "metaShare": 0.00033025099075297226
  },
  {
    "name": "Belbe, Corrupted Observer",
    "conversionRate": 0.3333333333333333,
    "metaShare": 0.0002476882430647292
  },
  {
    "name": "Kykar, Wind's Fury",
    "conversionRate": 1,
    "metaShare": 0.00016512549537648613
  },
  {
    "name": "Slimefoot and Squee",
    "conversionRate": 0.25,
    "metaShare": 0.00033025099075297226
  },
  {
    "name": "Loot, the Pathfinder",
    "conversionRate": 0.5,
    "metaShare": 0.00016512549537648613
  },
  {
    "name": "Tergrid, God of Fright // Tergrid's Lantern",
    "conversionRate": 0.2,
    "metaShare": 0.00041281373844121534
  },
  {
    "name": "Arthur, Marigold Knight",
    "conversionRate": 0,
    "metaShare": 0.0002476882430647292
  },
  {
    "name": "Muldrotha, the Gravetide",
    "conversionRate": 0,
    "metaShare": 0.0002476882430647292
  },
  {
    "name": "Anim Pakal, Thousandth Moon",
    "conversionRate": 0.25,
    "metaShare": 0.00033025099075297226
  },
  {
    "name": "Temmet, Naktamun's Will",
    "conversionRate": 0.25,
    "metaShare": 0.00033025099075297226
  },
  {
    "name": "Anzrag, the Quake-Mole",
    "conversionRate": 0.25,
    "metaShare": 0.00033025099075297226
  },
  {
    "name": "Atla Palani, Nest Tender",
    "conversionRate": 0,
    "metaShare": 0.0002476882430647292
  },
  {
    "name": "Jared Carthalion",
    "conversionRate": 0,
    "metaShare": 0.00033025099075297226
  },
  {
    "name": "Tinybones, Bauble Burglar",
    "conversionRate": 0,
    "metaShare": 0.00033025099075297226
  },
  {
    "name": "Sidar Jabari of Zhalfir",
    "conversionRate": 0,
    "metaShare": 0.0002476882430647292
  },
  {
    "name": "Old Stickfingers",
    "conversionRate": 0,
    "metaShare": 0.00033025099075297226
  },
  {
    "name": "Brago, King Eternal",
    "conversionRate": 0.5,
    "metaShare": 0.00016512549537648613
  },
  {
    "name": "Nicol Bolas, the Ravager // Nicol Bolas, the Arisen",
    "conversionRate": 0.3333333333333333,
    "metaShare": 0.0002476882430647292
  },
  {
    "name": "Sarah Jane Smith / The Fourth Doctor",
    "conversionRate": 0.3333333333333333,
    "metaShare": 0.0002476882430647292
  },
  {
    "name": "Purphoros, God of the Forge",
    "conversionRate": 0,
    "metaShare": 0.00033025099075297226
  },
  {
    "name": "Sakashima of a Thousand Faces / Tymna the Weaver",
    "conversionRate": 0,
    "metaShare": 0.00033025099075297226
  },
  {
    "name": "Miirym, Sentinel Wyrm",
    "conversionRate": 0,
    "metaShare": 0.00016512549537648613
  },
  {
    "name": "The Necrobloom",
    "conversionRate": 0,
    "metaShare": 0.00033025099075297226
  },
  {
    "name": "Rhys the Redeemed",
    "conversionRate": 0.25,
    "metaShare": 0.00033025099075297226
  },
  {
    "name": "Eivor, Battle-Ready",
    "conversionRate": 0,
    "metaShare": 0.0002476882430647292
  },
  {
    "name": "Hapatra, Vizier of Poisons",
    "conversionRate": 0.25,
    "metaShare": 0.00033025099075297226
  },
  {
    "name": "Eluge, the Shoreless Sea",
    "conversionRate": 0,
    "metaShare": 0.0002476882430647292
  },
  {
    "name": "Jacob Hauken, Inspector // Hauken's Insight",
    "conversionRate": 0.3333333333333333,
    "metaShare": 0.0002476882430647292
  },
  {
    "name": "Oskar, Rubbish Reclaimer",
    "conversionRate": 0,
    "metaShare": 0.00033025099075297226
  },
  {
    "name": "Edgar Markov",
    "conversionRate": 0,
    "metaShare": 0.00033025099075297226
  },
  {
    "name": "Ramos, Dragon Engine",
    "conversionRate": 0.25,
    "metaShare": 0.00033025099075297226
  },
  {
    "name": "Grolnok, the Omnivore",
    "conversionRate": 0.25,
    "metaShare": 0.00033025099075297226
  },
  {
    "name": "Baral, Chief of Compliance",
    "conversionRate": 0,
    "metaShare": 0.00033025099075297226
  },
  {
    "name": "Unesh, Criosphinx Sovereign",
    "conversionRate": 0,
    "metaShare": 0.0002476882430647292
  },
  {
    "name": "Bruse Tarl, Boorish Herder / Kamahl, Heart of Krosa",
    "conversionRate": 0.5,
    "metaShare": 0.00033025099075297226
  },
  {
    "name": "Ulalek, Fused Atrocity",
    "conversionRate": 0.3333333333333333,
    "metaShare": 0.0002476882430647292
  },
  {
    "name": "Coram, the Undertaker",
    "conversionRate": 0.5,
    "metaShare": 0.00016512549537648613
  },
  {
    "name": "Éowyn, Shieldmaiden",
    "conversionRate": 0,
    "metaShare": 0.00033025099075297226
  },
  {
    "name": "Anikthea, Hand of Erebos",
    "conversionRate": 0,
    "metaShare": 0.0002476882430647292
  },
  {
    "name": "Omo, Queen of Vesuva",
    "conversionRate": 0,
    "metaShare": 0.00033025099075297226
  },
  {
    "name": "Zimone, Paradox Sculptor",
    "conversionRate": 0,
    "metaShare": 0.0002476882430647292
  },
  {
    "name": "Frodo, Adventurous Hobbit / Sam, Loyal Attendant",
    "conversionRate": 0,
    "metaShare": 0.0002476882430647292
  },
  {
    "name": "Alexios, Deimos of Kosmos",
    "conversionRate": 0,
    "metaShare": 0.00033025099075297226
  },
  {
    "name": "Alania, Divergent Storm",
    "conversionRate": 0,
    "metaShare": 0.0002476882430647292
  },
  {
    "name": "Halana, Kessig Ranger / Tymna the Weaver",
    "conversionRate": 0,
    "metaShare": 0.00033025099075297226
  },
  {
    "name": "Reyhan, Last of the Abzan / Rograkh, Son of Rohgahh",
    "conversionRate": 0,
    "metaShare": 0.0002476882430647292
  },
  {
    "name": "Veyran, Voice of Duality",
    "conversionRate": 0,
    "metaShare": 0.0002476882430647292
  },
  {
    "name": "Zacama, Primal Calamity",
    "conversionRate": 0,
    "metaShare": 0.00033025099075297226
  },
  {
    "name": "Shroofus Sproutsire",
    "conversionRate": 0,
    "metaShare": 0.0002476882430647292
  },
  {
    "name": "Child of Alara",
    "conversionRate": 0,
    "metaShare": 0.00033025099075297226
  },
  {
    "name": "Rasputin Dreamweaver",
    "conversionRate": 0.3333333333333333,
    "metaShare": 0.0002476882430647292
  },
  {
    "name": "Zimone and Dina",
    "conversionRate": 0,
    "metaShare": 0.00016512549537648613
  },
  {
    "name": "Braids, Arisen Nightmare",
    "conversionRate": 0,
    "metaShare": 0.00033025099075297226
  },
  {
    "name": "Bello, Bard of the Brambles",
    "conversionRate": 0.3333333333333333,
    "metaShare": 0.0002476882430647292
  },
  {
    "name": "Ketramose, the New Dawn",
    "conversionRate": 0.3333333333333333,
    "metaShare": 0.0002476882430647292
  },
  {
    "name": "Giada, Font of Hope",
    "conversionRate": 0.25,
    "metaShare": 0.00033025099075297226
  },
  {
    "name": "Wick, the Whorled Mind",
    "conversionRate": 0.3333333333333333,
    "metaShare": 0.0002476882430647292
  },
  {
    "name": "Asmoranomardicadaistinaculdacar",
    "conversionRate": 0,
    "metaShare": 0.00016512549537648613
  },
  {
    "name": "Calix, Guided by Fate",
    "conversionRate": 0,
    "metaShare": 0.00016512549537648613
  },
  {
    "name": "Arabella, Abandoned Doll",
    "conversionRate": 0,
    "metaShare": 0.0002476882430647292
  },
  {
    "name": "Taii Wakeen, Perfect Shot",
    "conversionRate": 0,
    "metaShare": 0.0002476882430647292
  },
  {
    "name": "Ranar the Ever-Watchful",
    "conversionRate": 0,
    "metaShare": 0.0002476882430647292
  },
  {
    "name": "Cecily, Haunted Mage / Elmar, Ulvenwald Informant",
    "conversionRate": 0,
    "metaShare": 0.00016512549537648613
  },
  {
    "name": "Armix, Filigree Thrasher / Kraum, Ludevic's Opus",
    "conversionRate": 0,
    "metaShare": 0.0002476882430647292
  },
  {
    "name": "Urza, Chief Artificer",
    "conversionRate": 0.5,
    "metaShare": 0.00016512549537648613
  },
  {
    "name": "Marina Vendrell",
    "conversionRate": 0,
    "metaShare": 0.00016512549537648613
  },
  {
    "name": "Saruman, the White Hand",
    "conversionRate": 0,
    "metaShare": 0.0002476882430647292
  },
  {
    "name": "Liesa, Shroud of Dusk",
    "conversionRate": 0,
    "metaShare": 0.0002476882430647292
  },
  {
    "name": "Nymris, Oona's Trickster",
    "conversionRate": 0.3333333333333333,
    "metaShare": 0.0002476882430647292
  },
  {
    "name": "Nelly Borca, Impulsive Accuser",
    "conversionRate": 0,
    "metaShare": 0.00016512549537648613
  },
  {
    "name": "Francisco, Fowl Marauder / Rograkh, Son of Rohgahh",
    "conversionRate": 0,
    "metaShare": 0.00016512549537648613
  },
  {
    "name": "Kibo, Uktabi Prince",
    "conversionRate": 0,
    "metaShare": 0.0002476882430647292
  },
  {
    "name": "Narci, Fable Singer",
    "conversionRate": 0,
    "metaShare": 0.0002476882430647292
  },
  {
    "name": "Tor Wauki the Younger",
    "conversionRate": 0,
    "metaShare": 0.0002476882430647292
  },
  {
    "name": "Aminatou, the Fateshifter",
    "conversionRate": 0,
    "metaShare": 0.00016512549537648613
  },
  {
    "name": "Ardenn, Intrepid Archaeologist / Rograkh, Son of Rohgahh",
    "conversionRate": 0,
    "metaShare": 0.0002476882430647292
  },
  {
    "name": "Queza, Augur of Agonies",
    "conversionRate": 0,
    "metaShare": 0.00016512549537648613
  },
  {
    "name": "Teysa, Orzhov Scion",
    "conversionRate": 0,
    "metaShare": 0.00016512549537648613
  },
  {
    "name": "Daretti, Scrap Savant",
    "conversionRate": 0,
    "metaShare": 0.00016512549537648613
  },
  {
    "name": "Tovolar, Dire Overlord // Tovolar, the Midnight Scourge",
    "conversionRate": 0.3333333333333333,
    "metaShare": 0.0002476882430647292
  },
  {
    "name": "Omnath, Locus of All",
    "conversionRate": 0,
    "metaShare": 0.0002476882430647292
  },
  {
    "name": "Kraum, Ludevic's Opus / Tevesh Szat, Doom of Fools",
    "conversionRate": 0.3333333333333333,
    "metaShare": 0.0002476882430647292
  },
  {
    "name": "Malik, Grim Manipulator",
    "conversionRate": 0,
    "metaShare": 0.00008256274768824307
  },
  {
    "name": "Sliver Overlord",
    "conversionRate": 0,
    "metaShare": 0.0002476882430647292
  },
  {
    "name": "Francisco, Fowl Marauder / Ishai, Ojutai Dragonspeaker",
    "conversionRate": 0,
    "metaShare": 0.0002476882430647292
  },
  {
    "name": "Vishgraz, the Doomhive",
    "conversionRate": 0,
    "metaShare": 0.0002476882430647292
  },
  {
    "name": "Tiamat",
    "conversionRate": 0.3333333333333333,
    "metaShare": 0.0002476882430647292
  },
  {
    "name": "Zurgo and Ojutai",
    "conversionRate": 0.6666666666666666,
    "metaShare": 0.0002476882430647292
  },
  {
    "name": "Meria, Scholar of Antiquity",
    "conversionRate": 0,
    "metaShare": 0.00016512549537648613
  },
  {
    "name": "Ludevic, Necro-Alchemist / Tymna the Weaver",
    "conversionRate": 0.3333333333333333,
    "metaShare": 0.0002476882430647292
  },
  {
    "name": "Rukarumel, Biologist",
    "conversionRate": 0,
    "metaShare": 0.00016512549537648613
  },
  {
    "name": "Varina, Lich Queen",
    "conversionRate": 0.3333333333333333,
    "metaShare": 0.0002476882430647292
  },
  {
    "name": "Indoraptor, the Perfect Hybrid",
    "conversionRate": 0,
    "metaShare": 0.0002476882430647292
  },
  {
    "name": "Maelstrom Wanderer",
    "conversionRate": 0,
    "metaShare": 0.0002476882430647292
  },
  {
    "name": "Toxrill, the Corrosive",
    "conversionRate": 0,
    "metaShare": 0.00016512549537648613
  },
  {
    "name": "Grumgully, the Generous",
    "conversionRate": 0,
    "metaShare": 0.00016512549537648613
  },
  {
    "name": "Satoru, the Infiltrator",
    "conversionRate": 0,
    "metaShare": 0.00016512549537648613
  },
  {
    "name": "Rograkh, Son of Rohgahh / The Master of Keys",
    "conversionRate": 0.6666666666666666,
    "metaShare": 0.0002476882430647292
  },
  {
    "name": "Akiri, Line-Slinger / Malcolm, Keen-Eyed Navigator",
    "conversionRate": 0.3333333333333333,
    "metaShare": 0.0002476882430647292
  },
  {
    "name": "Niv-Mizzet Reborn",
    "conversionRate": 0,
    "metaShare": 0.00008256274768824307
  },
  {
    "name": "Zinnia, Valley's Voice",
    "conversionRate": 0.5,
    "metaShare": 0.00016512549537648613
  },
  {
    "name": "Magus Lucea Kane",
    "conversionRate": 0,
    "metaShare": 0.00016512549537648613
  },
  {
    "name": "Gisa, Glorious Resurrector",
    "conversionRate": 0,
    "metaShare": 0.00016512549537648613
  },
  {
    "name": "Bria, Riptide Rogue",
    "conversionRate": 0,
    "metaShare": 0.0002476882430647292
  },
  {
    "name": "Osgir, the Reconstructor",
    "conversionRate": 0.3333333333333333,
    "metaShare": 0.0002476882430647292
  },
  {
    "name": "Naru Meha, Master Wizard",
    "conversionRate": 0,
    "metaShare": 0.00016512549537648613
  },
  {
    "name": "Kroxa, Titan of Death's Hunger",
    "conversionRate": 0.5,
    "metaShare": 0.00016512549537648613
  },
  {
    "name": "Sen Triplets",
    "conversionRate": 0,
    "metaShare": 0.00016512549537648613
  },
  {
    "name": "Sivitri, Dragon Master",
    "conversionRate": 1,
    "metaShare": 0.00008256274768824307
  },
  {
    "name": "Ardenn, Intrepid Archaeologist / Tana, the Bloodsower",
    "conversionRate": 0,
    "metaShare": 0.00016512549537648613
  },
  {
    "name": "Clavileño, First of the Blessed",
    "conversionRate": 0,
    "metaShare": 0.0002476882430647292
  },
  {
    "name": "Kyodai, Soul of Kamigawa",
    "conversionRate": 0,
    "metaShare": 0.00016512549537648613
  },
  {
    "name": "Kozilek, the Great Distortion",
    "conversionRate": 0,
    "metaShare": 0.0002476882430647292
  },
  {
    "name": "Light-Paws, Emperor's Voice",
    "conversionRate": 0,
    "metaShare": 0.00016512549537648613
  },
  {
    "name": "Lazav, the Multifarious",
    "conversionRate": 0,
    "metaShare": 0.00008256274768824307
  },
  {
    "name": "Leonardo da Vinci",
    "conversionRate": 0,
    "metaShare": 0.00016512549537648613
  },
  {
    "name": "Cynette, Jelly Drover",
    "conversionRate": 0,
    "metaShare": 0.00016512549537648613
  },
  {
    "name": "Atraxa, Praetors' Voice",
    "conversionRate": 0,
    "metaShare": 0.00008256274768824307
  },
  {
    "name": "Archelos, Lagoon Mystic",
    "conversionRate": 0.5,
    "metaShare": 0.00016512549537648613
  },
  {
    "name": "Sram, Senior Edificer",
    "conversionRate": 0,
    "metaShare": 0.00016512549537648613
  },
  {
    "name": "Urtet, Remnant of Memnarch",
    "conversionRate": 0,
    "metaShare": 0.00008256274768824307
  },
  {
    "name": "Mr. Foxglove",
    "conversionRate": 0,
    "metaShare": 0.00016512549537648613
  },
  {
    "name": "Lavinia, Azorius Renegade",
    "conversionRate": 0,
    "metaShare": 0.00016512549537648613
  },
  {
    "name": "Obeka, Splitter of Seconds",
    "conversionRate": 0,
    "metaShare": 0.00016512549537648613
  },
  {
    "name": "Niko, Light of Hope",
    "conversionRate": 0,
    "metaShare": 0.00016512549537648613
  },
  {
    "name": "Pramikon, Sky Rampart",
    "conversionRate": 0,
    "metaShare": 0
  },
  {
    "name": "Finneas, Ace Archer",
    "conversionRate": 0,
    "metaShare": 0.00008256274768824307
  },
  {
    "name": "Fynn, the Fangbearer",
    "conversionRate": 0,
    "metaShare": 0.00016512549537648613
  },
  {
    "name": "Kodama of the East Tree / Toggo, Goblin Weaponsmith",
    "conversionRate": 0,
    "metaShare": 0.00016512549537648613
  },
  {
    "name": "Savra, Queen of the Golgari",
    "conversionRate": 0,
    "metaShare": 0.00016512549537648613
  },
  {
    "name": "Sakashima of a Thousand Faces / Vial Smasher the Fierce",
    "conversionRate": 0,
    "metaShare": 0.00008256274768824307
  },
  {
    "name": "Phelia, Exuberant Shepherd",
    "conversionRate": 0,
    "metaShare": 0.00008256274768824307
  },
  {
    "name": "Grand Arbiter Augustin IV",
    "conversionRate": 0,
    "metaShare": 0.00016512549537648613
  },
  {
    "name": "Volrath, the Shapestealer",
    "conversionRate": 0,
    "metaShare": 0.00016512549537648613
  },
  {
    "name": "Vannifar, Evolved Enigma",
    "conversionRate": 0,
    "metaShare": 0.00016512549537648613
  },
  {
    "name": "Neera, Wild Mage",
    "conversionRate": 0,
    "metaShare": 0.00008256274768824307
  },
  {
    "name": "Rendmaw, Creaking Nest",
    "conversionRate": 0,
    "metaShare": 0.00016512549537648613
  },
  {
    "name": "Lonis, Genetics Expert",
    "conversionRate": 0,
    "metaShare": 0.00016512549537648613
  },
  {
    "name": "Okaun, Eye of Chaos / Zndrsplt, Eye of Wisdom",
    "conversionRate": 0,
    "metaShare": 0.00016512549537648613
  },
  {
    "name": "Olivia, Opulent Outlaw",
    "conversionRate": 0,
    "metaShare": 0.00008256274768824307
  },
  {
    "name": "Mr. House, President and CEO",
    "conversionRate": 0,
    "metaShare": 0.00016512549537648613
  },
  {
    "name": "Jinnie Fay, Jetmir's Second",
    "conversionRate": 0,
    "metaShare": 0.00016512549537648613
  },
  {
    "name": "Brenard, Ginger Sculptor",
    "conversionRate": 0,
    "metaShare": 0.00016512549537648613
  },
  {
    "name": "Shelob, Child of Ungoliant",
    "conversionRate": 0,
    "metaShare": 0.00016512549537648613
  },
  {
    "name": "Selvala, Explorer Returned",
    "conversionRate": 0,
    "metaShare": 0.00008256274768824307
  },
  {
    "name": "Kardur, Doomscourge",
    "conversionRate": 0,
    "metaShare": 0.00008256274768824307
  },
  {
    "name": "Horde of Notions",
    "conversionRate": 0,
    "metaShare": 0.00016512549537648613
  },
  {
    "name": "Goreclaw, Terror of Qal Sisma",
    "conversionRate": 0,
    "metaShare": 0.00016512549537648613
  },
  {
    "name": "Lord Windgrace",
    "conversionRate": 0,
    "metaShare": 0.00016512549537648613
  },
  {
    "name": "Feather, the Redeemed",
    "conversionRate": 0,
    "metaShare": 0.00016512549537648613
  },
  {
    "name": "Magar of the Magic Strings",
    "conversionRate": 0,
    "metaShare": 0.00016512549537648613
  },
  {
    "name": "Go-Shintai of Life's Origin",
    "conversionRate": 0,
    "metaShare": 0.00008256274768824307
  },
  {
    "name": "Ishai, Ojutai Dragonspeaker / Reyhan, Last of the Abzan",
    "conversionRate": 0,
    "metaShare": 0.00016512549537648613
  },
  {
    "name": "Akiri, Line-Slinger / Francisco, Fowl Marauder",
    "conversionRate": 0,
    "metaShare": 0.00016512549537648613
  },
  {
    "name": "Lagomos, Hand of Hatred",
    "conversionRate": 0,
    "metaShare": 0.00008256274768824307
  },
  {
    "name": "Ikra Shidiqi, the Usurper / Kraum, Ludevic's Opus",
    "conversionRate": 0,
    "metaShare": 0.00016512549537648613
  },
  {
    "name": "Sheoldred, the Apocalypse",
    "conversionRate": 0,
    "metaShare": 0.00016512549537648613
  },
  {
    "name": "Candlekeep Sage / Ganax, Astral Hunter",
    "conversionRate": 0.5,
    "metaShare": 0.00016512549537648613
  },
  {
    "name": "Zurzoth, Chaos Rider",
    "conversionRate": 0,
    "metaShare": 0.00008256274768824307
  },
  {
    "name": "Kiki-Jiki, Mirror Breaker",
    "conversionRate": 0.5,
    "metaShare": 0.00016512549537648613
  },
  {
    "name": "Galazeth Prismari",
    "conversionRate": 0,
    "metaShare": 0.00016512549537648613
  },
  {
    "name": "Rionya, Fire Dancer",
    "conversionRate": 0,
    "metaShare": 0.00016512549537648613
  },
  {
    "name": "Dargo, the Shipwrecker / Ikra Shidiqi, the Usurper",
    "conversionRate": 0,
    "metaShare": 0.00008256274768824307
  },
  {
    "name": "Ziatora, the Incinerator",
    "conversionRate": 0,
    "metaShare": 0.00008256274768824307
  },
  {
    "name": "The Mindskinner",
    "conversionRate": 0,
    "metaShare": 0.00008256274768824307
  },
  {
    "name": "Jeska, Thrice Reborn / Rograkh, Son of Rohgahh",
    "conversionRate": 0,
    "metaShare": 0.00016512549537648613
  },
  {
    "name": "Far Traveler / Volo, Itinerant Scholar",
    "conversionRate": 0,
    "metaShare": 0.00008256274768824307
  },
  {
    "name": "Flamewar, Brash Veteran // Flamewar, Streetwise Operative",
    "conversionRate": 0,
    "metaShare": 0.00016512549537648613
  },
  {
    "name": "K-9, Mark I / The War Doctor",
    "conversionRate": 0.5,
    "metaShare": 0.00016512549537648613
  },
  {
    "name": "Karlov of the Ghost Council",
    "conversionRate": 0,
    "metaShare": 0.00016512549537648613
  },
  {
    "name": "Gishath, Sun's Avatar",
    "conversionRate": 0,
    "metaShare": 0.00016512549537648613
  },
  {
    "name": "Garth One-Eye",
    "conversionRate": 0,
    "metaShare": 0.00008256274768824307
  },
  {
    "name": "Laughing Jasper Flint",
    "conversionRate": 0,
    "metaShare": 0.00016512549537648613
  },
  {
    "name": "Dargo, the Shipwrecker / Malcolm, Keen-Eyed Navigator",
    "conversionRate": 0,
    "metaShare": 0.00016512549537648613
  },
  {
    "name": "Cecily, Haunted Mage / Othelm, Sigardian Outcast",
    "conversionRate": 0,
    "metaShare": 0.00016512549537648613
  },
  {
    "name": "Kydele, Chosen of Kruphix / Tymna the Weaver",
    "conversionRate": 0,
    "metaShare": 0.00016512549537648613
  },
  {
    "name": "Winter, Misanthropic Guide",
    "conversionRate": 0.5,
    "metaShare": 0.00016512549537648613
  },
  {
    "name": "Arcades, the Strategist",
    "conversionRate": 0.5,
    "metaShare": 0.00016512549537648613
  },
  {
    "name": "Amalia Benavides Aguirre",
    "conversionRate": 0,
    "metaShare": 0.00008256274768824307
  },
  {
    "name": "Dargo, the Shipwrecker / Reyhan, Last of the Abzan",
    "conversionRate": 0,
    "metaShare": 0.00016512549537648613
  },
  {
    "name": "Lord of the Nazgûl",
    "conversionRate": 0,
    "metaShare": 0.00016512549537648613
  },
  {
    "name": "Satoru Umezawa",
    "conversionRate": 0,
    "metaShare": 0.00016512549537648613
  },
  {
    "name": "Ashaya, Soul of the Wild",
    "conversionRate": 1,
    "metaShare": 0.00016512549537648613
  },
  {
    "name": "Kykar, Zephyr Awakener",
    "conversionRate": 0,
    "metaShare": 0.00008256274768824307
  },
  {
    "name": "Alela, Artful Provocateur",
    "conversionRate": 0,
    "metaShare": 0.00016512549537648613
  },
  {
    "name": "Falco Spara, Pactweaver",
    "conversionRate": 0,
    "metaShare": 0.00016512549537648613
  },
  {
    "name": "Wilhelt, the Rotcleaver",
    "conversionRate": 0,
    "metaShare": 0.00008256274768824307
  },
  {
    "name": "Kydele, Chosen of Kruphix / Rograkh, Son of Rohgahh",
    "conversionRate": 0,
    "metaShare": 0.00016512549537648613
  },
  {
    "name": "Padeem, Consul of Innovation",
    "conversionRate": 0,
    "metaShare": 0.00016512549537648613
  },
  {
    "name": "Slimefoot, the Stowaway",
    "conversionRate": 0,
    "metaShare": 0.00016512549537648613
  },
  {
    "name": "Kalamax, the Stormsire",
    "conversionRate": 0.5,
    "metaShare": 0.00016512549537648613
  },
  {
    "name": "Krark, the Thumbless / Tymna the Weaver",
    "conversionRate": 1,
    "metaShare": 0.00016512549537648613
  },
  {
    "name": "Jeska, Thrice Reborn / Thrasios, Triton Hero",
    "conversionRate": 0,
    "metaShare": 0.00016512549537648613
  },
  {
    "name": "Agent of the Iron Throne / Jaheira, Friend of the Forest",
    "conversionRate": 0.5,
    "metaShare": 0.00016512549537648613
  },
  {
    "name": "Nissa, Resurgent Animist",
    "conversionRate": 0,
    "metaShare": 0.00008256274768824307
  },
  {
    "name": "Aurelia, the Warleader",
    "conversionRate": 0,
    "metaShare": 0.00016512549537648613
  },
  {
    "name": "Dihada, Binder of Wills / Kinnan, Bonder Prodigy",
    "conversionRate": 0.5,
    "metaShare": 0.00016512549537648613
  },
  {
    "name": "Azusa, Lost but Seeking",
    "conversionRate": 0.5,
    "metaShare": 0.00016512549537648613
  },
  {
    "name": "Hanna, Ship's Navigator",
    "conversionRate": 0,
    "metaShare": 0.00016512549537648613
  },
  {
    "name": "Mishra, Eminent One",
    "conversionRate": 0,
    "metaShare": 0.00016512549537648613
  },
  {
    "name": "Kadena, Slinking Sorcerer",
    "conversionRate": 0,
    "metaShare": 0.00016512549537648613
  },
  {
    "name": "Davros, Dalek Creator",
    "conversionRate": 0,
    "metaShare": 0.00016512549537648613
  },
  {
    "name": "Ixhel, Scion of Atraxa",
    "conversionRate": 0,
    "metaShare": 0.00016512549537648613
  },
  {
    "name": "Breena, the Demagogue",
    "conversionRate": 0,
    "metaShare": 0.00016512549537648613
  },
  {
    "name": "Commodore Guff",
    "conversionRate": 0,
    "metaShare": 0.00008256274768824307
  },
  {
    "name": "Stenn, Paranoid Partisan",
    "conversionRate": 0,
    "metaShare": 0.00016512549537648613
  },
  {
    "name": "Xenagos, God of Revels",
    "conversionRate": 0,
    "metaShare": 0.00008256274768824307
  },
  {
    "name": "The First Sliver",
    "conversionRate": 0,
    "metaShare": 0.00016512549537648613
  },
  {
    "name": "Cecily, Haunted Mage / Sophina, Spearsage Deserter",
    "conversionRate": 1,
    "metaShare": 0.00016512549537648613
  },
  {
    "name": "Dargo, the Shipwrecker / Jeska, Thrice Reborn",
    "conversionRate": 0,
    "metaShare": 0.00016512549537648613
  },
  {
    "name": "Esior, Wardwing Familiar / Tymna the Weaver",
    "conversionRate": 0,
    "metaShare": 0.00016512549537648613
  },
  {
    "name": "Gale, Waterdeep Prodigy / Scion of Halaster",
    "conversionRate": 0,
    "metaShare": 0.00016512549537648613
  },
  {
    "name": "Alaundo the Seer",
    "conversionRate": 0,
    "metaShare": 0
  },
  {
    "name": "Brimaz, Blight of Oreskos",
    "conversionRate": 0,
    "metaShare": 0.00016512549537648613
  },
  {
    "name": "Karlach, Fury of Avernus / Sword Coast Sailor",
    "conversionRate": 0,
    "metaShare": 0.00016512549537648613
  },
  {
    "name": "Avacyn, Angel of Hope",
    "conversionRate": 0.5,
    "metaShare": 0.00016512549537648613
  },
  {
    "name": "Kraum, Ludevic's Opus / Yoshimaru, Ever Faithful",
    "conversionRate": 0,
    "metaShare": 0.00008256274768824307
  },
  {
    "name": "Kodama of the East Tree / Silas Renn, Seeker Adept",
    "conversionRate": 0,
    "metaShare": 0.00008256274768824307
  },
  {
    "name": "Kodama of the East Tree / Kraum, Ludevic's Opus",
    "conversionRate": 1,
    "metaShare": 0.00008256274768824307
  },
  {
    "name": "Kamahl, Heart of Krosa / Tymna the Weaver",
    "conversionRate": 0,
    "metaShare": 0.00008256274768824307
  },
  {
    "name": "Kotori, Pilot Prodigy",
    "conversionRate": 0,
    "metaShare": 0.00008256274768824307
  },
  {
    "name": "Captain N'ghathrod",
    "conversionRate": 0,
    "metaShare": 0.00008256274768824307
  },
  {
    "name": "Lazav, Dimir Mastermind",
    "conversionRate": 0,
    "metaShare": 0.00008256274768824307
  },
  {
    "name": "Zoraline, Cosmos Caller",
    "conversionRate": 0,
    "metaShare": 0.00008256274768824307
  },
  {
    "name": "Skullbriar, the Walking Grave",
    "conversionRate": 0,
    "metaShare": 0
  },
  {
    "name": "Prime Speaker Zegana",
    "conversionRate": 0,
    "metaShare": 0.00008256274768824307
  },
  {
    "name": "Obeka, Brute Chronologist",
    "conversionRate": 0,
    "metaShare": 0.00008256274768824307
  },
  {
    "name": "Tana, the Bloodsower / Tevesh Szat, Doom of Fools",
    "conversionRate": 0,
    "metaShare": 0.00008256274768824307
  },
  {
    "name": "The Red Terror",
    "conversionRate": 0,
    "metaShare": 0.00008256274768824307
  },
  {
    "name": "Sidisi, Brood Tyrant",
    "conversionRate": 1,
    "metaShare": 0.00008256274768824307
  },
  {
    "name": "Saffi Eriksdotter",
    "conversionRate": 0,
    "metaShare": 0.00008256274768824307
  },
  {
    "name": "Soul of Windgrace",
    "conversionRate": 0,
    "metaShare": 0.00008256274768824307
  },
  {
    "name": "Klothys, God of Destiny",
    "conversionRate": 0,
    "metaShare": 0.00008256274768824307
  },
  {
    "name": "Gisa and Geralf",
    "conversionRate": 0,
    "metaShare": 0.00008256274768824307
  },
  {
    "name": "Tetzin, Gnome Champion // The Golden-Gear Colossus",
    "conversionRate": 0,
    "metaShare": 0.00008256274768824307
  },
  {
    "name": "Kraum, Ludevic's Opus / Vial Smasher the Fierce",
    "conversionRate": 0,
    "metaShare": 0.00008256274768824307
  },
  {
    "name": "Ezuri, Claw of Progress",
    "conversionRate": 0,
    "metaShare": 0
  },
  {
    "name": "Ayara, Widow of the Realm // Ayara, Furnace Queen",
    "conversionRate": 0,
    "metaShare": 0
  },
  {
    "name": "Samwise Gamgee",
    "conversionRate": 0,
    "metaShare": 0
  },
  {
    "name": "Arixmethes, Slumbering Isle",
    "conversionRate": 0,
    "metaShare": 0
  },
  {
    "name": "Imotekh the Stormlord",
    "conversionRate": 0,
    "metaShare": 0.00008256274768824307
  },
  {
    "name": "Altaïr Ibn-La'Ahad",
    "conversionRate": 0,
    "metaShare": 0.00008256274768824307
  },
  {
    "name": "Preston, the Vanisher",
    "conversionRate": 0,
    "metaShare": 0
  },
  {
    "name": "Vadrok, Apex of Thunder",
    "conversionRate": 0,
    "metaShare": 0.00008256274768824307
  },
  {
    "name": "Trazyn the Infinite",
    "conversionRate": 0,
    "metaShare": 0.00008256274768824307
  },
  {
    "name": "Rin and Seri, Inseparable",
    "conversionRate": 0,
    "metaShare": 0.00008256274768824307
  },
  {
    "name": "Saheeli, the Sun's Brilliance",
    "conversionRate": 0,
    "metaShare": 0.00008256274768824307
  },
  {
    "name": "Inquisitor Greyfax",
    "conversionRate": 0,
    "metaShare": 0.00008256274768824307
  },
  {
    "name": "Eris, Roar of the Storm",
    "conversionRate": 0,
    "metaShare": 0.00008256274768824307
  },
  {
    "name": "Radha, Heir to Keld",
    "conversionRate": 0,
    "metaShare": 0.00008256274768824307
  },
  {
    "name": "Shadowfax, Lord of Horses",
    "conversionRate": 0,
    "metaShare": 0.00008256274768824307
  },
  {
    "name": "Delney, Streetwise Lookout",
    "conversionRate": 0,
    "metaShare": 0.00008256274768824307
  },
  {
    "name": "Aclazotz, Deepest Betrayal // Temple of the Dead",
    "conversionRate": 1,
    "metaShare": 0.00008256274768824307
  },
  {
    "name": "The Celestial Toymaker",
    "conversionRate": 1,
    "metaShare": 0.00008256274768824307
  },
  {
    "name": "Jeleva, Nephalia's Scourge",
    "conversionRate": 0,
    "metaShare": 0.00008256274768824307
  },
  {
    "name": "Ayara, First of Locthwain",
    "conversionRate": 0,
    "metaShare": 0
  },
  {
    "name": "Rowan Kenrith / Will Kenrith",
    "conversionRate": 0,
    "metaShare": 0.00008256274768824307
  },
  {
    "name": "Clara Oswald / The Third Doctor",
    "conversionRate": 0,
    "metaShare": 0.00008256274768824307
  },
  {
    "name": "Atarka, World Render",
    "conversionRate": 0,
    "metaShare": 0
  },
  {
    "name": "Ryan Sinclair / The War Doctor",
    "conversionRate": 0,
    "metaShare": 0
  },
  {
    "name": "Kasla, the Broken Halo",
    "conversionRate": 0,
    "metaShare": 0.00008256274768824307
  },
  {
    "name": "Niv-Mizzet, the Firemind",
    "conversionRate": 0,
    "metaShare": 0.00008256274768824307
  },
  {
    "name": "Lazav, Familiar Stranger",
    "conversionRate": 0,
    "metaShare": 0.00008256274768824307
  },
  {
    "name": "Alandra, Sky Dreamer",
    "conversionRate": 0,
    "metaShare": 0.00008256274768824307
  },
  {
    "name": "Toby, Beastie Befriender",
    "conversionRate": 1,
    "metaShare": 0.00008256274768824307
  },
  {
    "name": "Abdel Adrian, Gorion's Ward / Agent of the Iron Throne",
    "conversionRate": 0,
    "metaShare": 0
  },
  {
    "name": "Illuna, Apex of Wishes",
    "conversionRate": 0,
    "metaShare": 0
  },
  {
    "name": "Estrid, the Masked",
    "conversionRate": 0,
    "metaShare": 0
  },
  {
    "name": "Kylox, Visionary Inventor",
    "conversionRate": 0,
    "metaShare": 0
  },
  {
    "name": "Roon of the Hidden Realm",
    "conversionRate": 0,
    "metaShare": 0
  },
  {
    "name": "Ishai, Ojutai Dragonspeaker / Kediss, Emberclaw Familiar",
    "conversionRate": 0,
    "metaShare": 0.00008256274768824307
  },
  {
    "name": "Ilharg, the Raze-Boar",
    "conversionRate": 0,
    "metaShare": 0.00008256274768824307
  },
  {
    "name": "Baeloth Barrityl, Entertainer / Noble Heritage",
    "conversionRate": 0,
    "metaShare": 0.00008256274768824307
  },
  {
    "name": "Frodo, Sauron's Bane",
    "conversionRate": 0,
    "metaShare": 0.00008256274768824307
  },
  {
    "name": "Ezuri, Renegade Leader",
    "conversionRate": 0,
    "metaShare": 0
  },
  {
    "name": "Abaddon the Despoiler",
    "conversionRate": 0,
    "metaShare": 0.00008256274768824307
  },
  {
    "name": "Ishai, Ojutai Dragonspeaker / Krark, the Thumbless",
    "conversionRate": 1,
    "metaShare": 0.00008256274768824307
  },
  {
    "name": "Folk Hero / Volo, Itinerant Scholar",
    "conversionRate": 0,
    "metaShare": 0.00008256274768824307
  },
  {
    "name": "Scion of Halaster / Zellix, Sanity Flayer",
    "conversionRate": 0,
    "metaShare": 0.00008256274768824307
  },
  {
    "name": "Zaxara, the Exemplary",
    "conversionRate": 0,
    "metaShare": 0.00008256274768824307
  },
  {
    "name": "Ishai, Ojutai Dragonspeaker / Tymna the Weaver",
    "conversionRate": 0,
    "metaShare": 0.00008256274768824307
  },
  {
    "name": "Carmen, Cruel Skymarcher",
    "conversionRate": 0,
    "metaShare": 0.00008256274768824307
  },
  {
    "name": "Lathliss, Dragon Queen",
    "conversionRate": 0,
    "metaShare": 0.00008256274768824307
  },
  {
    "name": "Kodama of the East Tree / Tevesh Szat, Doom of Fools",
    "conversionRate": 1,
    "metaShare": 0.00008256274768824307
  },
  {
    "name": "Neerdiv, Devious Diver",
    "conversionRate": 0,
    "metaShare": 0.00008256274768824307
  },
  {
    "name": "Merieke Ri Berit",
    "conversionRate": 0,
    "metaShare": 0.00008256274768824307
  },
  {
    "name": "Mirko, Obsessive Theorist",
    "conversionRate": 0,
    "metaShare": 0.00008256274768824307
  },
  {
    "name": "Freyalise, Llanowar's Fury",
    "conversionRate": 0,
    "metaShare": 0.00008256274768824307
  },
  {
    "name": "General Tazri",
    "conversionRate": 0,
    "metaShare": 0.00008256274768824307
  },
  {
    "name": "Kastral, the Windcrested",
    "conversionRate": 0,
    "metaShare": 0.00008256274768824307
  },
  {
    "name": "Francisco, Fowl Marauder / Ludevic, Necro-Alchemist",
    "conversionRate": 0,
    "metaShare": 0.00008256274768824307
  },
  {
    "name": "Kothophed, Soul Hoarder",
    "conversionRate": 0,
    "metaShare": 0.00008256274768824307
  },
  {
    "name": "Akiri, Fearless Voyager",
    "conversionRate": 0,
    "metaShare": 0.00008256274768824307
  },
  {
    "name": "Herigast, Erupting Nullkite",
    "conversionRate": 0,
    "metaShare": 0.00008256274768824307
  },
  {
    "name": "Neyali, Suns' Vanguard",
    "conversionRate": 0,
    "metaShare": 0.00008256274768824307
  },
  {
    "name": "Otharri, Suns' Glory",
    "conversionRate": 0,
    "metaShare": 0.00008256274768824307
  },
  {
    "name": "Emmara, Soul of the Accord",
    "conversionRate": 0,
    "metaShare": 0.00008256274768824307
  },
  {
    "name": "Queen Allenal of Ruadach",
    "conversionRate": 0,
    "metaShare": 0.00008256274768824307
  },
  {
    "name": "Toluz, Clever Conductor",
    "conversionRate": 0,
    "metaShare": 0.00008256274768824307
  },
  {
    "name": "River Song",
    "conversionRate": 0,
    "metaShare": 0.00008256274768824307
  },
  {
    "name": "Yennett, Cryptic Sovereign",
    "conversionRate": 1,
    "metaShare": 0.00008256274768824307
  },
  {
    "name": "Ardenn, Intrepid Archaeologist / Thrasios, Triton Hero",
    "conversionRate": 0,
    "metaShare": 0
  },
  {
    "name": "Nashi, Searcher in the Dark",
    "conversionRate": 0,
    "metaShare": 0.00008256274768824307
  },
  {
    "name": "Urabrask // The Great Work",
    "conversionRate": 0,
    "metaShare": 0.00008256274768824307
  },
  {
    "name": "Wolverine, Best There Is",
    "conversionRate": 0,
    "metaShare": 0.00008256274768824307
  },
  {
    "name": "Ob Nixilis, Captive Kingpin / Shalai and Hallar",
    "conversionRate": 0,
    "metaShare": 0.00008256274768824307
  },
  {
    "name": "Yasharn, Implacable Earth",
    "conversionRate": 0,
    "metaShare": 0.00008256274768824307
  },
  {
    "name": "Karador, Ghost Chieftain",
    "conversionRate": 1,
    "metaShare": 0.00008256274768824307
  },
  {
    "name": "Basim Ibn Ishaq",
    "conversionRate": 0,
    "metaShare": 0.00008256274768824307
  },
  {
    "name": "Duskana, the Rage Mother",
    "conversionRate": 0,
    "metaShare": 0.00008256274768824307
  },
  {
    "name": "Koma, Cosmos Serpent",
    "conversionRate": 0,
    "metaShare": 0.00008256274768824307
  },
  {
    "name": "Pia and Kiran Nalaar",
    "conversionRate": 1,
    "metaShare": 0.00008256274768824307
  },
  {
    "name": "Jon Irenicus, Shattered One",
    "conversionRate": 0,
    "metaShare": 0
  },
  {
    "name": "Malcolm, Keen-Eyed Navigator / Rograkh, Son of Rohgahh",
    "conversionRate": 0,
    "metaShare": 0
  },
  {
    "name": "Thryx, the Sudden Storm",
    "conversionRate": 1,
    "metaShare": 0.00008256274768824307
  },
  {
    "name": "Kediss, Emberclaw Familiar / Reyhan, Last of the Abzan",
    "conversionRate": 0,
    "metaShare": 0.00008256274768824307
  },
  {
    "name": "The Thirteenth Doctor / Yasmin Khan",
    "conversionRate": 0,
    "metaShare": 0
  },
  {
    "name": "Timothar, Baron of Bats",
    "conversionRate": 0,
    "metaShare": 0.00008256274768824307
  },
  {
    "name": "Morophon, the Boundless",
    "conversionRate": 0,
    "metaShare": 0.00008256274768824307
  },
  {
    "name": "Rose Noble",
    "conversionRate": 0,
    "metaShare": 0.00008256274768824307
  },
  {
    "name": "Mabel, Heir to Cragflame",
    "conversionRate": 0,
    "metaShare": 0.00008256274768824307
  },
  {
    "name": "Ajani, Nacatl Pariah // Ajani, Nacatl Avenger",
    "conversionRate": 0,
    "metaShare": 0.00008256274768824307
  },
  {
    "name": "Kangee, Aerie Keeper",
    "conversionRate": 0,
    "metaShare": 0.00008256274768824307
  },
  {
    "name": "Rex, Cyber-Hound",
    "conversionRate": 0,
    "metaShare": 0.00008256274768824307
  },
  {
    "name": "Szarekh, the Silent King",
    "conversionRate": 0,
    "metaShare": 0.00008256274768824307
  },
  {
    "name": "Adrix and Nev, Twincasters",
    "conversionRate": 0,
    "metaShare": 0.00008256274768824307
  },
  {
    "name": "Zedruu the Greathearted",
    "conversionRate": 0,
    "metaShare": 0.00008256274768824307
  },
  {
    "name": "Lathiel, the Bounteous Dawn",
    "conversionRate": 0,
    "metaShare": 0.00008256274768824307
  },
  {
    "name": "Baba Lysaga, Night Witch",
    "conversionRate": 0,
    "metaShare": 0.00008256274768824307
  },
  {
    "name": "Meren of Clan Nel Toth",
    "conversionRate": 0,
    "metaShare": 0.00008256274768824307
  },
  {
    "name": "Inquisitor Eisenhorn",
    "conversionRate": 0,
    "metaShare": 0.00008256274768824307
  },
  {
    "name": "Solphim, Mayhem Dominus",
    "conversionRate": 0,
    "metaShare": 0
  },
  {
    "name": "Ikra Shidiqi, the Usurper / Rograkh, Son of Rohgahh",
    "conversionRate": 1,
    "metaShare": 0.00008256274768824307
  },
  {
    "name": "Hansk, Slayer Zealot",
    "conversionRate": 0,
    "metaShare": 0.00008256274768824307
  },
  {
    "name": "Vorinclex // The Grand Evolution",
    "conversionRate": 0,
    "metaShare": 0.00008256274768824307
  },
  {
    "name": "Gev, Scaled Scorch",
    "conversionRate": 0,
    "metaShare": 0.00008256274768824307
  },
  {
    "name": "Jeska, Thrice Reborn / Tevesh Szat, Doom of Fools",
    "conversionRate": 0,
    "metaShare": 0.00008256274768824307
  },
  {
    "name": "Agent of the Iron Throne / Gut, True Soul Zealot",
    "conversionRate": 0,
    "metaShare": 0.00008256274768824307
  },
  {
    "name": "Elesh Norn, Mother of Machines",
    "conversionRate": 0,
    "metaShare": 0.00008256274768824307
  },
  {
    "name": "Grismold, the Dreadsower",
    "conversionRate": 0,
    "metaShare": 0.00008256274768824307
  },
  {
    "name": "Be'lakor, the Dark Master",
    "conversionRate": 0,
    "metaShare": 0.00008256274768824307
  },
  {
    "name": "Bell Borca, Spectral Sergeant",
    "conversionRate": 0,
    "metaShare": 0.00008256274768824307
  },
  {
    "name": "Verazol, the Split Current",
    "conversionRate": 0,
    "metaShare": 0.00008256274768824307
  },
  {
    "name": "Zethi, Arcane Blademaster",
    "conversionRate": 0,
    "metaShare": 0.00008256274768824307
  },
  {
    "name": "Trelasarra, Moon Dancer",
    "conversionRate": 0,
    "metaShare": 0.00008256274768824307
  },
  {
    "name": "Titania, Protector of Argoth",
    "conversionRate": 0,
    "metaShare": 0.00008256274768824307
  },
  {
    "name": "Jan Jansen, Chaos Crafter",
    "conversionRate": 1,
    "metaShare": 0.00008256274768824307
  },
  {
    "name": "Kwain, Itinerant Meddler",
    "conversionRate": 1,
    "metaShare": 0.00008256274768824307
  },
  {
    "name": "Hazezon, Shaper of Sand",
    "conversionRate": 1,
    "metaShare": 0.00008256274768824307
  },
  {
    "name": "Thrun, Breaker of Silence",
    "conversionRate": 0,
    "metaShare": 0
  },
  {
    "name": "Sauron, Lord of the Rings",
    "conversionRate": 0,
    "metaShare": 0
  },
  {
    "name": "Rulik Mons, Warren Chief",
    "conversionRate": 0,
    "metaShare": 0
  },
  {
    "name": "Grenzo, Dungeon Warden",
    "conversionRate": 0,
    "metaShare": 0.00008256274768824307
  },
  {
    "name": "Nethroi, Apex of Death",
    "conversionRate": 1,
    "metaShare": 0.00008256274768824307
  },
  {
    "name": "Malcolm, Alluring Scoundrel",
    "conversionRate": 0,
    "metaShare": 0.00008256274768824307
  },
  {
    "name": "Uro, Titan of Nature's Wrath",
    "conversionRate": 0,
    "metaShare": 0.00008256274768824307
  },
  {
    "name": "Mogis, God of Slaughter",
    "conversionRate": 0,
    "metaShare": 0.00008256274768824307
  },
  {
    "name": "Hinata, Dawn-Crowned",
    "conversionRate": 0,
    "metaShare": 0.00008256274768824307
  },
  {
    "name": "Blex, Vexing Pest // Search for Blex",
    "conversionRate": 0,
    "metaShare": 0.00008256274768824307
  },
  {
    "name": "Thrasios, Triton Hero / Toggo, Goblin Weaponsmith",
    "conversionRate": 0,
    "metaShare": 0.00008256274768824307
  },
  {
    "name": "Katilda, Dawnhart Prime",
    "conversionRate": 1,
    "metaShare": 0.00008256274768824307
  },
  {
    "name": "Ikra Shidiqi, the Usurper / Jeska, Thrice Reborn",
    "conversionRate": 0,
    "metaShare": 0.00008256274768824307
  },
  {
    "name": "Ardenn, Intrepid Archaeologist / Silas Renn, Seeker Adept",
    "conversionRate": 1,
    "metaShare": 0.00008256274768824307
  },
  {
    "name": "Nadier, Agent of the Duskenel / Thrasios, Triton Hero",
    "conversionRate": 0,
    "metaShare": 0.00008256274768824307
  },
  {
    "name": "Rose, Cutthroat Raider",
    "conversionRate": 0,
    "metaShare": 0.00008256274768824307
  },
  {
    "name": "Koll, the Forgemaster",
    "conversionRate": 1,
    "metaShare": 0.00008256274768824307
  },
  {
    "name": "Pir, Imaginative Rascal / Toothy, Imaginary Friend",
    "conversionRate": 0,
    "metaShare": 0.00008256274768824307
  },
  {
    "name": "Dr. Madison Li",
    "conversionRate": 0,
    "metaShare": 0.00008256274768824307
  },
  {
    "name": "Volo, Guide to Monsters",
    "conversionRate": 0,
    "metaShare": 0.00008256274768824307
  },
  {
    "name": "Reyhan, Last of the Abzan / Yoshimaru, Ever Faithful",
    "conversionRate": 0,
    "metaShare": 0.00008256274768824307
  },
  {
    "name": "Sophina, Spearsage Deserter / Wernog, Rider's Chaplain",
    "conversionRate": 0,
    "metaShare": 0.00008256274768824307
  },
  {
    "name": "Hallar, the Firefletcher",
    "conversionRate": 0,
    "metaShare": 0.00008256274768824307
  },
  {
    "name": "Rodolf Duskbringer",
    "conversionRate": 0,
    "metaShare": 0.00008256274768824307
  },
  {
    "name": "Yargle and Multani",
    "conversionRate": 0,
    "metaShare": 0
  },
  {
    "name": "Queen Marchesa",
    "conversionRate": 0,
    "metaShare": 0.00008256274768824307
  },
  {
    "name": "K-9, Mark I / The Fugitive Doctor",
    "conversionRate": 0,
    "metaShare": 0.00008256274768824307
  },
  {
    "name": "Eladamri, Korvecdal",
    "conversionRate": 0,
    "metaShare": 0.00008256274768824307
  },
  {
    "name": "Ishai, Ojutai Dragonspeaker / Thrasios, Triton Hero",
    "conversionRate": 0,
    "metaShare": 0.00008256274768824307
  },
  {
    "name": "Judith, the Scourge Diva",
    "conversionRate": 1,
    "metaShare": 0.00008256274768824307
  },
  {
    "name": "Cait, Cage Brawler",
    "conversionRate": 0,
    "metaShare": 0.00008256274768824307
  },
  {
    "name": "O-Kagachi, Vengeful Kami",
    "conversionRate": 0,
    "metaShare": 0.00008256274768824307
  },
  {
    "name": "Venser, Corpse Puppet",
    "conversionRate": 0,
    "metaShare": 0.00008256274768824307
  },
  {
    "name": "Karn, Silver Golem",
    "conversionRate": 1,
    "metaShare": 0.00008256274768824307
  },
  {
    "name": "Ikra Shidiqi, the Usurper / Tymna the Weaver",
    "conversionRate": 0,
    "metaShare": 0.00008256274768824307
  },
  {
    "name": "Dargo, the Shipwrecker / Keskit, the Flesh Sculptor",
    "conversionRate": 0,
    "metaShare": 0.00008256274768824307
  },
  {
    "name": "Soundwave, Sonic Spy // Soundwave, Superior Captain",
    "conversionRate": 0,
    "metaShare": 0.00008256274768824307
  },
  {
    "name": "Rigo, Streetwise Mentor",
    "conversionRate": 0,
    "metaShare": 0.00008256274768824307
  },
  {
    "name": "Imoti, Celebrant of Bounty",
    "conversionRate": 1,
    "metaShare": 0.00008256274768824307
  },
  {
    "name": "Tatyova, Steward of Tides",
    "conversionRate": 0,
    "metaShare": 0.00008256274768824307
  },
  {
    "name": "Loot, Exuberant Explorer",
    "conversionRate": 0,
    "metaShare": 0.00008256274768824307
  },
  {
    "name": "Ryan Sinclair / The Thirteenth Doctor",
    "conversionRate": 0,
    "metaShare": 0.00008256274768824307
  },
  {
    "name": "Norin the Wary",
    "conversionRate": 0,
    "metaShare": 0.00008256274768824307
  },
  {
    "name": "Gilanra, Caller of Wirewood / Vial Smasher the Fierce",
    "conversionRate": 0,
    "metaShare": 0.00008256274768824307
  },
  {
    "name": "Neheb, the Eternal",
    "conversionRate": 0,
    "metaShare": 0.00008256274768824307
  },
  {
    "name": "Balthor the Defiled",
    "conversionRate": 0,
    "metaShare": 0.00008256274768824307
  },
  {
    "name": "Agatha of the Vile Cauldron",
    "conversionRate": 0,
    "metaShare": 0.00008256274768824307
  },
  {
    "name": "Goro-Goro and Satoru",
    "conversionRate": 0,
    "metaShare": 0.00008256274768824307
  },
  {
    "name": "Tawnos, Solemn Survivor",
    "conversionRate": 0,
    "metaShare": 0.00008256274768824307
  },
  {
    "name": "Ishai, Ojutai Dragonspeaker / Vial Smasher the Fierce",
    "conversionRate": 0,
    "metaShare": 0.00008256274768824307
  },
  {
    "name": "Tinybones, Trinket Thief",
    "conversionRate": 0,
    "metaShare": 0.00008256274768824307
  },
  {
    "name": "Neheb, the Worthy",
    "conversionRate": 0,
    "metaShare": 0.00008256274768824307
  },
  {
    "name": "Jenson Carthalion, Druid Exile",
    "conversionRate": 1,
    "metaShare": 0.00008256274768824307
  },
  {
    "name": "Kodama of the East Tree / Thrasios, Triton Hero",
    "conversionRate": 0,
    "metaShare": 0.00008256274768824307
  },
  {
    "name": "Nath of the Gilt-Leaf",
    "conversionRate": 0,
    "metaShare": 0.00008256274768824307
  },
  {
    "name": "Chandler",
    "conversionRate": 1,
    "metaShare": 0.00008256274768824307
  },
  {
    "name": "Elas il-Kor, Sadistic Pilgrim",
    "conversionRate": 1,
    "metaShare": 0.00008256274768824307
  },
  {
    "name": "Yarok, the Desecrated",
    "conversionRate": 0,
    "metaShare": 0.00008256274768824307
  },
  {
    "name": "Ghalta, Primal Hunger",
    "conversionRate": 0,
    "metaShare": 0.00008256274768824307
  },
  {
    "name": "Seton, Krosan Protector",
    "conversionRate": 1,
    "metaShare": 0.00008256274768824307
  },
  {
    "name": "Kaervek, the Punisher",
    "conversionRate": 0,
    "metaShare": 0.00008256274768824307
  },
  {
    "name": "Svyelun of Sea and Sky",
    "conversionRate": 0,
    "metaShare": 0.00008256274768824307
  },
  {
    "name": "Uril, the Miststalker",
    "conversionRate": 0,
    "metaShare": 0.00008256274768824307
  },
  {
    "name": "Kathril, Aspect Warper",
    "conversionRate": 0,
    "metaShare": 0.00008256274768824307
  },
  {
    "name": "Eivor, Wolf-Kissed",
    "conversionRate": 0,
    "metaShare": 0.00008256274768824307
  },
  {
    "name": "Yusri, Fortune's Flame",
    "conversionRate": 0,
    "metaShare": 0.00008256274768824307
  },
  {
    "name": "Demonlord Belzenlok",
    "conversionRate": 0,
    "metaShare": 0
  },
  {
    "name": "Danny Pink",
    "conversionRate": 0,
    "metaShare": 0.00008256274768824307
  },
  {
    "name": "Ghave, Guru of Spores",
    "conversionRate": 0,
    "metaShare": 0.00008256274768824307
  },
  {
    "name": "Myrel, Shield of Argive",
    "conversionRate": 0,
    "metaShare": 0.00008256274768824307
  },
  {
    "name": "Lurrus of the Dream-Den",
    "conversionRate": 0,
    "metaShare": 0.00008256274768824307
  },
  {
    "name": "Gisa, the Hellraiser",
    "conversionRate": 0,
    "metaShare": 0.00008256274768824307
  },
  {
    "name": "Sarah Jane Smith / The Sixth Doctor",
    "conversionRate": 0,
    "metaShare": 0.00008256274768824307
  },
  {
    "name": "Dargo, the Shipwrecker / Rakdos, the Muscle",
    "conversionRate": 0,
    "metaShare": 0.00008256274768824307
  },
  {
    "name": "Kaalia of the Vast / Thrasios, Triton Hero",
    "conversionRate": 0,
    "metaShare": 0.00008256274768824307
  },
  {
    "name": "Samut, Voice of Dissent / Sisay, Weatherlight Captain",
    "conversionRate": 0,
    "metaShare": 0.00008256274768824307
  },
  {
    "name": "Kydele, Chosen of Kruphix / Vilis, Broker of Blood",
    "conversionRate": 0,
    "metaShare": 0.00008256274768824307
  },
  {
    "name": "Imskir Iron-Eater / Tetzin, Gnome Champion // The Golden-Gear Colossus",
    "conversionRate": 0,
    "metaShare": 0.00008256274768824307
  },
  {
    "name": "Calix, Guided by Fate / Ellivere of the Wild Court",
    "conversionRate": 0,
    "metaShare": 0.00008256274768824307
  },
  {
    "name": "Ghyrson Starn, Kelermorph / Ob Nixilis, Captive Kingpin",
    "conversionRate": 0,
    "metaShare": 0.00008256274768824307
  },
  {
    "name": "Etali, Primal Conqueror // Etali, Primal Sickness / The Master of Keys",
    "conversionRate": 0,
    "metaShare": 0.00008256274768824307
  },
  {
    "name": "Etali, Primal Conqueror // Etali, Primal Sickness / Kinnan, Bonder Prodigy",
    "conversionRate": 0,
    "metaShare": 0.00008256274768824307
  },
  {
    "name": "Plagon, Lord of the Beach / Slicer, Hired Muscle // Slicer, High-Speed Antagonist",
    "conversionRate": 1,
    "metaShare": 0.00008256274768824307
  },
  {
    "name": "Nardole, Resourceful Cyborg / Tayam, Luminous Enigma",
    "conversionRate": 1,
    "metaShare": 0.00008256274768824307
  },
  {
    "name": "Acererak the Archlich / Kinnan, Bonder Prodigy",
    "conversionRate": 1,
    "metaShare": 0.00008256274768824307
  },
  {
    "name": "Arcum Dagsson / Urtet, Remnant of Memnarch",
    "conversionRate": 1,
    "metaShare": 0.00008256274768824307
  },
  {
    "name": "Sisay, Weatherlight Captain / Zur the Enchanter",
    "conversionRate": 1,
    "metaShare": 0.00008256274768824307
  },
  {
    "name": "Kinnan, Bonder Prodigy / Lotho, Corrupt Shirriff",
    "conversionRate": 1,
    "metaShare": 0.00008256274768824307
  },
  {
    "name": "Lotho, Corrupt Shirriff / Urza, Lord High Artificer",
    "conversionRate": 1,
    "metaShare": 0.00008256274768824307
  },
  {
    "name": "Dihada, Binder of Wills / Malcolm, Keen-Eyed Navigator",
    "conversionRate": 1,
    "metaShare": 0.00008256274768824307
  },
  {
    "name": "Derevi, Empyrial Tactician / Najeela, the Blade-Blossom",
    "conversionRate": 1,
    "metaShare": 0.00008256274768824307
  },
  {
    "name": "Chatterfang, Squirrel General / Kykar, Wind's Fury",
    "conversionRate": 1,
    "metaShare": 0.00008256274768824307
  },
  {
    "name": "Kamahl, Heart of Krosa / Kodama of the East Tree",
    "conversionRate": 0,
    "metaShare": 0.00008256274768824307
  },
  {
    "name": "The Beamtown Bullies",
    "conversionRate": 0,
    "metaShare": 0
  },
  {
    "name": "Urza, Lord Protector",
    "conversionRate": 0,
    "metaShare": 0
  },
  {
    "name": "Ob Nixilis of the Black Oath",
    "conversionRate": 0,
    "metaShare": 0.00008256274768824307
  },
  {
    "name": "Kitt Kanto, Mayhem Diva",
    "conversionRate": 0,
    "metaShare": 0.00008256274768824307
  },
  {
    "name": "Bright-Palm, Soul Awakener",
    "conversionRate": 0,
    "metaShare": 0.00008256274768824307
  },
  {
    "name": "Saheeli, Radiant Creator",
    "conversionRate": 0,
    "metaShare": 0.00008256274768824307
  },
  {
    "name": "The Dalek Emperor",
    "conversionRate": 0,
    "metaShare": 0.00008256274768824307
  },
  {
    "name": "Ruhan of the Fomori",
    "conversionRate": 0,
    "metaShare": 0.00008256274768824307
  },
  {
    "name": "Red Death, Shipwrecker",
    "conversionRate": 0,
    "metaShare": 0.00008256274768824307
  },
  {
    "name": "Gonti, Night Minister",
    "conversionRate": 0,
    "metaShare": 0.00008256274768824307
  },
  {
    "name": "Phelddagrif",
    "conversionRate": 0,
    "metaShare": 0.00008256274768824307
  },
  {
    "name": "Clara Oswald / The Thirteenth Doctor",
    "conversionRate": 0,
    "metaShare": 0
  },
  {
    "name": "Obuun, Mul Daya Ancestor",
    "conversionRate": 0,
    "metaShare": 0
  },
  {
    "name": "Kethis, the Hidden Hand",
    "conversionRate": 0,
    "metaShare": 0.00008256274768824307
  },
  {
    "name": "Calamity, Galloping Inferno",
    "conversionRate": 0,
    "metaShare": 0.00008256274768824307
  },
  {
    "name": "Jadzi, Oracle of Arcavios // Journey to the Oracle",
    "conversionRate": 0,
    "metaShare": 0.00008256274768824307
  },
  {
    "name": "Seizan, Perverter of Truth",
    "conversionRate": 0,
    "metaShare": 0.00008256274768824307
  },
  {
    "name": "Curie, Emergent Intelligence",
    "conversionRate": 1,
    "metaShare": 0.00008256274768824307
  },
  {
    "name": "Greensleeves, Maro-Sorcerer",
    "conversionRate": 0,
    "metaShare": 0.00008256274768824307
  },
  {
    "name": "Ghen, Arcanum Weaver",
    "conversionRate": 0,
    "metaShare": 0
  },
  {
    "name": "Surtr, Fiery Jötun",
    "conversionRate": 0,
    "metaShare": 0.00008256274768824307
  },
  {
    "name": "Varolz, the Scar-Striped",
    "conversionRate": 1,
    "metaShare": 0.00008256274768824307
  },
  {
    "name": "Daxos the Returned",
    "conversionRate": 0,
    "metaShare": 0.00008256274768824307
  },
  {
    "name": "Bilbo, Birthday Celebrant",
    "conversionRate": 0,
    "metaShare": 0.00008256274768824307
  },
  {
    "name": "Henrika Domnathi // Henrika, Infernal Seer",
    "conversionRate": 0,
    "metaShare": 0.00008256274768824307
  },
  {
    "name": "The Ancient One",
    "conversionRate": 0,
    "metaShare": 0.00008256274768824307
  },
  {
    "name": "Cadira, Caller of the Small",
    "conversionRate": 0,
    "metaShare": 0.00008256274768824307
  },
  {
    "name": "Sorin of House Markov // Sorin, Ravenous Neonate",
    "conversionRate": 0,
    "metaShare": 0.00008256274768824307
  },
  {
    "name": "Greymond, Avacyn's Stalwart",
    "conversionRate": 1,
    "metaShare": 0.00008256274768824307
  }
]}
